Workbook

Sheet LEEME
B1: FODA / DAFO / SWOT de viabilidad exportadora – Pymes industriales de Misiones
B2: Cuestionario basado en el Modelo Canvas | Investigación de Mercados Internacionales – Tecnicatura Superior en Comercio Exterior | Versión 2026
B3: Desarrollado y Preparado por el Prof. Hugo César Galván. ™
B4: 1. Para qué sirve
B5: Convierte las respuestas de una entrevista a una pyme industrial en un FODA cuantificado (fortalezas, debilidades, oportunidades y amenazas), en una matriz de cruces FO/FA/DO/DA y en un primer diagnóstico de viabilidad para exportar.
B7: 2. Cómo se usa (6 pasos)
B8: 1) Copie este archivo por cada empresa y complete los datos de la empresa en la hoja VIABILIDAD (celdas amarillas).
B9: 2) Realice la entrevista con la hoja GUIA_ENTREVISTA: cada factor tiene una pregunta abierta y la evidencia a solicitar.
B10: 3) En FormularioFODA marque con una "x" UNA opción de SITUACIÓN y UNA de IMPACTO por fila (solo se completan las celdas amarillas). La columna Control indica OK / pendiente / revisar.
B11: 4) Use la columna Mensaje para dejar el fundamento o el dato que respalda la respuesta.
B12: 5) Revise los resultados en ResumenFODA (gráficos), PART1 FODA (listas de F, D, O, A), PART2 FODA (cruces) y MATRIZ FODA (burbujas).
B13: 6) Lea la conclusión en VIABILIDAD. Las hojas CalculosFoda, CalculoFoda-1, VariablesFoda y Rango son el motor de cálculo: no se editan.
... B21: 4. Ejemplo de carga (una fila del formulario)
B22: Variable | C22: No corresp. | D22: Muy Desfav. | E22: Desfavorable | F22: Favorable | G22: Muy Favorable | H22: Muy insignif | I22: Insignificante | J22: Significante | K22: Muy Signific.
B23: IB3 - Certificaciones y normas de producto | E23: x | J23: x
B24: Lectura del ejemplo: la empresa tiene certificaciones incompletas (Desfavorable), pero son muy importantes para exportar (Significante). Resultado: debilidad de peso alto que aparecerá en PART1 FODA y bajará el puntaje del bloque Propuesta de valor.
B26: 5. Mapa de hojas
B27: FormularioFODA | C27: Cuestionario (entrada de datos). Único lugar donde se carga información.
B28: GUIA_ENTREVISTA | C28: Preguntas abiertas y evidencias para la entrevista (NUEVA).
B29: MATRIZ FODA | C29: Cuenta los cruces F-O, F-A, D-O, D-A por área y grafica el peso de cada cuadrante.
B30: PART2 FODA | C30: Matriz cruzada: cada factor interno frente a las variables externas de las que depende. Es dinámica (antes era manual).
B31: PART1 FODA | C31: Lista de fortalezas/debilidades (internas) y oportunidades/amenazas (externas).
B32: ResumenFODA | C32: Situación ideal, peor y actual por área, con gráficos.
B33: VIABILIDAD | C33: Puntajes por área, índices global interno y externo, conclusión de viabilidad y estrategia dominante (NUEVA).
B34: CalculoFoda-1 | C34: Motor: conteos por categoría, peso relativo y situación ponderada -1/+1.
B35: VariablesFoda | C35: Mapa de dependencias entre factores internos y variables externas.
B36: CalculosFoda | C36: Motor: puntos 0-10 por factor y ponderación por impacto; semáforo.
B37: Rango | C37: Tabla de conversión de % de logro a puntos.
B39: 6. Mapa Canvas -> áreas del cuestionario
B40: Bloque Canvas | C40: Código | D40: Ítems | E40: Pregunta que responde
B41: 1. Segmentos de clientes | C41: IA | D41: 5 | E41: ¿Para quién creamos valor y a qué mercados podría llegar?
B42: 2. Propuesta de valor | C42: IB | D42: 7 | E42: ¿Qué ofrecemos que el mercado externo valore y pueda comprar?
B43: 3. Canales | C43: IC | D43: 5 | E43: ¿Cómo llegamos al cliente del exterior y cómo le entregamos el producto?
B44: 4. Relación con clientes | C44: ID | D44: 5 | E44: ¿Cómo captamos, atendemos y retenemos al cliente externo?
B45: 5. Fuentes de ingresos | C45: IE | D45: 6 | E45: ¿Cuánto y cómo cobramos, y qué margen deja exportar?
B46: 6. Recursos clave | C46: IF | D46: 8 | E46: ¿Con qué recursos productivos, humanos y financieros contamos para exportar?
B47: 7. Actividades clave | C47: IG | D47: 9 | E47: ¿Qué procesos debemos dominar para producir, cumplir y entregar con calidad?
B48: 8. Socios clave | C48: IH | D48: 6 | E48: ¿Quiénes nos ayudan a producir, vender y cumplir en el exterior?
B49: 9. Estructura de costos | C49: II | D49: 6 | E49: ¿Cuánto cuesta producir y exportar, y a partir de qué escala es rentable?
B50: 10. Transversal: gestión y compromiso exportador | C50: IJ | D50: 7 | E50: ¿La dirección está preparada y decidida a sostener un proceso exportador?
B51: Total: 64 factores internos y 46 externos.
B54: 7. Empresas que no exportan y evalúan iniciar (perfil aspirante, MERCOSUR)
B55: Este cuestionario sirve para dos perfiles de empresa: la que ya exporta (o exportó alguna vez) y la que nunca exportó pero está dispuesta a evaluar una inversión en exportación. En VIABILIDAD hay un campo 'Perfil de la empresa' para dejarlo asentado; las preguntas y la forma de puntuar NO cambian entre perfiles, pero sí cambia CÓMO se interpretan.
B56: ¿Quién responde? Regla general: el empresario responde todo lo que es diagnóstico de su realidad actual, aunque hoy solo aplique al mercado interno (cartera de clientes, idiomas del personal, uso de contratos, ventas, márgenes). El estudiante completa lo que exige investigación externa (países y segmentos candidatos, canales de exportación, normativa, logística, mercado destino) y lo valida con el empresario en la entrevista. La hoja GUIA_ENTREVISTA tiene una columna 'Quién responde' por cada bloque.
B57: ¿Cómo marcar la SITUACIÓN sin actividad exportadora? No se usa 'No corresponde' solo porque la empresa nunca exportó: eso vaciaría justo la parte del diagnóstico que más importa. Se marca la Situación según el grado de preparación o capacidad ACTUAL de la empresa frente a ese factor, usando la mejor evidencia disponible (casi siempre doméstica). Si la empresa nunca pensó en países destino, eso es información real y se marca Muy Desfavorable, no 'No corresponde'.
B58: ¿Cómo marcar el IMPACTO sin actividad exportadora? El Impacto no mide lo que la empresa siente hoy (que sería siempre bajo, si no exporta) sino qué tan determinante sería ese factor para que un FUTURO proyecto de exportación tenga éxito. Se evalúa igual, exporte o no la empresa actualmente.
B59: Con esta lectura, es normal y correcto que una empresa sin experiencia exportadora obtenga varias Debilidades de peso alto en Segmentos de clientes, Canales y Fuentes de ingresos: son las brechas reales que hay que cerrar antes de exportar, no un defecto del formulario.
B60: La hoja GUIA_ENTREVISTA agrega, para cada uno de los 21 factores donde la lectura no es obvia (Segmentos de clientes, Canales, Relación con clientes y Fuentes de ingresos), una nota puntual en la columna 'Si la empresa NO exporta: cómo leer la Situación'. Para el resto de los factores (y para todo el ámbito externo) la lectura es la misma, exporte o no la empresa.
B62: 8. Controles y notas
B63: Correcciones respecto del archivo original (detalle en el archivo .md): se corrigió la escala de situación de CalculoFoda-1 (Desfavorable sumaba en positivo y Muy favorable no sumaba), rangos de suma con errores, división por cero en planillas vacías, conteo de la matriz (COUNTA contaba celdas vacías) y el área Proveedores, que no aparecía en el resumen.
B64: Los umbrales de viabilidad (VIABILIDAD!C11 y C12) son supuestos de diseño editables. El diagnóstico es preliminar: no reemplaza un plan de exportación completo.

Sheet FormularioFODA
B1: FORMULARIO DE RELEVAMIENTO – Marque con una "x" UNA opción de SITUACIÓN y UNA de IMPACTO por cada fila (celdas amarillas)
D2: SITUACIÓN | J2: IMPACTO
B3: Variables | D3: No corresp. | E3: Muy Desfav. | F3: Desfavorable | G3: Favorable | H3: Muy Favorable | J3: Muy insignif | K3: Insignificante | L3: Significante | M3: Muy Signific. | O3: Mensaje / observación de la empresa | P3: Control
B4: MODELO DE NEGOCIO (CANVAS) – LADO CLIENTE Y VALOR
B5: Segmentos de Clientes
B6: 1 - Definición de segmentos y países objetivo. Se considera favorable si la empresa tiene definidos, con datos, los tipos de cliente externo (importador, distribuidor, industria, retail) y los 2 o 3 países prioritarios. | C6: =+CalculosFoda!AD3 -> 6.9999 | G6: x | L6: x | P6: =IF(AND(COUNTIF(D6:H6,"x")=1,COUNTIF(J6:M6,"x")=1),"OK",IF(AND(COUNTIF(D6:H6,"x")=0,COUNTIF(J6:M6,"x")=0),"pendiente","revisar")) -> OK
B7: 2 - Conocimiento de las necesidades del cliente externo. Se considera favorable si la empresa conoce qué exige el comprador del exterior (calidad, volumen, plazos, formatos, certificaciones) y no solo lo que pide el mercado interno. | C7: =+CalculosFoda!AD4 -> 6.9999 | G7: x | M7: x | P7: =IF(AND(COUNTIF(D7:H7,"x")=1,COUNTIF(J7:M7,"x")=1),"OK",IF(AND(COUNTIF(D7:H7,"x")=0,COUNTIF(J7:M7,"x")=0),"pendiente","revisar")) -> OK
B8: 3 - Concentración de clientes. Se considera favorable si ningún cliente supera el 40% de las ventas y la cartera está balanceada entre mercado interno y potencial externo. | C8: =+CalculosFoda!AD5 -> 6.9999 | G8: x | L8: x | P8: =IF(AND(COUNTIF(D8:H8,"x")=1,COUNTIF(J8:M8,"x")=1),"OK",IF(AND(COUNTIF(D8:H8,"x")=0,COUNTIF(J8:M8,"x")=0),"pendiente","revisar")) -> OK
B9: 4 - Experiencia previa exportadora. Se considera favorable si la empresa ya exportó (aunque sea de forma esporádica o indirecta, vía un tercero) o cotizó operaciones al exterior. | C9: =+CalculosFoda!AD6 -> 4.9999 | F9: x | L9: x | P9: =IF(AND(COUNTIF(D9:H9,"x")=1,COUNTIF(J9:M9,"x")=1),"OK",IF(AND(COUNTIF(D9:H9,"x")=0,COUNTIF(J9:M9,"x")=0),"pendiente","revisar")) -> OK
B10: 5 - Acceso a información de mercados. Se considera favorable si la empresa consulta fuentes sistemáticas (estadísticas de comercio, cámaras, agencias de promoción, consulados) para elegir destinos y precios. | C10: =+CalculosFoda!AD7 -> 4.9999 | F10: x | M10: x | P10: =IF(AND(COUNTIF(D10:H10,"x")=1,COUNTIF(J10:M10,"x")=1),"OK",IF(AND(COUNTIF(D10:H10,"x")=0,COUNTIF(J10:M10,"x")=0),"pendiente","revisar")) -> OK
B12: Propuesta de Valor
B13: 1 - Diferenciación del producto. Se considera favorable si el producto tiene atributos diferenciales (calidad, diseño, especie o variedad, proceso, origen) que el cliente externo reconoce y valora. | C13: =+CalculosFoda!AD10 -> 4.9999 | F13: x | M13: x | P13: =IF(AND(COUNTIF(D13:H13,"x")=1,COUNTIF(J13:M13,"x")=1),"OK",IF(AND(COUNTIF(D13:H13,"x")=0,COUNTIF(J13:M13,"x")=0),"pendiente","revisar")) -> OK
B14: 2 - Adecuación a requisitos del mercado destino. Se considera favorable si el producto (norma técnica, envase, etiquetado, idioma, unidades) está adaptado como mínimo al 80% de lo que exige el destino elegido. | C14: =+CalculosFoda!AD11 -> 6.9999 | G14: x | L14: x | P14: =IF(AND(COUNTIF(D14:H14,"x")=1,COUNTIF(J14:M14,"x")=1),"OK",IF(AND(COUNTIF(D14:H14,"x")=0,COUNTIF(J14:M14,"x")=0),"pendiente","revisar")) -> OK
B15: 3 - Certificaciones y normas de producto. Se considera favorable si la empresa posee, o tiene en trámite, las certificaciones que exige el destino (p. ej., FSC/PEFC, orgánico, BPM/HACCP, normas técnicas). | C15: =+CalculosFoda!AD12 -> 4.9999 | F15: x | L15: x | P15: =IF(AND(COUNTIF(D15:H15,"x")=1,COUNTIF(J15:M15,"x")=1),"OK",IF(AND(COUNTIF(D15:H15,"x")=0,COUNTIF(J15:M15,"x")=0),"pendiente","revisar")) -> OK
B16: 4 - Competitividad de precio internacional. Se considera favorable si el precio FOB estimado resulta competitivo frente al de los principales oferentes en el mercado destino. | C16: =+CalculosFoda!AD13 -> 9.99985 | H16: x | L16: x | P16: =IF(AND(COUNTIF(D16:H16,"x")=1,COUNTIF(J16:M16,"x")=1),"OK",IF(AND(COUNTIF(D16:H16,"x")=0,COUNTIF(J16:M16,"x")=0),"pendiente","revisar")) -> OK
B17: 5 - Marca, presentación y material comercial. Se considera favorable si la marca está registrada y existen catálogo, ficha técnica y sitio web al menos en inglés o portugués. | C17: =+CalculosFoda!AD14 -> 9.99985 | H17: x | M17: x | P17: =IF(AND(COUNTIF(D17:H17,"x")=1,COUNTIF(J17:M17,"x")=1),"OK",IF(AND(COUNTIF(D17:H17,"x")=0,COUNTIF(J17:M17,"x")=0),"pendiente","revisar")) -> OK
B18: 6 - Origen e identidad regional. Se considera favorable si el origen misionero/NEA (territorio, tradición, sello o indicación geográfica) agrega valor reconocible al producto. | C18: =+CalculosFoda!AD15 -> 4.9999 | F18: x | L18: x | P18: =IF(AND(COUNTIF(D18:H18,"x")=1,COUNTIF(J18:M18,"x")=1),"OK",IF(AND(COUNTIF(D18:H18,"x")=0,COUNTIF(J18:M18,"x")=0),"pendiente","revisar")) -> OK
B19: 7 - Amplitud de línea y desarrollo de nuevos productos. Se considera favorable si existe una línea suficiente para exportar y una política de adaptar o desarrollar productos para nuevos mercados. | C19: =+CalculosFoda!AD16 -> 2.9999 | E19: x | L19: x | P19: =IF(AND(COUNTIF(D19:H19,"x")=1,COUNTIF(J19:M19,"x")=1),"OK",IF(AND(COUNTIF(D19:H19,"x")=0,COUNTIF(J19:M19,"x")=0),"pendiente","revisar")) -> OK
B21: Canales
B22: 1 - Canales de comercialización externos. Se considera favorable si están identificados y evaluados los canales posibles (importador, distribuidor, agente, trading, venta directa, plataformas) y se sabe cuál usar por segmento. | C22: =+CalculosFoda!AD19 -> 6.9999 | G22: x | M22: x | P22: =IF(AND(COUNTIF(D22:H22,"x")=1,COUNTIF(J22:M22,"x")=1),"OK",IF(AND(COUNTIF(D22:H22,"x")=0,COUNTIF(J22:M22,"x")=0),"pendiente","revisar")) -> OK
B23: 2 - Presencia digital y venta online. Se considera favorable si la empresa tiene sitio web activo y perfiles comerciales, y puede responder consultas del exterior en tiempo razonable. | C23: =+CalculosFoda!AD20 -> 2.9999 | E23: x | M23: x | P23: =IF(AND(COUNTIF(D23:H23,"x")=1,COUNTIF(J23:M23,"x")=1),"OK",IF(AND(COUNTIF(D23:H23,"x")=0,COUNTIF(J23:M23,"x")=0),"pendiente","revisar")) -> OK
B24: 3 - Promoción internacional. Se considera favorable si participa o planea participar en ferias, rondas de negocios, misiones comerciales o campañas de promoción. | C24: =+CalculosFoda!AD21 -> 2.9999 | E24: x | L24: x | P24: =IF(AND(COUNTIF(D24:H24,"x")=1,COUNTIF(J24:M24,"x")=1),"OK",IF(AND(COUNTIF(D24:H24,"x")=0,COUNTIF(J24:M24,"x")=0),"pendiente","revisar")) -> OK
B25: 4 - Logística y embalaje de exportación. Se considera favorable si la empresa sabe cotizar bajo Incoterms, dispone de embalaje apto para transporte internacional y conoce opciones de flete y seguro. | C25: =+CalculosFoda!AD22 -> 2.9999 | E25: x | L25: x | P25: =IF(AND(COUNTIF(D25:H25,"x")=1,COUNTIF(J25:M25,"x")=1),"OK",IF(AND(COUNTIF(D25:H25,"x")=0,COUNTIF(J25:M25,"x")=0),"pendiente","revisar")) -> OK
B26: 5 - Gestión documental y aduanera. Se considera favorable si la empresa conoce o tiene acceso a la documentación de exportación (factura, packing list, certificado de origen, permiso de embarque) y a un despachante. | C26: =+CalculosFoda!AD23 -> 2.9999 | E26: x | M26: x | P26: =IF(AND(COUNTIF(D26:H26,"x")=1,COUNTIF(J26:M26,"x")=1),"OK",IF(AND(COUNTIF(D26:H26,"x")=0,COUNTIF(J26:M26,"x")=0),"pendiente","revisar")) -> OK
B28: Relación con Clientes
B29: 1 - Atención y postventa internacional. Se considera favorable si hay un responsable y un procedimiento para atender consultas, pedidos y postventa del exterior con tiempos de respuesta definidos. | C29: =+CalculosFoda!AD26 -> 6.9999 | G29: x | M29: x | P29: =IF(AND(COUNTIF(D29:H29,"x")=1,COUNTIF(J29:M29,"x")=1),"OK",IF(AND(COUNTIF(D29:H29,"x")=0,COUNTIF(J29:M29,"x")=0),"pendiente","revisar")) -> OK
B30: 2 - Comunicación en idioma extranjero. Se considera favorable si el personal comercial puede negociar y redactar en inglés y/o portugués, o cuenta con traductor o intérprete. | C30: =+CalculosFoda!AD27 -> 4.9999 | F30: x | M30: x | P30: =IF(AND(COUNTIF(D30:H30,"x")=1,COUNTIF(J30:M30,"x")=1),"OK",IF(AND(COUNTIF(D30:H30,"x")=0,COUNTIF(J30:M30,"x")=0),"pendiente","revisar")) -> OK
B31: 3 - Contratos y condiciones con compradores. Se considera favorable si se usan contratos o condiciones de venta escritas (precio, Incoterm, forma de pago, resolución de conflictos) y se evalúa la solvencia del comprador. | C31: =+CalculosFoda!AD28 -> 4.9999 | F31: x | L31: x | P31: =IF(AND(COUNTIF(D31:H31,"x")=1,COUNTIF(J31:M31,"x")=1),"OK",IF(AND(COUNTIF(D31:H31,"x")=0,COUNTIF(J31:M31,"x")=0),"pendiente","revisar")) -> OK
B32: 4 - Fidelización y recompra. Se considera favorable si existen mecanismos para sostener la relación (seguimiento, acuerdos de abastecimiento, condiciones especiales) y hay recompra. | C32: =+CalculosFoda!AD29 -> 2.9999 | E32: x | L32: x | P32: =IF(AND(COUNTIF(D32:H32,"x")=1,COUNTIF(J32:M32,"x")=1),"OK",IF(AND(COUNTIF(D32:H32,"x")=0,COUNTIF(J32:M32,"x")=0),"pendiente","revisar")) -> OK
B33: 5 - Gestión de reclamos y devoluciones. Se considera favorable si hay un procedimiento para reclamos, cambios y devoluciones que resuelve los casos sin pérdida relevante del cliente. | C33: =+CalculosFoda!AD30 -> 4.9999 | F33: x | L33: x | P33: =IF(AND(COUNTIF(D33:H33,"x")=1,COUNTIF(J33:M33,"x")=1),"OK",IF(AND(COUNTIF(D33:H33,"x")=0,COUNTIF(J33:M33,"x")=0),"pendiente","revisar")) -> OK
B35: Fuentes de Ingresos
B36: 1 - Evolución de ventas. Se considera favorable si las ventas crecen o se sostienen en términos reales y hay renovación de clientes y nuevos requerimientos. | C36: =+CalculosFoda!AD33 -> 6.9999 | G36: x | M36: x | P36: =IF(AND(COUNTIF(D36:H36,"x")=1,COUNTIF(J36:M36,"x")=1),"OK",IF(AND(COUNTIF(D36:H36,"x")=0,COUNTIF(J36:M36,"x")=0),"pendiente","revisar")) -> OK
B37: 2 - Fijación de precio de exportación. Se considera favorable si existe un método sistematizado para construir el precio (costo, margen, flete, seguro, comisiones, impuestos) según el Incoterm. | C37: =+CalculosFoda!AD34 -> 6.9999 | G37: x | L37: x | P37: =IF(AND(COUNTIF(D37:H37,"x")=1,COUNTIF(J37:M37,"x")=1),"OK",IF(AND(COUNTIF(D37:H37,"x")=0,COUNTIF(J37:M37,"x")=0),"pendiente","revisar")) -> OK
B38: 3 - Margen del producto exportable. Se considera favorable si el margen de contribución soporta descuentos, comisiones, fletes y derechos de exportación sin quedar por debajo del margen del mercado interno. | C38: =+CalculosFoda!AD35 -> 0.99995 | D38: x | L38: x | P38: =IF(AND(COUNTIF(D38:H38,"x")=1,COUNTIF(J38:M38,"x")=1),"OK",IF(AND(COUNTIF(D38:H38,"x")=0,COUNTIF(J38:M38,"x")=0),"pendiente","revisar")) -> OK
B39: 4 - Medios y condiciones de cobro. Se considera favorable si la empresa conoce y puede operar instrumentos de cobro internacional (transferencia anticipada, cobranza documentaria, carta de crédito, seguro de crédito). | C39: =+CalculosFoda!AD36 -> 6.9999 | G39: x | L39: x | P39: =IF(AND(COUNTIF(D39:H39,"x")=1,COUNTIF(J39:M39,"x")=1),"OK",IF(AND(COUNTIF(D39:H39,"x")=0,COUNTIF(J39:M39,"x")=0),"pendiente","revisar")) -> OK
B40: 5 - Diversificación de ingresos. Se considera favorable si los ingresos no dependen de un único producto, cliente o mercado y hay margen para sumar mercados externos. | C40: =+CalculosFoda!AD37 -> 6.9999 | G40: x | L40: x | P40: =IF(AND(COUNTIF(D40:H40,"x")=1,COUNTIF(J40:M40,"x")=1),"OK",IF(AND(COUNTIF(D40:H40,"x")=0,COUNTIF(J40:M40,"x")=0),"pendiente","revisar")) -> OK
B41: 6 - Resistencia a variaciones cambiarias. Se considera favorable si la empresa puede absorber cambios en el tipo de cambio o cubrirse (precios en dólares, costos dolarizados, coberturas). | C41: =+CalculosFoda!AD38 -> 4.9999 | F41: x | J41: x | P41: =IF(AND(COUNTIF(D41:H41,"x")=1,COUNTIF(J41:M41,"x")=1),"OK",IF(AND(COUNTIF(D41:H41,"x")=0,COUNTIF(J41:M41,"x")=0),"pendiente","revisar")) -> OK
B43: MODELO DE NEGOCIO (CANVAS) – LADO OPERACIÓN Y RECURSOS
B44: Recursos Clave
B45: 1 - Capacidad instalada y ociosa. Se considera favorable si existe capacidad ociosa o ampliable de al menos 30% sin comprometer la atención del mercado actual. | C45: =+CalculosFoda!AD41 -> 6.9999 | G45: x | J45: x | P45: =IF(AND(COUNTIF(D45:H45,"x")=1,COUNTIF(J45:M45,"x")=1),"OK",IF(AND(COUNTIF(D45:H45,"x")=0,COUNTIF(J45:M45,"x")=0),"pendiente","revisar")) -> OK
B46: 2 - Estado y tecnología de la maquinaria. Se considera favorable si equipos, líneas y tecnología permiten cumplir volúmenes y estándares de calidad del exterior. | C46: =+CalculosFoda!AD42 -> 6.9999 | G46: x | M46: x | P46: =IF(AND(COUNTIF(D46:H46,"x")=1,COUNTIF(J46:M46,"x")=1),"OK",IF(AND(COUNTIF(D46:H46,"x")=0,COUNTIF(J46:M46,"x")=0),"pendiente","revisar")) -> OK
B47: 3 - Personal calificado. Se considera favorable si la dotación operativa está calificada para los procesos críticos y la rotación es baja. | C47: =+CalculosFoda!AD43 -> 6.9999 | G47: x | L47: x | P47: =IF(AND(COUNTIF(D47:H47,"x")=1,COUNTIF(J47:M47,"x")=1),"OK",IF(AND(COUNTIF(D47:H47,"x")=0,COUNTIF(J47:M47,"x")=0),"pendiente","revisar")) -> OK
B48: 4 - Formación continua y capacitación en comercio exterior. Se considera favorable si existen planes de capacitación en producción, calidad y comercio exterior, y al menos una persona con formación específica. | C48: =+CalculosFoda!AD44 -> 4.9999 | F48: x | L48: x | P48: =IF(AND(COUNTIF(D48:H48,"x")=1,COUNTIF(J48:M48,"x")=1),"OK",IF(AND(COUNTIF(D48:H48,"x")=0,COUNTIF(J48:M48,"x")=0),"pendiente","revisar")) -> OK
B49: 5 - Capital de trabajo y capacidad financiera. Se considera favorable si la empresa puede financiar el ciclo exportador (producción, flete, plazo de cobro) sin comprometer su operación. | C49: =+CalculosFoda!AD45 -> 4.9999 | F49: x | M49: x | P49: =IF(AND(COUNTIF(D49:H49,"x")=1,COUNTIF(J49:M49,"x")=1),"OK",IF(AND(COUNTIF(D49:H49,"x")=0,COUNTIF(J49:M49,"x")=0),"pendiente","revisar")) -> OK
B50: 6 - Sistemas de información y gestión. Se considera favorable si hay sistemas (gestión, facturación, stock) que permiten emitir facturas de exportación y controlar pedidos. | C50: =+CalculosFoda!AD46 -> 6.9999 | G50: x | L50: x | P50: =IF(AND(COUNTIF(D50:H50,"x")=1,COUNTIF(J50:M50,"x")=1),"OK",IF(AND(COUNTIF(D50:H50,"x")=0,COUNTIF(J50:M50,"x")=0),"pendiente","revisar")) -> OK
B51: 7 - Infraestructura, depósitos y conservación. Se considera favorable si predios y depósitos aseguran conservación, orden y espacio para consolidar mercadería de exportación. | C51: =+CalculosFoda!AD47 -> 4.9999 | F51: x | M51: x | P51: =IF(AND(COUNTIF(D51:H51,"x")=1,COUNTIF(J51:M51,"x")=1),"OK",IF(AND(COUNTIF(D51:H51,"x")=0,COUNTIF(J51:M51,"x")=0),"pendiente","revisar")) -> OK
B52: 8 - Habilitaciones y registros oficiales. Se considera favorable si cuenta con las habilitaciones y registros de establecimiento y producto exigidos (p. ej., SENASA, INAL/ANMAT, registros de exportador ante ARCA). | C52: =+CalculosFoda!AD48 -> 6.9999 | G52: x | M52: x | P52: =IF(AND(COUNTIF(D52:H52,"x")=1,COUNTIF(J52:M52,"x")=1),"OK",IF(AND(COUNTIF(D52:H52,"x")=0,COUNTIF(J52:M52,"x")=0),"pendiente","revisar")) -> OK
B54: Actividades Clave
B55: 1 - Descripción técnica y estandarización. Se considera favorable si procesos y productos están descriptos (manuales, especificaciones, diagramas de flujo) y son reproducibles lote a lote. | C55: =+CalculosFoda!AD51 -> 4.9999 | F55: x | M55: x | P55: =IF(AND(COUNTIF(D55:H55,"x")=1,COUNTIF(J55:M55,"x")=1),"OK",IF(AND(COUNTIF(D55:H55,"x")=0,COUNTIF(J55:M55,"x")=0),"pendiente","revisar")) -> OK
B56: 2 - Mantenimiento y continuidad operativa. Se considera favorable si hay mantenimiento preventivo sistematizado y no existen paradas críticas recurrentes (fallas, cortes de energía, faltantes). | C56: =+CalculosFoda!AD52 -> 6.9999 | G56: x | L56: x | P56: =IF(AND(COUNTIF(D56:H56,"x")=1,COUNTIF(J56:M56,"x")=1),"OK",IF(AND(COUNTIF(D56:H56,"x")=0,COUNTIF(J56:M56,"x")=0),"pendiente","revisar")) -> OK
B57: 3 - Planificación de producción y abastecimiento. Se considera favorable si se planifica producción y aprovisionamiento con antelación y pueden comprometerse volúmenes y fechas de entrega. | C57: =+CalculosFoda!AD53 -> 6.9999 | G57: x | L57: x | P57: =IF(AND(COUNTIF(D57:H57,"x")=1,COUNTIF(J57:M57,"x")=1),"OK",IF(AND(COUNTIF(D57:H57,"x")=0,COUNTIF(J57:M57,"x")=0),"pendiente","revisar")) -> OK
B58: 4 - Gestión de calidad. Se considera favorable si existe un sistema de calidad (controles, muestreo, normas como ISO 9001, BPM/HACCP) que asegura estándares constantes. | C58: =+CalculosFoda!AD54 -> 4.9999 | F58: x | M58: x | P58: =IF(AND(COUNTIF(D58:H58,"x")=1,COUNTIF(J58:M58,"x")=1),"OK",IF(AND(COUNTIF(D58:H58,"x")=0,COUNTIF(J58:M58,"x")=0),"pendiente","revisar")) -> OK
B59: 5 - Trazabilidad y control de stock. Se considera favorable si el producto se identifica por lote y origen y el inventario está sistematizado y actualizado. | C59: =+CalculosFoda!AD55 -> 4.9999 | F59: x | L59: x | P59: =IF(AND(COUNTIF(D59:H59,"x")=1,COUNTIF(J59:M59,"x")=1),"OK",IF(AND(COUNTIF(D59:H59,"x")=0,COUNTIF(J59:M59,"x")=0),"pendiente","revisar")) -> OK
B60: 6 - Cumplimiento de plazos de entrega. Se considera favorable si la empresa cumple sus plazos comprometidos (al menos 90% de los pedidos en fecha y completos). | C60: =+CalculosFoda!AD56 -> 6.9999 | G60: x | J60: x | P60: =IF(AND(COUNTIF(D60:H60,"x")=1,COUNTIF(J60:M60,"x")=1),"OK",IF(AND(COUNTIF(D60:H60,"x")=0,COUNTIF(J60:M60,"x")=0),"pendiente","revisar")) -> OK
B61: 7 - Mejora de procesos e I+D. Se considera favorable si existen planes de mejora de productividad y de desarrollo de procesos con inversión asignada. | C61: =+CalculosFoda!AD57 -> 4.9999 | F61: x | L61: x | P61: =IF(AND(COUNTIF(D61:H61,"x")=1,COUNTIF(J61:M61,"x")=1),"OK",IF(AND(COUNTIF(D61:H61,"x")=0,COUNTIF(J61:M61,"x")=0),"pendiente","revisar")) -> OK
B62: 8 - Gestión ambiental y de residuos. Se considera favorable si la planta cumple la normativa ambiental, gestiona residuos y efluentes y puede demostrarlo. | C62: =+CalculosFoda!AD58 -> 4.9999 | F62: x | L62: x | P62: =IF(AND(COUNTIF(D62:H62,"x")=1,COUNTIF(J62:M62,"x")=1),"OK",IF(AND(COUNTIF(D62:H62,"x")=0,COUNTIF(J62:M62,"x")=0),"pendiente","revisar")) -> OK
B63: 9 - Seguridad e higiene laboral. Se considera favorable si el ambiente de trabajo es seguro, limpio y organizado, con programa de seguridad e higiene y cobertura de ART. | C63: =+CalculosFoda!AD59 -> 2.9999 | E63: x | L63: x | P63: =IF(AND(COUNTIF(D63:H63,"x")=1,COUNTIF(J63:M63,"x")=1),"OK",IF(AND(COUNTIF(D63:H63,"x")=0,COUNTIF(J63:M63,"x")=0),"pendiente","revisar")) -> OK
B65: Socios Clave
B66: 1 - Proveedores estratégicos. Se considera favorable si la estrategia de compras permite negociar precio y plazo con proveedores confiables, sin depender de uno solo. | C66: =+CalculosFoda!AD62 -> 6.9999 | G66: x | L66: x | P66: =IF(AND(COUNTIF(D66:H66,"x")=1,COUNTIF(J66:M66,"x")=1),"OK",IF(AND(COUNTIF(D66:H66,"x")=0,COUNTIF(J66:M66,"x")=0),"pendiente","revisar")) -> OK
B67: 2 - Alianzas comerciales. Se considera favorable si existen o son posibles acuerdos con agentes, distribuidores, otras pymes (consorcios de exportación) o traders para llegar al exterior. | C67: =+CalculosFoda!AD63 -> 2.9999 | E67: x | M67: x | P67: =IF(AND(COUNTIF(D67:H67,"x")=1,COUNTIF(J67:M67,"x")=1),"OK",IF(AND(COUNTIF(D67:H67,"x")=0,COUNTIF(J67:M67,"x")=0),"pendiente","revisar")) -> OK
B68: 3 - Socios logísticos y aduaneros. Se considera favorable si trabaja o puede trabajar con despachante, forwarder y transportistas confiables. | C68: =+CalculosFoda!AD64 -> 4.9999 | F68: x | L68: x | P68: =IF(AND(COUNTIF(D68:H68,"x")=1,COUNTIF(J68:M68,"x")=1),"OK",IF(AND(COUNTIF(D68:H68,"x")=0,COUNTIF(J68:M68,"x")=0),"pendiente","revisar")) -> OK
B69: 4 - Apoyo institucional. Se considera favorable si la empresa se vincula con cámaras, agencias de promoción, organismos provinciales o nacionales, INTA y universidades, y accede a programas de apoyo. | C69: =+CalculosFoda!AD65 -> 9.99985 | H69: x | L69: x | P69: =IF(AND(COUNTIF(D69:H69,"x")=1,COUNTIF(J69:M69,"x")=1),"OK",IF(AND(COUNTIF(D69:H69,"x")=0,COUNTIF(J69:M69,"x")=0),"pendiente","revisar")) -> OK
B70: 5 - Socios financieros y de seguros. Se considera favorable si mantiene relación con bancos y aseguradoras con productos de comercio exterior (prefinanciación, seguros de carga y de crédito). | C70: =+CalculosFoda!AD66 -> 2.9999 | E70: x | M70: x | P70: =IF(AND(COUNTIF(D70:H70,"x")=1,COUNTIF(J70:M70,"x")=1),"OK",IF(AND(COUNTIF(D70:H70,"x")=0,COUNTIF(J70:M70,"x")=0),"pendiente","revisar")) -> OK
B71: 6 - Tercerización y subcontratación. Se considera favorable si los servicios tercerizados mantienen equilibrio entre conocimiento, costo y control de calidad, sin crear dependencia crítica. | C71: =+CalculosFoda!AD67 -> 9.99985 | H71: x | M71: x | P71: =IF(AND(COUNTIF(D71:H71,"x")=1,COUNTIF(J71:M71,"x")=1),"OK",IF(AND(COUNTIF(D71:H71,"x")=0,COUNTIF(J71:M71,"x")=0),"pendiente","revisar")) -> OK
B73: Estructura de Costos
B74: 1 - Costos fijos. Se considera favorable si los costos fijos no aumentaron más del 15% real en el último año y su peso es manejable frente al volumen. | C74: =+CalculosFoda!AD70 -> 6.9999 | G74: x | L74: x | P74: =IF(AND(COUNTIF(D74:H74,"x")=1,COUNTIF(J74:M74,"x")=1),"OK",IF(AND(COUNTIF(D74:H74,"x")=0,COUNTIF(J74:M74,"x")=0),"pendiente","revisar")) -> OK
B75: 2 - Punto de equilibrio y escala mínima exportable. Se considera favorable si se conoce el punto de equilibrio y el volumen mínimo por embarque que resulta rentable. | C75: =+CalculosFoda!AD71 -> 0.99995 | D75: x | M75: x | P75: =IF(AND(COUNTIF(D75:H75,"x")=1,COUNTIF(J75:M75,"x")=1),"OK",IF(AND(COUNTIF(D75:H75,"x")=0,COUNTIF(J75:M75,"x")=0),"pendiente","revisar")) -> OK
B76: 3 - Sistema de costos de exportación. Se considera favorable si existe un sistema que distribuye costos por producto e incorpora los de comercio exterior (flete, seguro, tasas, comisiones). | C76: =+CalculosFoda!AD72 -> 6.9999 | G76: x | M76: x | P76: =IF(AND(COUNTIF(D76:H76,"x")=1,COUNTIF(J76:M76,"x")=1),"OK",IF(AND(COUNTIF(D76:H76,"x")=0,COUNTIF(J76:M76,"x")=0),"pendiente","revisar")) -> OK
B77: 4 - Costo de materias primas. Se considera favorable si el costo y la disponibilidad de la materia prima son estables, sin fuertes variaciones estacionales o de precio. | C77: =+CalculosFoda!AD73 -> 4.9999 | F77: x | L77: x | P77: =IF(AND(COUNTIF(D77:H77,"x")=1,COUNTIF(J77:M77,"x")=1),"OK",IF(AND(COUNTIF(D77:H77,"x")=0,COUNTIF(J77:M77,"x")=0),"pendiente","revisar")) -> OK
B78: 5 - Costos logísticos y de comercio exterior. Se considera favorable si los costos de flete, embalaje, despacho y seguros representan un porcentaje del precio compatible con la competitividad. | C78: =+CalculosFoda!AD74 -> 4.9999 | F78: x | L78: x | P78: =IF(AND(COUNTIF(D78:H78,"x")=1,COUNTIF(J78:M78,"x")=1),"OK",IF(AND(COUNTIF(D78:H78,"x")=0,COUNTIF(J78:M78,"x")=0),"pendiente","revisar")) -> OK
B79: 6 - Endeudamiento. Se considera favorable si el endeudamiento es menor al activo corriente y no compromete la capacidad de invertir. | C79: =+CalculosFoda!AD75 -> 9.99985 | H79: x | L79: x | P79: =IF(AND(COUNTIF(D79:H79,"x")=1,COUNTIF(J79:M79,"x")=1),"OK",IF(AND(COUNTIF(D79:H79,"x")=0,COUNTIF(J79:M79,"x")=0),"pendiente","revisar")) -> OK
B81: GESTIÓN Y COMPROMISO EXPORTADOR (BLOQUE TRANSVERSAL)
B82: Gestión y Compromiso Exportador
B83: 1 - Estrategia y objetivos de largo plazo. Se considera favorable si hay una estrategia con visión a más de tres años y objetivos de exportación medibles. | C83: =+CalculosFoda!AD78 -> 4.9999 | F83: x | L83: x | P83: =IF(AND(COUNTIF(D83:H83,"x")=1,COUNTIF(J83:M83,"x")=1),"OK",IF(AND(COUNTIF(D83:H83,"x")=0,COUNTIF(J83:M83,"x")=0),"pendiente","revisar")) -> OK
B84: 2 - Compromiso de la dirección. Se considera favorable si la dirección asigna tiempo, presupuesto y decisiones concretas a la exportación (no solo interés declarativo). | C84: =+CalculosFoda!AD79 -> 2.9999 | E84: x | L84: x | P84: =IF(AND(COUNTIF(D84:H84,"x")=1,COUNTIF(J84:M84,"x")=1),"OK",IF(AND(COUNTIF(D84:H84,"x")=0,COUNTIF(J84:M84,"x")=0),"pendiente","revisar")) -> OK
B85: 3 - Estructura y responsable de comercio exterior. Se considera favorable si existe una persona o equipo responsable de exportar y la estructura y funciones son acordes al volumen de actividad. | C85: =+CalculosFoda!AD80 -> 2.9999 | E85: x | M85: x | P85: =IF(AND(COUNTIF(D85:H85,"x")=1,COUNTIF(J85:M85,"x")=1),"OK",IF(AND(COUNTIF(D85:H85,"x")=0,COUNTIF(J85:M85,"x")=0),"pendiente","revisar")) -> OK
B86: 4 - Conocimiento de la competencia internacional. Se considera favorable si se conocen competidores, capacidades, precios y estrategias en los mercados elegidos. | C86: =+CalculosFoda!AD81 -> 6.9999 | G86: x | L86: x | P86: =IF(AND(COUNTIF(D86:H86,"x")=1,COUNTIF(J86:M86,"x")=1),"OK",IF(AND(COUNTIF(D86:H86,"x")=0,COUNTIF(J86:M86,"x")=0),"pendiente","revisar")) -> OK
B87: 5 - Capacidad de anticipación a los cambios. Se considera favorable si existen planes de contingencia y análisis de escenarios ante cambios de normas, tipo de cambio y demanda. | C87: =+CalculosFoda!AD82 -> 4.9999 | F87: x | L87: x | P87: =IF(AND(COUNTIF(D87:H87,"x")=1,COUNTIF(J87:M87,"x")=1),"OK",IF(AND(COUNTIF(D87:H87,"x")=0,COUNTIF(J87:M87,"x")=0),"pendiente","revisar")) -> OK
B88: 6 - Cultura empresarial y estilo de dirección. Se considera favorable si la cultura es abierta al cambio, hay compromiso compartido con una visión y los mandos medios participan en las decisiones. | C88: =+CalculosFoda!AD83 -> 2.9999 | E88: x | M88: x | P88: =IF(AND(COUNTIF(D88:H88,"x")=1,COUNTIF(J88:M88,"x")=1),"OK",IF(AND(COUNTIF(D88:H88,"x")=0,COUNTIF(J88:M88,"x")=0),"pendiente","revisar")) -> OK
B89: 7 - Herramientas de planificación y control. Se considera favorable si existen presupuesto, tableros de indicadores y herramientas de planificación sistematizadas en cada proceso. | C89: =+CalculosFoda!AD84 -> 0.99995 | D89: x | L89: x | P89: =IF(AND(COUNTIF(D89:H89,"x")=1,COUNTIF(J89:M89,"x")=1),"OK",IF(AND(COUNTIF(D89:H89,"x")=0,COUNTIF(J89:M89,"x")=0),"pendiente","revisar")) -> OK
B91: AMBITO EXTERNO
B92: Ámbito Político/Legal y Regulatorio
B93: 1 - Política de comercio exterior. Se considera favorable si las reglas de exportación (autorizaciones, cupos, restricciones) son previsibles y estables y no obstaculizan al sector. | C93: =+CalculosFoda!AD87 -> 4.9999 | F93: x | L93: x | P93: =IF(AND(COUNTIF(D93:H93,"x")=1,COUNTIF(J93:M93,"x")=1),"OK",IF(AND(COUNTIF(D93:H93,"x")=0,COUNTIF(J93:M93,"x")=0),"pendiente","revisar")) -> OK
B94: 2 - Acuerdos comerciales y preferencias arancelarias. Se considera favorable si existen acuerdos vigentes (Mercosur, ALADI u otros) que otorgan preferencias arancelarias al producto en los destinos elegidos. | C94: =+CalculosFoda!AD88 -> 4.9999 | F94: x | M94: x | P94: =IF(AND(COUNTIF(D94:H94,"x")=1,COUNTIF(J94:M94,"x")=1),"OK",IF(AND(COUNTIF(D94:H94,"x")=0,COUNTIF(J94:M94,"x")=0),"pendiente","revisar")) -> OK
B95: 3 - Barreras arancelarias y técnicas del destino. Se considera favorable si aranceles, cupos, licencias y reglamentos técnicos del destino no impiden ni encarecen de manera significativa el ingreso del producto. | C95: =+CalculosFoda!AD89 -> 6.9999 | G95: x | M95: x | P95: =IF(AND(COUNTIF(D95:H95,"x")=1,COUNTIF(J95:M95,"x")=1),"OK",IF(AND(COUNTIF(D95:H95,"x")=0,COUNTIF(J95:M95,"x")=0),"pendiente","revisar")) -> OK
B96: 4 - Trámites y aduana. Se considera favorable si los trámites y controles (permisos, certificados de origen, despacho) son ágiles, digitalizados y de costo razonable. | C96: =+CalculosFoda!AD90 -> 2.9999 | E96: x | K96: x | P96: =IF(AND(COUNTIF(D96:H96,"x")=1,COUNTIF(J96:M96,"x")=1),"OK",IF(AND(COUNTIF(D96:H96,"x")=0,COUNTIF(J96:M96,"x")=0),"pendiente","revisar")) -> OK
B97: 5 - Promoción y fomento a exportadores. Se considera favorable si existen programas nacionales, provinciales o sectoriales (asistencia técnica, ferias, financiamiento, reintegros) accesibles para pymes. | C97: =+CalculosFoda!AD91 -> 4.9999 | F97: x | M97: x | P97: =IF(AND(COUNTIF(D97:H97,"x")=1,COUNTIF(J97:M97,"x")=1),"OK",IF(AND(COUNTIF(D97:H97,"x")=0,COUNTIF(J97:M97,"x")=0),"pendiente","revisar")) -> OK
B98: 6 - Propiedad intelectual y seguridad jurídica. Se considera favorable si es posible proteger marcas y patentes y hacer cumplir contratos internacionales (Incoterms, arbitraje) con reglas claras. | C98: =+CalculosFoda!AD92 -> 6.9999 | G98: x | M98: x | P98: =IF(AND(COUNTIF(D98:H98,"x")=1,COUNTIF(J98:M98,"x")=1),"OK",IF(AND(COUNTIF(D98:H98,"x")=0,COUNTIF(J98:M98,"x")=0),"pendiente","revisar")) -> OK
B100: Ámbito Económico/Financiero/Cambiario
B101: 1 - Crecimiento económico y ciclo. Se considera favorable si la economía argentina y las de los destinos crecen o se estabilizan, sin ciclos que reduzcan la demanda de manera abrupta. | C101: =+CalculosFoda!AD95 -> 2.9999 | E101: x | M101: x | P101: =IF(AND(COUNTIF(D101:H101,"x")=1,COUNTIF(J101:M101,"x")=1),"OK",IF(AND(COUNTIF(D101:H101,"x")=0,COUNTIF(J101:M101,"x")=0),"pendiente","revisar")) -> OK
B102: 2 - Crecimiento sectorial del rubro. Se considera favorable si el rubro (forestoindustrial, yerbatero, alimentos, etc.) crece en los destinos objetivo y permite mayores transacciones. | C102: =+CalculosFoda!AD96 -> 4.9999 | F102: x | M102: x | P102: =IF(AND(COUNTIF(D102:H102,"x")=1,COUNTIF(J102:M102,"x")=1),"OK",IF(AND(COUNTIF(D102:H102,"x")=0,COUNTIF(J102:M102,"x")=0),"pendiente","revisar")) -> OK
B103: 3 - Tipo de cambio y competitividad. Se considera favorable si el esquema cambiario es previsible y sostiene precios competitivos en dólares. | C103: =+CalculosFoda!AD97 -> 4.9999 | F103: x | L103: x | P103: =IF(AND(COUNTIF(D103:H103,"x")=1,COUNTIF(J103:M103,"x")=1),"OK",IF(AND(COUNTIF(D103:H103,"x")=0,COUNTIF(J103:M103,"x")=0),"pendiente","revisar")) -> OK
B104: 4 - Inflación y costos internos. Se considera favorable si la inflación no desbalancea salarios e insumos ni erosiona el margen frente al precio internacional. | C104: =+CalculosFoda!AD98 -> 0.99995 | D104: x | L104: x | P104: =IF(AND(COUNTIF(D104:H104,"x")=1,COUNTIF(J104:M104,"x")=1),"OK",IF(AND(COUNTIF(D104:H104,"x")=0,COUNTIF(J104:M104,"x")=0),"pendiente","revisar")) -> OK
B105: 5 - Financiamiento y crédito para exportar. Se considera favorable si hay líneas de crédito y prefinanciación de exportaciones a tasas y plazos que permitan financiar el ciclo exportador. | C105: =+CalculosFoda!AD99 -> 4.9999 | F105: x | K105: x | P105: =IF(AND(COUNTIF(D105:H105,"x")=1,COUNTIF(J105:M105,"x")=1),"OK",IF(AND(COUNTIF(D105:H105,"x")=0,COUNTIF(J105:M105,"x")=0),"pendiente","revisar")) -> OK
B106: 6 - Cobros y acceso a divisas. Se considera favorable si las normas de cobro y liquidación de divisas no restringen ni demoran el cobro de exportaciones ni el pago de insumos importados. | C106: =+CalculosFoda!AD100 -> 2.9999 | E106: x | J106: x | P106: =IF(AND(COUNTIF(D106:H106,"x")=1,COUNTIF(J106:M106,"x")=1),"OK",IF(AND(COUNTIF(D106:H106,"x")=0,COUNTIF(J106:M106,"x")=0),"pendiente","revisar")) -> OK
B107: 7 - Impuestos, derechos de exportación y reintegros. Se considera favorable si la carga tributaria (derechos de exportación, IVA, ingresos brutos, reintegros) no resta competitividad al producto. | C107: =+CalculosFoda!AD101 -> 6.9999 | G107: x | K107: x | P107: =IF(AND(COUNTIF(D107:H107,"x")=1,COUNTIF(J107:M107,"x")=1),"OK",IF(AND(COUNTIF(D107:H107,"x")=0,COUNTIF(J107:M107,"x")=0),"pendiente","revisar")) -> OK
B108: 8 - Precios internacionales del producto. Se considera favorable si los precios internacionales de referencia son estables o favorables y dejan margen a la empresa. | C108: =+CalculosFoda!AD102 -> 6.9999 | G108: x | L108: x | P108: =IF(AND(COUNTIF(D108:H108,"x")=1,COUNTIF(J108:M108,"x")=1),"OK",IF(AND(COUNTIF(D108:H108,"x")=0,COUNTIF(J108:M108,"x")=0),"pendiente","revisar")) -> OK
B110: Ámbito Sociocultural
B111: 1 - Afinidad cultural y hábitos de consumo. Se considera favorable si el uso, el gusto y los hábitos de consumo del destino coinciden con lo que la empresa ofrece. | C111: =+CalculosFoda!AD105 -> 4.9999 | F111: x | J111: x | P111: =IF(AND(COUNTIF(D111:H111,"x")=1,COUNTIF(J111:M111,"x")=1),"OK",IF(AND(COUNTIF(D111:H111,"x")=0,COUNTIF(J111:M111,"x")=0),"pendiente","revisar")) -> OK
B112: 2 - Idioma y cercanía cultural. Se considera favorable si hay cercanía idiomática y cultural (español, portugués, guaraní) con mercados vecinos que facilita negociar. | C112: =+CalculosFoda!AD106 -> 9.99985 | H112: x | L112: x | P112: =IF(AND(COUNTIF(D112:H112,"x")=1,COUNTIF(J112:M112,"x")=1),"OK",IF(AND(COUNTIF(D112:H112,"x")=0,COUNTIF(J112:M112,"x")=0),"pendiente","revisar")) -> OK
...

Sheet GUIA_ENTREVISTA
B1: GUÍA DE ENTREVISTA – Preguntas abiertas por factor (para el relevamiento a la empresa)
B2: Formule la pregunta guía, pida la evidencia indicada y recién entonces marque situación e impacto en FormularioFODA. Las columnas H e I orientan cómo leer cada factor cuando la empresa entrevistada NO exporta todavía y evalúa iniciar (ver también LEEME §8).
B4: Código | C4: Área / bloque Canvas | D4: Factor | E4: Pregunta guía para la entrevista | F4: Evidencia a solicitar / fuente a consultar | G4: Fila en FormularioFODA | H4: Quién responde | I4: Si la empresa NO exporta: cómo leer la Situación
B5: IA1 | C5: 1. Segmentos de clientes | D5: Definición de segmentos y países objetivo | E5: ¿A qué tipo de clientes y en qué países querría vender? ¿Con qué datos lo decidió? | F5: Lista de países y segmentos priorizados; estudio o fuente consultada. | G5: =+ROW(FormularioFODA!B6) -> 6 | H5: Empresario: datos de cartera y experiencia actuales. Estudiante: investigación de países y segmentos candidatos, a validar con el empresario. | I5: Favorable si, aunque nunca exportó, el equipo ya identificó con datos 2-3 países/segmentos candidatos (puede ser trabajo del estudiante avalado por el empresario). Si no hay ese trabajo previo, es Desfavorable real, no 'No corresponde'.
B6: IA2 | C6: 1. Segmentos de clientes | D6: Conocimiento de las necesidades del cliente externo | E6: ¿Qué le exigiría un comprador de Brasil, Paraguay u otro destino que hoy no le piden en Argentina? | F6: Consultas o cotizaciones recibidas del exterior; fichas de requisitos. | G6: =+ROW(FormularioFODA!B7) -> 7 | H6: Empresario: datos de cartera y experiencia actuales. Estudiante: investigación de países y segmentos candidatos, a validar con el empresario. | I6: Sin exportar, esto casi siempre será Desfavorable o Muy desfavorable: es una brecha real de información, regístrela así en vez de neutralizarla.
B7: IA3 | C7: 1. Segmentos de clientes | D7: Concentración de clientes | E7: ¿Qué porcentaje de las ventas representa su mayor cliente? ¿Y los tres mayores? | F7: Ranking de clientes por facturación del último año. | G7: =+ROW(FormularioFODA!B8) -> 8 | H7: Empresario: datos de cartera y experiencia actuales. Estudiante: investigación de países y segmentos candidatos, a validar con el empresario. | I7: No cambia: se responde con la cartera de clientes doméstica actual, exporte o no la empresa.
B8: IA4 | C8: 1. Segmentos de clientes | D8: Experiencia previa exportadora | E8: ¿Exportó directa o indirectamente, o cotizó alguna vez a un cliente del exterior? ¿Qué aprendió? | F8: Facturas de exportación, permisos de embarque o cotizaciones. | G8: =+ROW(FormularioFODA!B9) -> 9 | H8: Empresario: datos de cartera y experiencia actuales. Estudiante: investigación de países y segmentos candidatos, a validar con el empresario. | I8: Si nunca exportó ni cotizó, marque Muy Desfavorable con naturalidad: es la respuesta correcta, no un fracaso del formulario. Su Impacto suele ser menor en un primer proyecto acompañado por una cámara, consorcio o la propia tecnicatura.
B9: IA5 | C9: 1. Segmentos de clientes | D9: Acceso a información de mercados | E9: ¿De dónde obtiene información sobre precios, demanda y competidores en el exterior? | F9: Fuentes o informes utilizados; suscripciones o contactos institucionales. | G9: =+ROW(FormularioFODA!B10) -> 10 | H9: Empresario: datos de cartera y experiencia actuales. Estudiante: investigación de países y segmentos candidatos, a validar con el empresario. | I9: Evalúe con lo que el empresario y el equipo estudiante ya reunieron a la fecha de la entrevista, aunque sea incipiente.
B10: IB1 | C10: 2. Propuesta de valor | D10: Diferenciación del producto | E10: ¿Por qué un comprador del exterior le compraría a usted y no a otro proveedor? | F10: Fichas técnicas, muestras, testimonios de clientes, premios. | G10: =+ROW(FormularioFODA!B13) -> 13 | H10: Empresario, con apoyo del estudiante para comparar el producto contra los requisitos del destino elegido. | I10: Se responde igual, exporte o no la empresa: use la evidencia doméstica disponible como capacidad transferible.
B11: IB2 | C11: 2. Propuesta de valor | D11: Adecuación a requisitos del mercado destino | E11: ¿Qué cambios necesitaría el producto, el envase o la etiqueta para venderse en el país objetivo? | F11: Comparación de requisitos del destino frente al producto actual. | G11: =+ROW(FormularioFODA!B14) -> 14 | H11: Empresario, con apoyo del estudiante para comparar el producto contra los requisitos del destino elegido. | I11: Se responde igual, exporte o no la empresa: use la evidencia doméstica disponible como capacidad transferible.
B12: IB3 | C12: 2. Propuesta de valor | D12: Certificaciones y normas de producto | E12: ¿Qué certificaciones tiene vigentes y cuáles le piden sus clientes potenciales? | F12: Certificados vigentes con fecha de vencimiento. | G12: =+ROW(FormularioFODA!B15) -> 15 | H12: Empresario, con apoyo del estudiante para comparar el producto contra los requisitos del destino elegido. | I12: Se responde igual, exporte o no la empresa: use la evidencia doméstica disponible como capacidad transferible.
B13: IB4 | C13: 2. Propuesta de valor | D13: Competitividad de precio internacional | E13: ¿Conoce a qué precio vende la competencia en el destino? ¿Cómo se compara el suyo puesto en frontera o puerto? | F13: Comparativo de precios (fuente pública o listas de compradores). | G13: =+ROW(FormularioFODA!B16) -> 16 | H13: Empresario, con apoyo del estudiante para comparar el producto contra los requisitos del destino elegido. | I13: Se responde igual, exporte o no la empresa: use la evidencia doméstica disponible como capacidad transferible.
B14: IB5 | C14: 2. Propuesta de valor | D14: Marca, presentación y material comercial | E14: ¿Tiene la marca registrada (y en el país destino)? ¿Cuenta con catálogo en otro idioma? | F14: Constancia de registro de marca; catálogo y sitio web. | G14: =+ROW(FormularioFODA!B17) -> 17 | H14: Empresario, con apoyo del estudiante para comparar el producto contra los requisitos del destino elegido. | I14: Se responde igual, exporte o no la empresa: use la evidencia doméstica disponible como capacidad transferible.
B15: IB6 | C15: 2. Propuesta de valor | D15: Origen e identidad regional | E15: ¿Su producto comunica su origen? ¿Los compradores lo valoran? | F15: Sellos de origen, historia de marca, material promocional. | G15: =+ROW(FormularioFODA!B18) -> 18 | H15: Empresario, con apoyo del estudiante para comparar el producto contra los requisitos del destino elegido. | I15: Se responde igual, exporte o no la empresa: use la evidencia doméstica disponible como capacidad transferible.
B16: IB7 | C16: 2. Propuesta de valor | D16: Amplitud de línea y desarrollo de nuevos productos | E16: ¿Cuántas líneas o productos podría ofrecer al exterior y qué desarrollos tiene previstos? | F16: Catálogo de productos; proyectos de desarrollo. | G16: =+ROW(FormularioFODA!B19) -> 19 | H16: Empresario, con apoyo del estudiante para comparar el producto contra los requisitos del destino elegido. | I16: Se responde igual, exporte o no la empresa: use la evidencia doméstica disponible como capacidad transferible.
B17: IC1 | C17: 3. Canales | D17: Canales de comercialización externos | E17: ¿A través de quién vendería en el exterior? ¿Qué canales evaluó? | F17: Mapa de canales; contactos iniciales. | G17: =+ROW(FormularioFODA!B22) -> 22 | H17: Empresario: situación comercial/digital actual. Estudiante: propuesta de canales externos, a validar con el empresario. | I17: Es una propuesta, no un hecho: se marca según la investigación del estudiante y la apertura real del empresario a usar ese canal.
B18: IC2 | C18: 3. Canales | D18: Presencia digital y venta online | E18: ¿Recibe consultas por web o redes sociales? ¿En qué idioma y con qué demora responde? | F18: Sitio web, métricas de contacto. | G18: =+ROW(FormularioFODA!B23) -> 23 | H18: Empresario: situación comercial/digital actual. Estudiante: propuesta de canales externos, a validar con el empresario. | I18: Se evalúa la situación digital ACTUAL de la empresa (sitio, redes, tiempos de respuesta): es una capacidad transferible, no requiere haber exportado.
B19: IC3 | C19: 3. Canales | D19: Promoción internacional | E19: ¿Participó en ferias o rondas de negocios? ¿Qué presupuesto de promoción tiene? | F19: Registro de ferias y rondas; presupuesto de promoción. | G19: =+ROW(FormularioFODA!B24) -> 24 | H19: Empresario: situación comercial/digital actual. Estudiante: propuesta de canales externos, a validar con el empresario. | I19: Si nunca participó de una feria o ronda de negocios, Desfavorable/Muy desfavorable es la respuesta honesta.
B20: IC4 | C20: 3. Canales | D20: Logística y embalaje de exportación | E20: ¿Sabe cómo enviaría la mercadería (embalaje, transporte, seguro) y qué Incoterm ofrecería? | F20: Cotizaciones de flete; especificación de embalaje. | G20: =+ROW(FormularioFODA!B25) -> 25 | H20: Empresario: situación comercial/digital actual. Estudiante: propuesta de canales externos, a validar con el empresario. | I20: Se evalúa la capacidad técnica de adaptar embalaje y transporte actuales, aunque nunca se hayan usado para exportar.
B21: IC5 | C21: 3. Canales | D21: Gestión documental y aduanera | E21: ¿Qué documentos necesita para exportar y quién los gestionaría? | F21: Checklist documental; contacto con despachante. | G21: =+ROW(FormularioFODA!B26) -> 26 | H21: Empresario: situación comercial/digital actual. Estudiante: propuesta de canales externos, a validar con el empresario. | I21: Se evalúa el conocimiento o la disposición a averiguarlo (¿sabe a quién consultar?), no la experiencia previa en despachos.
B22: ID1 | C22: 4. Relación con clientes | D22: Atención y postventa internacional | E22: ¿Quién atendería a un cliente del exterior y en qué plazos? | F22: Procedimiento o responsable designado. | G22: =+ROW(FormularioFODA!B29) -> 29 | H22: Empresario (capacidades transferibles del mercado interno: idioma, contratos, atención, reclamos). | I22: Se evalúa la estructura de atención actual y su capacidad de adaptarse a un cliente a distancia y en otro huso horario.
B23: ID2 | C23: 4. Relación con clientes | D23: Comunicación en idioma extranjero | E23: ¿Quién de la empresa puede negociar en portugués o inglés? | F23: Perfil del personal; servicios de traducción contratados. | G23: =+ROW(FormularioFODA!B30) -> 30 | H23: Empresario (capacidades transferibles del mercado interno: idioma, contratos, atención, reclamos). | I23: Capacidad real del personal hoy, exporte o no la empresa.
B24: ID3 | C24: 4. Relación con clientes | D24: Contratos y condiciones con compradores | E24: ¿Usa contratos o condiciones generales de venta? ¿Cómo verifica la solvencia de un comprador? | F24: Modelo de contrato; informes comerciales. | G24: =+ROW(FormularioFODA!B31) -> 31 | H24: Empresario (capacidades transferibles del mercado interno: idioma, contratos, atención, reclamos). | I24: Se evalúa el uso actual de contratos o condiciones de venta con clientes domésticos, como capacidad transferible a un comprador externo.
B25: ID4 | C25: 4. Relación con clientes | D25: Fidelización y recompra | E25: ¿Qué porcentaje de los clientes vuelve a comprar? ¿Cómo los mantiene? | F25: Tasa de recompra; acuerdos vigentes. | G25: =+ROW(FormularioFODA!B32) -> 32 | H25: Empresario (capacidades transferibles del mercado interno: idioma, contratos, atención, reclamos). | I25: Dato doméstico real: aplica igual exporte o no la empresa.
B26: ID5 | C26: 4. Relación con clientes | D26: Gestión de reclamos y devoluciones | E26: ¿Cómo resuelve hoy un reclamo? ¿Podría hacerlo con un cliente a distancia? | F26: Registro de reclamos y tiempos de resolución. | G26: =+ROW(FormularioFODA!B33) -> 33 | H26: Empresario (capacidades transferibles del mercado interno: idioma, contratos, atención, reclamos). | I26: Dato doméstico real: aplica igual exporte o no la empresa.
B27: IE1 | C27: 5. Fuentes de ingresos | D27: Evolución de ventas | E27: ¿Cómo evolucionaron las ventas en los últimos tres años? | F27: Facturación anual de tres años. | G27: =+ROW(FormularioFODA!B36) -> 36 | H27: Empresario: datos reales de ventas y margen. Estudiante: construcción del costeo/precio de exportación hipotético, a validar con el empresario. | I27: Dato doméstico real: aplica igual exporte o no la empresa.
B28: IE2 | C28: 5. Fuentes de ingresos | D28: Fijación de precio de exportación | E28: ¿Cómo calcularía el precio en dólares de una venta al exterior? | F28: Planilla de costeo de exportación. | G28: =+ROW(FormularioFODA!B37) -> 37 | H28: Empresario: datos reales de ventas y margen. Estudiante: construcción del costeo/precio de exportación hipotético, a validar con el empresario. | I28: Se evalúa si existe (o puede construirse con ayuda del estudiante) un método de costeo, no si ya se aplicó a una venta real.
B29: IE3 | C29: 5. Fuentes de ingresos | D29: Margen del producto exportable | E29: ¿Qué margen deja el producto hoy y cuánto podría ceder para exportar? | F29: Margen por producto. | G29: =+ROW(FormularioFODA!B38) -> 38 | H29: Empresario: datos reales de ventas y margen. Estudiante: construcción del costeo/precio de exportación hipotético, a validar con el empresario. | I29: Se estima a partir del margen doméstico actual y de cuánto podría ceder la empresa, sin necesidad de una venta de exportación real.
B30: IE4 | C30: 5. Fuentes de ingresos | D30: Medios y condiciones de cobro | E30: ¿Cómo cobraría una venta al exterior y qué riesgo aceptaría? | F30: Instrumentos habilitados con su banco. | G30: =+ROW(FormularioFODA!B39) -> 39 | H30: Empresario: datos reales de ventas y margen. Estudiante: construcción del costeo/precio de exportación hipotético, a validar con el empresario. | I30: Se evalúa el conocimiento y la disposición del empresario y su banco, no una operación ya realizada.
B31: IE5 | C31: 5. Fuentes de ingresos | D31: Diversificación de ingresos | E31: ¿De cuántos productos, clientes o mercados depende su facturación? | F31: Composición de ventas. | G31: =+ROW(FormularioFODA!B40) -> 40 | H31: Empresario: datos reales de ventas y margen. Estudiante: construcción del costeo/precio de exportación hipotético, a validar con el empresario. | I31: Dato doméstico real: aplica igual exporte o no la empresa.
B32: IE6 | C32: 5. Fuentes de ingresos | D32: Resistencia a variaciones cambiarias | E32: ¿Qué pasa con su rentabilidad si el tipo de cambio se mueve un 10%? | F32: Sensibilidad de márgenes; proporción de costos en dólares. | G32: =+ROW(FormularioFODA!B41) -> 41 | H32: Empresario: datos reales de ventas y margen. Estudiante: construcción del costeo/precio de exportación hipotético, a validar con el empresario. | I32: Dato doméstico real: sensibilidad de costos y márgenes actuales frente al tipo de cambio.
B33: IF1 | C33: 6. Recursos clave | D33: Capacidad instalada y ociosa | E33: ¿Qué porcentaje de su capacidad usa hoy? ¿Podría producir un pedido exportable sin frenar al resto? | F33: Capacidad nominal frente a producción real. | G33: =+ROW(FormularioFODA!B45) -> 45 | H33: Empresario (recursos productivos, financieros y humanos propios). | I33: Se responde igual, exporte o no la empresa: use la evidencia doméstica disponible como capacidad transferible.
B34: IF2 | C34: 6. Recursos clave | D34: Estado y tecnología de la maquinaria | E34: ¿Qué equipos limitan calidad o volumen? ¿Qué inversión requeriría reemplazarlos? | F34: Inventario de equipos y antigüedad. | G34: =+ROW(FormularioFODA!B46) -> 46 | H34: Empresario (recursos productivos, financieros y humanos propios). | I34: Se responde igual, exporte o no la empresa: use la evidencia doméstica disponible como capacidad transferible.
B35: IF3 | C35: 6. Recursos clave | D35: Personal calificado | E35: ¿Cuenta con personal formado y estable en los puestos críticos? | F35: Nómina por calificación; índice de rotación. | G35: =+ROW(FormularioFODA!B47) -> 47 | H35: Empresario (recursos productivos, financieros y humanos propios). | I35: Se responde igual, exporte o no la empresa: use la evidencia doméstica disponible como capacidad transferible.
B36: IF4 | C36: 6. Recursos clave | D36: Formación continua y capacitación en comercio exterior | E36: ¿Capacita a su personal? ¿Alguien tiene formación en comercio exterior? | F36: Plan de capacitación; certificados. | G36: =+ROW(FormularioFODA!B48) -> 48 | H36: Empresario (recursos productivos, financieros y humanos propios). | I36: Se responde igual, exporte o no la empresa: use la evidencia doméstica disponible como capacidad transferible.
B37: IF5 | C37: 6. Recursos clave | D37: Capital de trabajo y capacidad financiera | E37: ¿Podría afrontar 60 a 90 días de plazo de cobro y los costos de embarque? | F37: Flujo de fondos; líneas bancarias. | G37: =+ROW(FormularioFODA!B49) -> 49 | H37: Empresario (recursos productivos, financieros y humanos propios). | I37: Se responde igual, exporte o no la empresa: use la evidencia doméstica disponible como capacidad transferible.
B38: IF6 | C38: 6. Recursos clave | D38: Sistemas de información y gestión | E38: ¿Su sistema permite facturar en moneda extranjera y seguir pedidos? | F38: Sistema utilizado; capturas o reportes. | G38: =+ROW(FormularioFODA!B50) -> 50 | H38: Empresario (recursos productivos, financieros y humanos propios). | I38: Se responde igual, exporte o no la empresa: use la evidencia doméstica disponible como capacidad transferible.
B39: IF7 | C39: 6. Recursos clave | D39: Infraestructura, depósitos y conservación | E39: ¿Cómo conserva y almacena el producto terminado? ¿Tiene espacio para consolidar un embarque? | F39: Fotos, planos y condiciones de depósito. | G39: =+ROW(FormularioFODA!B51) -> 51 | H39: Empresario (recursos productivos, financieros y humanos propios). | I39: Se responde igual, exporte o no la empresa: use la evidencia doméstica disponible como capacidad transferible.
B40: IF8 | C40: 6. Recursos clave | D40: Habilitaciones y registros oficiales | E40: ¿Qué habilitaciones y registros tiene vigentes? ¿Está inscripta como exportadora? | F40: Constancias vigentes. | G40: =+ROW(FormularioFODA!B52) -> 52 | H40: Empresario (recursos productivos, financieros y humanos propios). | I40: Se responde igual, exporte o no la empresa: use la evidencia doméstica disponible como capacidad transferible.
B41: IG1 | C41: 7. Actividades clave | D41: Descripción técnica y estandarización | E41: ¿Existen procedimientos escritos? ¿Obtiene siempre la misma calidad? | F41: Manuales y diagramas de flujo. | G41: =+ROW(FormularioFODA!B55) -> 55 | H41: Empresario, con relevamiento en planta del estudiante cuando sea posible. | I41: Se responde igual, exporte o no la empresa: use la evidencia doméstica disponible como capacidad transferible.
B42: IG2 | C42: 7. Actividades clave | D42: Mantenimiento y continuidad operativa | E42: ¿Cuántas paradas no planificadas tuvo el último año? | F42: Registro de paradas; plan de mantenimiento. | G42: =+ROW(FormularioFODA!B56) -> 56 | H42: Empresario, con relevamiento en planta del estudiante cuando sea posible. | I42: Se responde igual, exporte o no la empresa: use la evidencia doméstica disponible como capacidad transferible.
B43: IG3 | C43: 7. Actividades clave | D43: Planificación de producción y abastecimiento | E43: ¿Con cuánta anticipación planifica? ¿Puede comprometer un volumen mensual firme? | F43: Plan de producción. | G43: =+ROW(FormularioFODA!B57) -> 57 | H43: Empresario, con relevamiento en planta del estudiante cuando sea posible. | I43: Se responde igual, exporte o no la empresa: use la evidencia doméstica disponible como capacidad transferible.
B44: IG4 | C44: 7. Actividades clave | D44: Gestión de calidad | E44: ¿Qué controles de calidad realiza? ¿Tiene alguna norma implementada? | F44: Manual y registros de calidad. | G44: =+ROW(FormularioFODA!B58) -> 58 | H44: Empresario, con relevamiento en planta del estudiante cuando sea posible. | I44: Se responde igual, exporte o no la empresa: use la evidencia doméstica disponible como capacidad transferible.
B45: IG5 | C45: 7. Actividades clave | D45: Trazabilidad y control de stock | E45: ¿Puede rastrear un lote desde la materia prima hasta el cliente? | F45: Registros de lote; inventario. | G45: =+ROW(FormularioFODA!B59) -> 59 | H45: Empresario, con relevamiento en planta del estudiante cuando sea posible. | I45: Se responde igual, exporte o no la empresa: use la evidencia doméstica disponible como capacidad transferible.
B46: IG6 | C46: 7. Actividades clave | D46: Cumplimiento de plazos de entrega | E46: ¿Qué porcentaje de los pedidos entrega a tiempo y completos? | F46: Indicador de cumplimiento de entregas. | G46: =+ROW(FormularioFODA!B60) -> 60 | H46: Empresario, con relevamiento en planta del estudiante cuando sea posible. | I46: Se responde igual, exporte o no la empresa: use la evidencia doméstica disponible como capacidad transferible.
B47: IG7 | C47: 7. Actividades clave | D47: Mejora de procesos e I+D | E47: ¿Qué mejoras implementó y qué proyectos tiene en marcha? | F47: Proyectos e inversiones. | G47: =+ROW(FormularioFODA!B61) -> 61 | H47: Empresario, con relevamiento en planta del estudiante cuando sea posible. | I47: Se responde igual, exporte o no la empresa: use la evidencia doméstica disponible como capacidad transferible.
B48: IG8 | C48: 7. Actividades clave | D48: Gestión ambiental y de residuos | E48: ¿Cuenta con habilitación ambiental? ¿Cómo gestiona residuos y subproductos? | F48: Permisos y registros ambientales. | G48: =+ROW(FormularioFODA!B62) -> 62 | H48: Empresario, con relevamiento en planta del estudiante cuando sea posible. | I48: Se responde igual, exporte o no la empresa: use la evidencia doméstica disponible como capacidad transferible.
B49: IG9 | C49: 7. Actividades clave | D49: Seguridad e higiene laboral | E49: ¿Hay programa de seguridad e higiene? ¿Cuál es su índice de accidentes? | F49: Programa y estadísticas de accidentes. | G49: =+ROW(FormularioFODA!B63) -> 63 | H49: Empresario, con relevamiento en planta del estudiante cuando sea posible. | I49: Se responde igual, exporte o no la empresa: use la evidencia doméstica disponible como capacidad transferible.
B50: IH1 | C50: 8. Socios clave | D50: Proveedores estratégicos | E50: ¿Cuáles son los proveedores críticos y qué alternativa tiene para cada uno? | F50: Listado de proveedores y porcentaje de compras. | G50: =+ROW(FormularioFODA!B66) -> 66 | H50: Empresario: proveedores y socios actuales. Estudiante: identificación de despachante/forwarder y programas de apoyo. | I50: Se responde igual, exporte o no la empresa: use la evidencia doméstica disponible como capacidad transferible.
B51: IH2 | C51: 8. Socios clave | D51: Alianzas comerciales | E51: ¿Trabajaría con un consorcio o un agente? ¿Tiene contactos? | F51: Acuerdos o cartas de intención. | G51: =+ROW(FormularioFODA!B67) -> 67 | H51: Empresario: proveedores y socios actuales. Estudiante: identificación de despachante/forwarder y programas de apoyo. | I51: Se responde igual, exporte o no la empresa: use la evidencia doméstica disponible como capacidad transferible.
B52: IH3 | C52: 8. Socios clave | D52: Socios logísticos y aduaneros | E52: ¿Con qué despachante o forwarder trabajaría? ¿Ya pidió cotización? | F52: Cotizaciones recibidas. | G52: =+ROW(FormularioFODA!B68) -> 68 | H52: Empresario: proveedores y socios actuales. Estudiante: identificación de despachante/forwarder y programas de apoyo. | I52: Se responde igual, exporte o no la empresa: use la evidencia doméstica disponible como capacidad transferible.
B53: IH4 | C53: 8. Socios clave | D53: Apoyo institucional | E53: ¿Participa en alguna cámara o programa de apoyo a exportadores? | F53: Membresías y programas en los que participa. | G53: =+ROW(FormularioFODA!B69) -> 69 | H53: Empresario: proveedores y socios actuales. Estudiante: identificación de despachante/forwarder y programas de apoyo. | I53: Se responde igual, exporte o no la empresa: use la evidencia doméstica disponible como capacidad transferible.
B54: IH5 | C54: 8. Socios clave | D54: Socios financieros y de seguros | E54: ¿Su banco opera comercio exterior? ¿Qué líneas utilizó? | F54: Líneas y pólizas vigentes. | G54: =+ROW(FormularioFODA!B70) -> 70 | H54: Empresario: proveedores y socios actuales. Estudiante: identificación de despachante/forwarder y programas de apoyo. | I54: Se responde igual, exporte o no la empresa: use la evidencia doméstica disponible como capacidad transferible.
B55: IH6 | C55: 8. Socios clave | D55: Tercerización y subcontratación | E55: ¿Qué procesos terceriza y con qué grado de dependencia? | F55: Contratos de tercerización. | G55: =+ROW(FormularioFODA!B71) -> 71 | H55: Empresario: proveedores y socios actuales. Estudiante: identificación de despachante/forwarder y programas de apoyo. | I55: Se responde igual, exporte o no la empresa: use la evidencia doméstica disponible como capacidad transferible.
B56: II1 | C56: 9. Estructura de costos | D56: Costos fijos | E56: ¿Cómo evolucionaron los costos fijos el último año? | F56: Estado de resultados. | G56: =+ROW(FormularioFODA!B74) -> 74 | H56: Empresario (costos, precios y endeudamiento reales), con el estudiante armando el costeo de exportación. | I56: Se responde igual, exporte o no la empresa: use la evidencia doméstica disponible como capacidad transferible.
B57: II2 | C57: 9. Estructura de costos | D57: Punto de equilibrio y escala mínima exportable | E57: ¿Cuál es el volumen mínimo por contenedor o camión que sería rentable? | F57: Cálculo del punto de equilibrio. | G57: =+ROW(FormularioFODA!B75) -> 75 | H57: Empresario (costos, precios y endeudamiento reales), con el estudiante armando el costeo de exportación. | I57: Se responde igual, exporte o no la empresa: use la evidencia doméstica disponible como capacidad transferible.
B58: II3 | C58: 9. Estructura de costos | D58: Sistema de costos de exportación | E58: ¿Sabe cuánto cuesta producir y colocar un producto en destino? | F58: Planilla de costos por producto. | G58: =+ROW(FormularioFODA!B76) -> 76 | H58: Empresario (costos, precios y endeudamiento reales), con el estudiante armando el costeo de exportación. | I58: Se responde igual, exporte o no la empresa: use la evidencia doméstica disponible como capacidad transferible.
B59: II4 | C59: 9. Estructura de costos | D59: Costo de materias primas | E59: ¿Cuánto varía el costo de su materia prima durante el año? | F59: Historial de precios de compra. | G59: =+ROW(FormularioFODA!B77) -> 77 | H59: Empresario (costos, precios y endeudamiento reales), con el estudiante armando el costeo de exportación. | I59: Se responde igual, exporte o no la empresa: use la evidencia doméstica disponible como capacidad transferible.
B60: II5 | C60: 9. Estructura de costos | D60: Costos logísticos y de comercio exterior | E60: ¿Qué porcentaje del precio representarían fletes y gastos de exportación? | F60: Cotizaciones logísticas. | G60: =+ROW(FormularioFODA!B78) -> 78 | H60: Empresario (costos, precios y endeudamiento reales), con el estudiante armando el costeo de exportación. | I60: Se responde igual, exporte o no la empresa: use la evidencia doméstica disponible como capacidad transferible.
B61: II6 | C61: 9. Estructura de costos | D61: Endeudamiento | E61: ¿Cuál es su nivel de endeudamiento y su costo financiero? | F61: Balance y detalle de deudas. | G61: =+ROW(FormularioFODA!B79) -> 79 | H61: Empresario (costos, precios y endeudamiento reales), con el estudiante armando el costeo de exportación. | I61: Se responde igual, exporte o no la empresa: use la evidencia doméstica disponible como capacidad transferible.
B62: IJ1 | C62: 10. Transversal: gestión y compromiso exportador | D62: Estrategia y objetivos de largo plazo | E62: ¿Qué lugar tiene la exportación en su plan a 3 o 5 años? | F62: Plan escrito o acta de directorio. | G62: =+ROW(FormularioFODA!B83) -> 83 | H62: Dirección de la empresa (empresario o socios): estas preguntas son sobre compromiso y decisión, no requieren datos externos. | I62: Se responde igual, exporte o no la empresa: use la evidencia doméstica disponible como capacidad transferible.
B63: IJ2 | C63: 10. Transversal: gestión y compromiso exportador | D63: Compromiso de la dirección | E63: ¿Qué recursos está dispuesto a comprometer en los próximos 12 meses? | F63: Presupuesto asignado. | G63: =+ROW(FormularioFODA!B84) -> 84 | H63: Dirección de la empresa (empresario o socios): estas preguntas son sobre compromiso y decisión, no requieren datos externos. | I63: Se responde igual, exporte o no la empresa: use la evidencia doméstica disponible como capacidad transferible.
B64: IJ3 | C64: 10. Transversal: gestión y compromiso exportador | D64: Estructura y responsable de comercio exterior | E64: ¿Quién sería el responsable de exportar? ¿Tiene tiempo para hacerlo? | F64: Organigrama. | G64: =+ROW(FormularioFODA!B85) -> 85 | H64: Dirección de la empresa (empresario o socios): estas preguntas son sobre compromiso y decisión, no requieren datos externos. | I64: Se responde igual, exporte o no la empresa: use la evidencia doméstica disponible como capacidad transferible.
B65: IJ4 | C65: 10. Transversal: gestión y compromiso exportador | D65: Conocimiento de la competencia internacional | E65: ¿Quiénes serían sus tres competidores en el destino y cómo compiten? | F65: Análisis de competidores. | G65: =+ROW(FormularioFODA!B86) -> 86 | H65: Dirección de la empresa (empresario o socios): estas preguntas son sobre compromiso y decisión, no requieren datos externos. | I65: Se responde igual, exporte o no la empresa: use la evidencia doméstica disponible como capacidad transferible.
B66: IJ5 | C66: 10. Transversal: gestión y compromiso exportador | D66: Capacidad de anticipación a los cambios | E66: ¿Qué haría si cambian las reglas de exportación o el tipo de cambio? | F66: Planes de contingencia. | G66: =+ROW(FormularioFODA!B87) -> 87 | H66: Dirección de la empresa (empresario o socios): estas preguntas son sobre compromiso y decisión, no requieren datos externos. | I66: Se responde igual, exporte o no la empresa: use la evidencia doméstica disponible como capacidad transferible.
B67: IJ6 | C67: 10. Transversal: gestión y compromiso exportador | D67: Cultura empresarial y estilo de dirección | E67: ¿Cómo se toman las decisiones? ¿La organización está abierta a cambiar? | F67: Observación en la entrevista. | G67: =+ROW(FormularioFODA!B88) -> 88 | H67: Dirección de la empresa (empresario o socios): estas preguntas son sobre compromiso y decisión, no requieren datos externos. | I67: Se responde igual, exporte o no la empresa: use la evidencia doméstica disponible como capacidad transferible.
B68: IJ7 | C68: 10. Transversal: gestión y compromiso exportador | D68: Herramientas de planificación y control | E68: ¿Qué indicadores controla todos los meses? | F68: Tablero de indicadores. | G68: =+ROW(FormularioFODA!B89) -> 89 | H68: Dirección de la empresa (empresario o socios): estas preguntas son sobre compromiso y decisión, no requieren datos externos. | I68: Se responde igual, exporte o no la empresa: use la evidencia doméstica disponible como capacidad transferible.
B69: EA1 | C69: Ámbito Político/Legal y Regulatorio | D69: Política de comercio exterior | E69: ¿Qué cambios normativos afectaron sus operaciones o su decisión de exportar? | F69: Boletín Oficial; normativa de ARCA-Aduana y del organismo sectorial. | G69: =+ROW(FormularioFODA!B93) -> 93 | H69: Estudiante (investigación normativa: Boletín Oficial, aduana, ARCA); validar con contador/despachante si la empresa tiene uno. | I69: No depende de si la empresa exporta: describe el entorno o el mercado destino, no a la empresa.
B70: EA2 | C70: Ámbito Político/Legal y Regulatorio | D70: Acuerdos comerciales y preferencias arancelarias | E70: ¿Su producto paga arancel en el destino? ¿Existe alguna preferencia? | F70: Aranceles por posición arancelaria en Market Access Map (ITC) y normativa del Mercosur. | G70: =+ROW(FormularioFODA!B94) -> 94 | H70: Estudiante (investigación normativa: Boletín Oficial, aduana, ARCA); validar con contador/despachante si la empresa tiene uno. | I70: No depende de si la empresa exporta: describe el entorno o el mercado destino, no a la empresa.
B71: EA3 | C71: Ámbito Político/Legal y Regulatorio | D71: Barreras arancelarias y técnicas del destino | E71: ¿Qué exige la aduana del país destino para su producto? | F71: Posición arancelaria del producto; requisitos de importación del destino. | G71: =+ROW(FormularioFODA!B95) -> 95 | H71: Estudiante (investigación normativa: Boletín Oficial, aduana, ARCA); validar con contador/despachante si la empresa tiene uno. | I71: No depende de si la empresa exporta: describe el entorno o el mercado destino, no a la empresa.
B72: EA4 | C72: Ámbito Político/Legal y Regulatorio | D72: Trámites y aduana | E72: ¿Cuánto tarda y cuánto cuesta un despacho de exportación? | F72: Experiencia de despachantes; tiempos de despacho. | G72: =+ROW(FormularioFODA!B96) -> 96 | H72: Estudiante (investigación normativa: Boletín Oficial, aduana, ARCA); validar con contador/despachante si la empresa tiene uno. | I72: No depende de si la empresa exporta: describe el entorno o el mercado destino, no a la empresa.
B73: EA5 | C73: Ámbito Político/Legal y Regulatorio | D73: Promoción y fomento a exportadores | E73: ¿Conoce programas de apoyo a exportadores? ¿Accedió alguna vez? | F73: Convocatorias vigentes de organismos nacionales y provinciales. | G73: =+ROW(FormularioFODA!B97) -> 97 | H73: Estudiante (investigación normativa: Boletín Oficial, aduana, ARCA); validar con contador/despachante si la empresa tiene uno. | I73: No depende de si la empresa exporta: describe el entorno o el mercado destino, no a la empresa.
B74: EA6 | C74: Ámbito Político/Legal y Regulatorio | D74: Propiedad intelectual y seguridad jurídica | E74: ¿Registró su marca? ¿Tuvo dificultades para hacer cumplir un contrato? | F74: Registro de marcas; modelos de contrato internacional. | G74: =+ROW(FormularioFODA!B98) -> 98 | H74: Estudiante (investigación normativa: Boletín Oficial, aduana, ARCA); validar con contador/despachante si la empresa tiene uno. | I74: No depende de si la empresa exporta: describe el entorno o el mercado destino, no a la empresa.
B75: EB1 | C75: Ámbito Económico/Financiero/Cambiario | D75: Crecimiento económico y ciclo | E75: ¿Cómo influye el ciclo económico sobre sus ventas? | F75: Informes macroeconómicos de organismos oficiales e internacionales. | G75: =+ROW(FormularioFODA!B101) -> 101 | H75: Estudiante (fuentes macroeconómicas y bancarias); el empresario aporta su situación financiera y de acceso al crédito. | I75: No depende de si la empresa exporta: describe el entorno o el mercado destino, no a la empresa.
B76: EB2 | C76: Ámbito Económico/Financiero/Cambiario | D76: Crecimiento sectorial del rubro | E76: ¿Cómo evoluciona la demanda mundial de su producto? | F76: Trade Map (ITC); informes de cámaras sectoriales. | G76: =+ROW(FormularioFODA!B102) -> 102 | H76: Estudiante (fuentes macroeconómicas y bancarias); el empresario aporta su situación financiera y de acceso al crédito. | I76: No depende de si la empresa exporta: describe el entorno o el mercado destino, no a la empresa.
B77: EB3 | C77: Ámbito Económico/Financiero/Cambiario | D77: Tipo de cambio y competitividad | E77: ¿Con el tipo de cambio actual, exporta siendo competitivo? | F77: Tipo de cambio real multilateral; costos en dólares. | G77: =+ROW(FormularioFODA!B103) -> 103 | H77: Estudiante (fuentes macroeconómicas y bancarias); el empresario aporta su situación financiera y de acceso al crédito. | I77: No depende de si la empresa exporta: describe el entorno o el mercado destino, no a la empresa.
B78: EB4 | C78: Ámbito Económico/Financiero/Cambiario | D78: Inflación y costos internos | E78: ¿Qué costos suben más rápido que su precio en dólares? | F78: Índices de precios y de costos del sector. | G78: =+ROW(FormularioFODA!B104) -> 104 | H78: Estudiante (fuentes macroeconómicas y bancarias); el empresario aporta su situación financiera y de acceso al crédito. | I78: No depende de si la empresa exporta: describe el entorno o el mercado destino, no a la empresa.
B79: EB5 | C79: Ámbito Económico/Financiero/Cambiario | D79: Financiamiento y crédito para exportar | E79: ¿Accede a créditos para producir y exportar? ¿A qué tasa y plazo? | F79: Líneas bancarias públicas y privadas. | G79: =+ROW(FormularioFODA!B105) -> 105 | H79: Estudiante (fuentes macroeconómicas y bancarias); el empresario aporta su situación financiera y de acceso al crédito. | I79: No depende de si la empresa exporta: describe el entorno o el mercado destino, no a la empresa.
B80: EB6 | C80: Ámbito Económico/Financiero/Cambiario | D80: Cobros y acceso a divisas | E80: ¿Tuvo restricciones o demoras para cobrar o pagar operaciones? | F80: Normativa cambiaria del BCRA. | G80: =+ROW(FormularioFODA!B106) -> 106 | H80: Estudiante (fuentes macroeconómicas y bancarias); el empresario aporta su situación financiera y de acceso al crédito. | I80: No depende de si la empresa exporta: describe el entorno o el mercado destino, no a la empresa.
B81: EB7 | C81: Ámbito Económico/Financiero/Cambiario | D81: Impuestos, derechos de exportación y reintegros | E81: ¿Cuánto pesan impuestos y derechos sobre su precio de exportación? | F81: Alícuotas vigentes; asesoramiento contable. | G81: =+ROW(FormularioFODA!B107) -> 107 | H81: Estudiante (fuentes macroeconómicas y bancarias); el empresario aporta su situación financiera y de acceso al crédito. | I81: No depende de si la empresa exporta: describe el entorno o el mercado destino, no a la empresa.
B82: EB8 | C82: Ámbito Económico/Financiero/Cambiario | D82: Precios internacionales del producto | E82: ¿Cuál es el precio internacional de referencia y cuánto varía en el año? | F82: Series de precios y estadísticas de comercio. | G82: =+ROW(FormularioFODA!B108) -> 108 | H82: Estudiante (fuentes macroeconómicas y bancarias); el empresario aporta su situación financiera y de acceso al crédito. | I82: No depende de si la empresa exporta: describe el entorno o el mercado destino, no a la empresa.
B83: EC1 | C83: Ámbito Sociocultural | D83: Afinidad cultural y hábitos de consumo | E83: ¿Se consume su producto en el destino? ¿De qué manera? | F83: Estudios de mercado; consulados y cámaras binacionales. | G83: =+ROW(FormularioFODA!B111) -> 111 | H83: Estudiante (investigación cultural y del sector); el empresario aporta su percepción de clientes actuales del rubro. | I83: No depende de si la empresa exporta: describe el entorno o el mercado destino, no a la empresa.
B84: EC2 | C84: Ámbito Sociocultural | D84: Idioma y cercanía cultural | E84: ¿En qué idioma negociaría? ¿Conoce las costumbres comerciales del destino? | F84: Guías de negociación intercultural. | G84: =+ROW(FormularioFODA!B112) -> 112 | H84: Estudiante (investigación cultural y del sector); el empresario aporta su percepción de clientes actuales del rubro. | I84: No depende de si la empresa exporta: describe el entorno o el mercado destino, no a la empresa.
B85: EC3 | C85: Ámbito Sociocultural | D85: Valoración del origen y la sustentabilidad | E85: ¿Sus clientes piden información sobre origen o sustentabilidad? | F85: Requisitos de compradores; tendencias de consumo. | G85: =+ROW(FormularioFODA!B113) -> 113 | H85: Estudiante (investigación cultural y del sector); el empresario aporta su percepción de clientes actuales del rubro. | I85: No depende de si la empresa exporta: describe el entorno o el mercado destino, no a la empresa.
B86: EC4 | C86: Ámbito Sociocultural | D86: Formación técnica y mano de obra regional | E86: ¿Le resulta fácil conseguir personal calificado en la región? | F86: Oferta educativa provincial; bolsas de empleo. | G86: =+ROW(FormularioFODA!B114) -> 114 | H86: Estudiante (investigación cultural y del sector); el empresario aporta su percepción de clientes actuales del rubro. | I86: No depende de si la empresa exporta: describe el entorno o el mercado destino, no a la empresa.
B87: EC5 | C87: Ámbito Sociocultural | D87: Asociativismo y cultura exportadora regional | E87: ¿Existen consorcios, cámaras o cluster de su rubro en la región? | F87: Nómina de cámaras y entes sectoriales. | G87: =+ROW(FormularioFODA!B115) -> 115 | H87: Estudiante (investigación cultural y del sector); el empresario aporta su percepción de clientes actuales del rubro. | I87: No depende de si la empresa exporta: describe el entorno o el mercado destino, no a la empresa.
B88: ED1 | C88: Ámbito Tecnológico y Digital | D88: Avances tecnológicos del sector | E88: ¿Qué tecnología del sector le permitiría competir mejor y está a su alcance? | F88: Proveedores de tecnología; INTA y centros tecnológicos. | G88: =+ROW(FormularioFODA!B118) -> 118 | H88: Estudiante (investigación tecnológica y digital); el empresario informa su conectividad y sistemas actuales. | I88: No depende de si la empresa exporta: describe el entorno o el mercado destino, no a la empresa.
B89: ED2 | C89: Ámbito Tecnológico y Digital | D89: Conectividad y plataformas de comercio electrónico | E89: ¿Cómo es la conectividad en su planta y qué plataformas conoce para vender afuera? | F89: Plataformas y marketplaces B2B del rubro. | G89: =+ROW(FormularioFODA!B119) -> 119 | H89: Estudiante (investigación tecnológica y digital); el empresario informa su conectividad y sistemas actuales. | I89: No depende de si la empresa exporta: describe el entorno o el mercado destino, no a la empresa.
B90: ED3 | C90: Ámbito Tecnológico y Digital | D90: Digitalización del comercio exterior | E90: ¿Qué trámites de exportación puede hacer hoy de forma electrónica? | F90: Servicios digitales de ARCA-Aduana y ventanilla única. | G90: =+ROW(FormularioFODA!B120) -> 120 | H90: Estudiante (investigación tecnológica y digital); el empresario informa su conectividad y sistemas actuales. | I90: No depende de si la empresa exporta: describe el entorno o el mercado destino, no a la empresa.
B91: ED4 | C91: Ámbito Tecnológico y Digital | D91: Trazabilidad y certificación digital | E91: ¿Sus compradores le piden trazabilidad digital? ¿Qué herramientas tiene disponibles? | F91: Requisitos de compradores; herramientas de trazabilidad. | G91: =+ROW(FormularioFODA!B121) -> 121 | H91: Estudiante (investigación tecnológica y digital); el empresario informa su conectividad y sistemas actuales. | I91: No depende de si la empresa exporta: describe el entorno o el mercado destino, no a la empresa.
B92: EE1 | C92: Logística e Infraestructura Regional | D92: Red vial y conectividad multimodal | E92: ¿Cómo es hoy el traslado de su mercadería hacia frontera y puertos? | F92: Estado de rutas; tiempos y costos de transporte. | G92: =+ROW(FormularioFODA!B124) -> 124 | H92: Estudiante (investigación de rutas, pasos de frontera, puertos y prestadores logísticos regionales). | I92: No depende de si la empresa exporta: describe el entorno o el mercado destino, no a la empresa.
B93: EE2 | C93: Logística e Infraestructura Regional | D93: Pasos de frontera y puentes internacionales | E93: ¿Qué demoras o costos tiene el paso de frontera que usaría? | F93: Tiempos de cruce; tarifas y horarios operativos. | G93: =+ROW(FormularioFODA!B125) -> 125 | H93: Estudiante (investigación de rutas, pasos de frontera, puertos y prestadores logísticos regionales). | I93: No depende de si la empresa exporta: describe el entorno o el mercado destino, no a la empresa.
B94: EE3 | C94: Logística e Infraestructura Regional | D94: Puertos, hidrovía y salida a ultramar | E94: ¿Cómo llegaría su carga a un puerto para exportar a ultramar? | F94: Operadores portuarios y navieros; costos de traslado. | G94: =+ROW(FormularioFODA!B126) -> 126 | H94: Estudiante (investigación de rutas, pasos de frontera, puertos y prestadores logísticos regionales). | I94: No depende de si la empresa exporta: describe el entorno o el mercado destino, no a la empresa.
B95: EE4 | C95: Logística e Infraestructura Regional | D95: Costo y disponibilidad de fletes | E95: ¿Qué cotizaciones de flete obtuvo y cómo pesan sobre el precio? | F95: Cotizaciones de transportistas y forwarders. | G95: =+ROW(FormularioFODA!B127) -> 127 | H95: Estudiante (investigación de rutas, pasos de frontera, puertos y prestadores logísticos regionales). | I95: No depende de si la empresa exporta: describe el entorno o el mercado destino, no a la empresa.
B96: EE5 | C96: Logística e Infraestructura Regional | D96: Servicios aduaneros locales | E96: ¿Puede despachar su mercadería en la provincia o debe trasladarla a otra aduana? | F96: Oferta de servicios aduaneros y depósitos fiscales. | G96: =+ROW(FormularioFODA!B128) -> 128 | H96: Estudiante (investigación de rutas, pasos de frontera, puertos y prestadores logísticos regionales). | I96: No depende de si la empresa exporta: describe el entorno o el mercado destino, no a la empresa.
B97: EE6 | C97: Logística e Infraestructura Regional | D97: Prestadores logísticos regionales | E97: ¿Encuentra despachantes y forwarders con experiencia en su rubro? | F97: Directorio de prestadores logísticos. | G97: =+ROW(FormularioFODA!B129) -> 129 | H97: Estudiante (investigación de rutas, pasos de frontera, puertos y prestadores logísticos regionales). | I97: No depende de si la empresa exporta: describe el entorno o el mercado destino, no a la empresa.
B98: EE7 | C98: Logística e Infraestructura Regional | D98: Energía y servicios públicos industriales | E98: ¿Con qué frecuencia sufre cortes o variaciones de tensión? ¿Cuánto pesa la energía en sus costos? | F98: Facturas de energía; registro de cortes. | G98: =+ROW(FormularioFODA!B130) -> 130 | H98: Estudiante (investigación de rutas, pasos de frontera, puertos y prestadores logísticos regionales). | I98: No depende de si la empresa exporta: describe el entorno o el mercado destino, no a la empresa.
B99: EF1 | C99: Mercado y Competencia | D99: Barreras de entrada al mercado destino | E99: ¿Qué le impediría ingresar al mercado destino? | F99: Análisis del destino; consultas a importadores. | G99: =+ROW(FormularioFODA!B133) -> 133 | H99: Estudiante (investigación de mercado destino y competidores). | I99: No depende de si la empresa exporta: describe el entorno o el mercado destino, no a la empresa.
B100: EF2 | C100: Mercado y Competencia | D100: Costos de cambio de los clientes externos | E100: ¿Qué haría que un comprador no cambie de proveedor? | F100: Contratos y relaciones vigentes del sector. | G100: =+ROW(FormularioFODA!B134) -> 134 | H100: Estudiante (investigación de mercado destino y competidores). | I100: No depende de si la empresa exporta: describe el entorno o el mercado destino, no a la empresa.
B101: EF3 | C101: Mercado y Competencia | D101: Tamaño y crecimiento del mercado destino | E101: ¿Qué tamaño tiene el mercado destino para su producto y cómo evoluciona? | F101: Trade Map (ITC); estadísticas de importación del destino. | G101: =+ROW(FormularioFODA!B135) -> 135 | H101: Estudiante (investigación de mercado destino y competidores). | I101: No depende de si la empresa exporta: describe el entorno o el mercado destino, no a la empresa.
...

Sheet MATRIZ FODA
I1: Izq. arriba: Fortalezas-Oportunidades | Der. arriba: Fortalezas-Amenazas | Izq. abajo: Debilidades-Oportunidades | Der. abajo: Debilidades-Amenazas
B4: AREA INTERNA - VISTO DESDE EL MODELO CANVAS | C4: Fortalezas Oportunidades | D4: Fortalezas Amenazas | E4: Debilidades Oportunidades | F4: Debilidades Amenazas | G4: Variables no Consideradas
B5: =+FormularioFODA!B5 -> Segmentos de Clientes | C5: =SUMPRODUCT(--(LEN('PART2 FODA'!D4:D10)>0)) -> 2 | D5: =SUMPRODUCT(--(LEN('PART2 FODA'!E4:E10)>0)) -> 2 | E5: =SUMPRODUCT(--(LEN('PART2 FODA'!F4:F10)>0)) -> 1 | F5: =SUMPRODUCT(--(LEN('PART2 FODA'!G4:G10)>0)) -> 1 | G5: =SUMPRODUCT(--(LEN('PART2 FODA'!H4:H10)>0)) -> 1
B6: =+FormularioFODA!B12 -> Propuesta de Valor | C6: =SUMPRODUCT(--(LEN('PART2 FODA'!D12:D25)>0)) -> 3 | D6: =SUMPRODUCT(--(LEN('PART2 FODA'!E12:E25)>0)) -> 3 | E6: =SUMPRODUCT(--(LEN('PART2 FODA'!F12:F25)>0)) -> 3 | F6: =SUMPRODUCT(--(LEN('PART2 FODA'!G12:G25)>0)) -> 5 | G6: =SUMPRODUCT(--(LEN('PART2 FODA'!H12:H25)>0)) -> 0
B7: =+FormularioFODA!B21 -> Canales | C7: =SUMPRODUCT(--(LEN('PART2 FODA'!D27:D37)>0)) -> 0 | D7: =SUMPRODUCT(--(LEN('PART2 FODA'!E27:E37)>0)) -> 1 | E7: =SUMPRODUCT(--(LEN('PART2 FODA'!F27:F37)>0)) -> 0 | F7: =SUMPRODUCT(--(LEN('PART2 FODA'!G27:G37)>0)) -> 8 | G7: =SUMPRODUCT(--(LEN('PART2 FODA'!H27:H37)>0)) -> 2
B8: =+FormularioFODA!B28 -> Relación con Clientes | C8: =SUMPRODUCT(--(LEN('PART2 FODA'!D39:D43)>0)) -> 0 | D8: =SUMPRODUCT(--(LEN('PART2 FODA'!E39:E43)>0)) -> 0 | E8: =SUMPRODUCT(--(LEN('PART2 FODA'!F39:F43)>0)) -> 2 | F8: =SUMPRODUCT(--(LEN('PART2 FODA'!G39:G43)>0)) -> 1 | G8: =SUMPRODUCT(--(LEN('PART2 FODA'!H39:H43)>0)) -> 2
B9: =+FormularioFODA!B35 -> Fuentes de Ingresos | C9: =SUMPRODUCT(--(LEN('PART2 FODA'!D45:D53)>0)) -> 2 | D9: =SUMPRODUCT(--(LEN('PART2 FODA'!E45:E53)>0)) -> 4 | E9: =SUMPRODUCT(--(LEN('PART2 FODA'!F45:F53)>0)) -> 0 | F9: =SUMPRODUCT(--(LEN('PART2 FODA'!G45:G53)>0)) -> 1 | G9: =SUMPRODUCT(--(LEN('PART2 FODA'!H45:H53)>0)) -> 2
B10: =+FormularioFODA!B44 -> Recursos Clave | C10: =SUMPRODUCT(--(LEN('PART2 FODA'!D55:D67)>0)) -> 1 | D10: =SUMPRODUCT(--(LEN('PART2 FODA'!E55:E67)>0)) -> 7 | E10: =SUMPRODUCT(--(LEN('PART2 FODA'!F55:F67)>0)) -> 1 | F10: =SUMPRODUCT(--(LEN('PART2 FODA'!G55:G67)>0)) -> 4 | G10: =SUMPRODUCT(--(LEN('PART2 FODA'!H55:H67)>0)) -> 0
B11: =+FormularioFODA!B54 -> Actividades Clave | C11: =SUMPRODUCT(--(LEN('PART2 FODA'!D69:D81)>0)) -> 2 | D11: =SUMPRODUCT(--(LEN('PART2 FODA'!E69:E81)>0)) -> 3 | E11: =SUMPRODUCT(--(LEN('PART2 FODA'!F69:F81)>0)) -> 2 | F11: =SUMPRODUCT(--(LEN('PART2 FODA'!G69:G81)>0)) -> 3 | G11: =SUMPRODUCT(--(LEN('PART2 FODA'!H69:H81)>0)) -> 3
B12: =+FormularioFODA!B65 -> Socios Clave | C12: =SUMPRODUCT(--(LEN('PART2 FODA'!D83:D93)>0)) -> 2 | D12: =SUMPRODUCT(--(LEN('PART2 FODA'!E83:E93)>0)) -> 4 | E12: =SUMPRODUCT(--(LEN('PART2 FODA'!F83:F93)>0)) -> 1 | F12: =SUMPRODUCT(--(LEN('PART2 FODA'!G83:G93)>0)) -> 3 | G12: =SUMPRODUCT(--(LEN('PART2 FODA'!H83:H93)>0)) -> 1
B13: =+FormularioFODA!B73 -> Estructura de Costos | C13: =SUMPRODUCT(--(LEN('PART2 FODA'!D95:D104)>0)) -> 1 | D13: =SUMPRODUCT(--(LEN('PART2 FODA'!E95:E104)>0)) -> 3 | E13: =SUMPRODUCT(--(LEN('PART2 FODA'!F95:F104)>0)) -> 2 | F13: =SUMPRODUCT(--(LEN('PART2 FODA'!G95:G104)>0)) -> 1 | G13: =SUMPRODUCT(--(LEN('PART2 FODA'!H95:H104)>0)) -> 3
B14: =+FormularioFODA!B82 -> Gestión y Compromiso Exportador | C14: =SUMPRODUCT(--(LEN('PART2 FODA'!D106:D114)>0)) -> 1 | D14: =SUMPRODUCT(--(LEN('PART2 FODA'!E106:E114)>0)) -> 1 | E14: =SUMPRODUCT(--(LEN('PART2 FODA'!F106:F114)>0)) -> 0 | F14: =SUMPRODUCT(--(LEN('PART2 FODA'!G106:G114)>0)) -> 3 | G14: =SUMPRODUCT(--(LEN('PART2 FODA'!H106:H114)>0)) -> 4
B15: Total de cruces | C15: =SUM(C5:C14) -> 14 | D15: =SUM(D5:D14) -> 28 | E15: =SUM(E5:E14) -> 12 | F15: =SUM(F5:F14) -> 30 | G15: =SUM(G5:G14) -> 18
B16: % sobre cruces evaluados | C16: =IF(SUM($C$15:$F$15)=0,0,C15/SUM($C$15:$F$15)) -> 0.16666667 | D16: =IF(SUM($C$15:$F$15)=0,0,D15/SUM($C$15:$F$15)) -> 0.33333333 | E16: =IF(SUM($C$15:$F$15)=0,0,E15/SUM($C$15:$F$15)) -> 0.14285714 | F16: =IF(SUM($C$15:$F$15)=0,0,F15/SUM($C$15:$F$15)) -> 0.35714286
D18: Oportunidades | E18: Amenazas
C19: Fortalezas | D19: =+C15 -> 14 | E19: =+D15 -> 28
C20: Debilidades | D20: =+E15 -> 12 | E20: =+F15 -> 30
B22: Datos auxiliares del gráfico de burbujas (no borrar)
B23: Cuadrante | C23: X | D23: Y | E23: Tamaño (%)
B24: FO - Ofensiva | C24: 4 | D24: 6 | E24: =+C16 -> 0.16666667
B25: FA - Defensiva | C25: 8 | D25: 6 | E25: =+D16 -> 0.33333333
B26: DO - Reorientación | C26: 4 | D26: 2 | E26: =+E16 -> 0.14285714
B27: DA - Supervivencia | C27: 8 | D27: 2 | E27: =+F16 -> 0.35714286

Sheet PART2 FODA
B2: AMBITO INTERNO | C2: Factores Internos | D2: Fortalezas-Oportunidades | E2: Fortalezas-Amenazas | F2: Debilidades-Oportunidades | G2: Debilidades-Amenazas | H2: Variables no consideradas
B3: Se cruza cada factor interno con las variables externas de las que depende (hoja VariablesFoda); el cuadrante surge de la situación cargada.
B4: =+FormularioFODA!B5 -> Segmentos de Clientes | C4: =+CalculosFoda!AF3 -> Definición de segmentos y países objetivo | D4: =IF(AND(OR('CalculoFoda-1'!H3=1,'CalculoFoda-1'!I3=1),OR('CalculoFoda-1'!H129=1,'CalculoFoda-1'!I129=1)),CalculosFoda!AF129,"") | E4: =IF(AND(OR('CalculoFoda-1'!H3=1,'CalculoFoda-1'!I3=1),OR('CalculoFoda-1'!F129=1,'CalculoFoda-1'!G129=1)),CalculosFoda!AF129,"") -> Tamaño y crecimiento del mercado destino | F4: =IF(AND(OR('CalculoFoda-1'!F3=1,'CalculoFoda-1'!G3=1),OR('CalculoFoda-1'!H129=1,'CalculoFoda-1'!I129=1)),CalculosFoda!AF129,"") | G4: =IF(AND(OR('CalculoFoda-1'!F3=1,'CalculoFoda-1'!G3=1),OR('CalculoFoda-1'!F129=1,'CalculoFoda-1'!G129=1)),CalculosFoda!AF129,"") | H4: =IF(OR(NOT(OR('CalculoFoda-1'!F3=1,'CalculoFoda-1'!G3=1,'CalculoFoda-1'!H3=1,'CalculoFoda-1'!I3=1)),NOT(OR('CalculoFoda-1'!F129=1,'CalculoFoda-1'!G129=1,'CalculoFoda-1'!H129=1,'CalculoFoda-1'!I129=1))),"sin dato: "&CalculosFoda!AF129,"")
D5: =IF(AND(OR('CalculoFoda-1'!H3=1,'CalculoFoda-1'!I3=1),OR('CalculoFoda-1'!H132=1,'CalculoFoda-1'!I132=1)),CalculosFoda!AF132,"") -> Cambios del mercado e inteligencia comercial | E5: =IF(AND(OR('CalculoFoda-1'!H3=1,'CalculoFoda-1'!I3=1),OR('CalculoFoda-1'!F132=1,'CalculoFoda-1'!G132=1)),CalculosFoda!AF132,"") | F5: =IF(AND(OR('CalculoFoda-1'!F3=1,'CalculoFoda-1'!G3=1),OR('CalculoFoda-1'!H132=1,'CalculoFoda-1'!I132=1)),CalculosFoda!AF132,"") | G5: =IF(AND(OR('CalculoFoda-1'!F3=1,'CalculoFoda-1'!G3=1),OR('CalculoFoda-1'!F132=1,'CalculoFoda-1'!G132=1)),CalculosFoda!AF132,"") | H5: =IF(OR(NOT(OR('CalculoFoda-1'!F3=1,'CalculoFoda-1'!G3=1,'CalculoFoda-1'!H3=1,'CalculoFoda-1'!I3=1)),NOT(OR('CalculoFoda-1'!F132=1,'CalculoFoda-1'!G132=1,'CalculoFoda-1'!H132=1,'CalculoFoda-1'!I132=1))),"sin dato: "&CalculosFoda!AF132,"")
C6: =+CalculosFoda!AF4 -> Conocimiento de las necesidades del cliente externo | D6: =IF(AND(OR('CalculoFoda-1'!H4=1,'CalculoFoda-1'!I4=1),OR('CalculoFoda-1'!H105=1,'CalculoFoda-1'!I105=1)),CalculosFoda!AF105,"") | E6: =IF(AND(OR('CalculoFoda-1'!H4=1,'CalculoFoda-1'!I4=1),OR('CalculoFoda-1'!F105=1,'CalculoFoda-1'!G105=1)),CalculosFoda!AF105,"") -> Afinidad cultural y hábitos de consumo | F6: =IF(AND(OR('CalculoFoda-1'!F4=1,'CalculoFoda-1'!G4=1),OR('CalculoFoda-1'!H105=1,'CalculoFoda-1'!I105=1)),CalculosFoda!AF105,"") | G6: =IF(AND(OR('CalculoFoda-1'!F4=1,'CalculoFoda-1'!G4=1),OR('CalculoFoda-1'!F105=1,'CalculoFoda-1'!G105=1)),CalculosFoda!AF105,"") | H6: =IF(OR(NOT(OR('CalculoFoda-1'!F4=1,'CalculoFoda-1'!G4=1,'CalculoFoda-1'!H4=1,'CalculoFoda-1'!I4=1)),NOT(OR('CalculoFoda-1'!F105=1,'CalculoFoda-1'!G105=1,'CalculoFoda-1'!H105=1,'CalculoFoda-1'!I105=1))),"sin dato: "&CalculosFoda!AF105,"")
C7: =+CalculosFoda!AF5 -> Concentración de clientes | D7: =IF(AND(OR('CalculoFoda-1'!H5=1,'CalculoFoda-1'!I5=1),OR('CalculoFoda-1'!H130=1,'CalculoFoda-1'!I130=1)),CalculosFoda!AF130,"") -> Poder negociador de compradores e importadores | E7: =IF(AND(OR('CalculoFoda-1'!H5=1,'CalculoFoda-1'!I5=1),OR('CalculoFoda-1'!F130=1,'CalculoFoda-1'!G130=1)),CalculosFoda!AF130,"") | F7: =IF(AND(OR('CalculoFoda-1'!F5=1,'CalculoFoda-1'!G5=1),OR('CalculoFoda-1'!H130=1,'CalculoFoda-1'!I130=1)),CalculosFoda!AF130,"") | G7: =IF(AND(OR('CalculoFoda-1'!F5=1,'CalculoFoda-1'!G5=1),OR('CalculoFoda-1'!F130=1,'CalculoFoda-1'!G130=1)),CalculosFoda!AF130,"") | H7: =IF(OR(NOT(OR('CalculoFoda-1'!F5=1,'CalculoFoda-1'!G5=1,'CalculoFoda-1'!H5=1,'CalculoFoda-1'!I5=1)),NOT(OR('CalculoFoda-1'!F130=1,'CalculoFoda-1'!G130=1,'CalculoFoda-1'!H130=1,'CalculoFoda-1'!I130=1))),"sin dato: "&CalculosFoda!AF130,"")
C8: =+CalculosFoda!AF6 -> Experiencia previa exportadora | H8: variable independiente
C9: =+CalculosFoda!AF7 -> Acceso a información de mercados | D9: =IF(AND(OR('CalculoFoda-1'!H7=1,'CalculoFoda-1'!I7=1),OR('CalculoFoda-1'!H132=1,'CalculoFoda-1'!I132=1)),CalculosFoda!AF132,"") | E9: =IF(AND(OR('CalculoFoda-1'!H7=1,'CalculoFoda-1'!I7=1),OR('CalculoFoda-1'!F132=1,'CalculoFoda-1'!G132=1)),CalculosFoda!AF132,"") | F9: =IF(AND(OR('CalculoFoda-1'!F7=1,'CalculoFoda-1'!G7=1),OR('CalculoFoda-1'!H132=1,'CalculoFoda-1'!I132=1)),CalculosFoda!AF132,"") -> Cambios del mercado e inteligencia comercial | G9: =IF(AND(OR('CalculoFoda-1'!F7=1,'CalculoFoda-1'!G7=1),OR('CalculoFoda-1'!F132=1,'CalculoFoda-1'!G132=1)),CalculosFoda!AF132,"") | H9: =IF(OR(NOT(OR('CalculoFoda-1'!F7=1,'CalculoFoda-1'!G7=1,'CalculoFoda-1'!H7=1,'CalculoFoda-1'!I7=1)),NOT(OR('CalculoFoda-1'!F132=1,'CalculoFoda-1'!G132=1,'CalculoFoda-1'!H132=1,'CalculoFoda-1'!I132=1))),"sin dato: "&CalculosFoda!AF132,"")
D10: =IF(AND(OR('CalculoFoda-1'!H7=1,'CalculoFoda-1'!I7=1),OR('CalculoFoda-1'!H113=1,'CalculoFoda-1'!I113=1)),CalculosFoda!AF113,"") | E10: =IF(AND(OR('CalculoFoda-1'!H7=1,'CalculoFoda-1'!I7=1),OR('CalculoFoda-1'!F113=1,'CalculoFoda-1'!G113=1)),CalculosFoda!AF113,"") | F10: =IF(AND(OR('CalculoFoda-1'!F7=1,'CalculoFoda-1'!G7=1),OR('CalculoFoda-1'!H113=1,'CalculoFoda-1'!I113=1)),CalculosFoda!AF113,"") | G10: =IF(AND(OR('CalculoFoda-1'!F7=1,'CalculoFoda-1'!G7=1),OR('CalculoFoda-1'!F113=1,'CalculoFoda-1'!G113=1)),CalculosFoda!AF113,"") -> Conectividad y plataformas de comercio electrónico | H10: =IF(OR(NOT(OR('CalculoFoda-1'!F7=1,'CalculoFoda-1'!G7=1,'CalculoFoda-1'!H7=1,'CalculoFoda-1'!I7=1)),NOT(OR('CalculoFoda-1'!F113=1,'CalculoFoda-1'!G113=1,'CalculoFoda-1'!H113=1,'CalculoFoda-1'!I113=1))),"sin dato: "&CalculosFoda!AF113,"")
B12: =+FormularioFODA!B12 -> Propuesta de Valor | C12: =+CalculosFoda!AF10 -> Diferenciación del producto | D12: =IF(AND(OR('CalculoFoda-1'!H10=1,'CalculoFoda-1'!I10=1),OR('CalculoFoda-1'!H131=1,'CalculoFoda-1'!I131=1)),CalculosFoda!AF131,"") | E12: =IF(AND(OR('CalculoFoda-1'!H10=1,'CalculoFoda-1'!I10=1),OR('CalculoFoda-1'!F131=1,'CalculoFoda-1'!G131=1)),CalculosFoda!AF131,"") | F12: =IF(AND(OR('CalculoFoda-1'!F10=1,'CalculoFoda-1'!G10=1),OR('CalculoFoda-1'!H131=1,'CalculoFoda-1'!I131=1)),CalculosFoda!AF131,"") | G12: =IF(AND(OR('CalculoFoda-1'!F10=1,'CalculoFoda-1'!G10=1),OR('CalculoFoda-1'!F131=1,'CalculoFoda-1'!G131=1)),CalculosFoda!AF131,"") -> Rivalidad y competidores internacionales | H12: =IF(OR(NOT(OR('CalculoFoda-1'!F10=1,'CalculoFoda-1'!G10=1,'CalculoFoda-1'!H10=1,'CalculoFoda-1'!I10=1)),NOT(OR('CalculoFoda-1'!F131=1,'CalculoFoda-1'!G131=1,'CalculoFoda-1'!H131=1,'CalculoFoda-1'!I131=1))),"sin dato: "&CalculosFoda!AF131,"")
D13: =IF(AND(OR('CalculoFoda-1'!H10=1,'CalculoFoda-1'!I10=1),OR('CalculoFoda-1'!H105=1,'CalculoFoda-1'!I105=1)),CalculosFoda!AF105,"") | E13: =IF(AND(OR('CalculoFoda-1'!H10=1,'CalculoFoda-1'!I10=1),OR('CalculoFoda-1'!F105=1,'CalculoFoda-1'!G105=1)),CalculosFoda!AF105,"") | F13: =IF(AND(OR('CalculoFoda-1'!F10=1,'CalculoFoda-1'!G10=1),OR('CalculoFoda-1'!H105=1,'CalculoFoda-1'!I105=1)),CalculosFoda!AF105,"") | G13: =IF(AND(OR('CalculoFoda-1'!F10=1,'CalculoFoda-1'!G10=1),OR('CalculoFoda-1'!F105=1,'CalculoFoda-1'!G105=1)),CalculosFoda!AF105,"") -> Afinidad cultural y hábitos de consumo | H13: =IF(OR(NOT(OR('CalculoFoda-1'!F10=1,'CalculoFoda-1'!G10=1,'CalculoFoda-1'!H10=1,'CalculoFoda-1'!I10=1)),NOT(OR('CalculoFoda-1'!F105=1,'CalculoFoda-1'!G105=1,'CalculoFoda-1'!H105=1,'CalculoFoda-1'!I105=1))),"sin dato: "&CalculosFoda!AF105,"")
C14: =+CalculosFoda!AF11 -> Adecuación a requisitos del mercado destino | D14: =IF(AND(OR('CalculoFoda-1'!H11=1,'CalculoFoda-1'!I11=1),OR('CalculoFoda-1'!H89=1,'CalculoFoda-1'!I89=1)),CalculosFoda!AF89,"") -> Barreras arancelarias y técnicas del destino | E14: =IF(AND(OR('CalculoFoda-1'!H11=1,'CalculoFoda-1'!I11=1),OR('CalculoFoda-1'!F89=1,'CalculoFoda-1'!G89=1)),CalculosFoda!AF89,"") | F14: =IF(AND(OR('CalculoFoda-1'!F11=1,'CalculoFoda-1'!G11=1),OR('CalculoFoda-1'!H89=1,'CalculoFoda-1'!I89=1)),CalculosFoda!AF89,"") | G14: =IF(AND(OR('CalculoFoda-1'!F11=1,'CalculoFoda-1'!G11=1),OR('CalculoFoda-1'!F89=1,'CalculoFoda-1'!G89=1)),CalculosFoda!AF89,"") | H14: =IF(OR(NOT(OR('CalculoFoda-1'!F11=1,'CalculoFoda-1'!G11=1,'CalculoFoda-1'!H11=1,'CalculoFoda-1'!I11=1)),NOT(OR('CalculoFoda-1'!F89=1,'CalculoFoda-1'!G89=1,'CalculoFoda-1'!H89=1,'CalculoFoda-1'!I89=1))),"sin dato: "&CalculosFoda!AF89,"")
D15: =IF(AND(OR('CalculoFoda-1'!H11=1,'CalculoFoda-1'!I11=1),OR('CalculoFoda-1'!H146=1,'CalculoFoda-1'!I146=1)),CalculosFoda!AF146,"") | E15: =IF(AND(OR('CalculoFoda-1'!H11=1,'CalculoFoda-1'!I11=1),OR('CalculoFoda-1'!F146=1,'CalculoFoda-1'!G146=1)),CalculosFoda!AF146,"") -> Requisitos sanitarios y fitosanitarios del destino | F15: =IF(AND(OR('CalculoFoda-1'!F11=1,'CalculoFoda-1'!G11=1),OR('CalculoFoda-1'!H146=1,'CalculoFoda-1'!I146=1)),CalculosFoda!AF146,"") | G15: =IF(AND(OR('CalculoFoda-1'!F11=1,'CalculoFoda-1'!G11=1),OR('CalculoFoda-1'!F146=1,'CalculoFoda-1'!G146=1)),CalculosFoda!AF146,"") | H15: =IF(OR(NOT(OR('CalculoFoda-1'!F11=1,'CalculoFoda-1'!G11=1,'CalculoFoda-1'!H11=1,'CalculoFoda-1'!I11=1)),NOT(OR('CalculoFoda-1'!F146=1,'CalculoFoda-1'!G146=1,'CalculoFoda-1'!H146=1,'CalculoFoda-1'!I146=1))),"sin dato: "&CalculosFoda!AF146,"")
C16: =+CalculosFoda!AF12 -> Certificaciones y normas de producto | D16: =IF(AND(OR('CalculoFoda-1'!H12=1,'CalculoFoda-1'!I12=1),OR('CalculoFoda-1'!H147=1,'CalculoFoda-1'!I147=1)),CalculosFoda!AF147,"") | E16: =IF(AND(OR('CalculoFoda-1'!H12=1,'CalculoFoda-1'!I12=1),OR('CalculoFoda-1'!F147=1,'CalculoFoda-1'!G147=1)),CalculosFoda!AF147,"") | F16: =IF(AND(OR('CalculoFoda-1'!F12=1,'CalculoFoda-1'!G12=1),OR('CalculoFoda-1'!H147=1,'CalculoFoda-1'!I147=1)),CalculosFoda!AF147,"") -> Certificaciones exigidas por los compradores | G16: =IF(AND(OR('CalculoFoda-1'!F12=1,'CalculoFoda-1'!G12=1),OR('CalculoFoda-1'!F147=1,'CalculoFoda-1'!G147=1)),CalculosFoda!AF147,"") | H16: =IF(OR(NOT(OR('CalculoFoda-1'!F12=1,'CalculoFoda-1'!G12=1,'CalculoFoda-1'!H12=1,'CalculoFoda-1'!I12=1)),NOT(OR('CalculoFoda-1'!F147=1,'CalculoFoda-1'!G147=1,'CalculoFoda-1'!H147=1,'CalculoFoda-1'!I147=1))),"sin dato: "&CalculosFoda!AF147,"")
D17: =IF(AND(OR('CalculoFoda-1'!H12=1,'CalculoFoda-1'!I12=1),OR('CalculoFoda-1'!H89=1,'CalculoFoda-1'!I89=1)),CalculosFoda!AF89,"") | E17: =IF(AND(OR('CalculoFoda-1'!H12=1,'CalculoFoda-1'!I12=1),OR('CalculoFoda-1'!F89=1,'CalculoFoda-1'!G89=1)),CalculosFoda!AF89,"") | F17: =IF(AND(OR('CalculoFoda-1'!F12=1,'CalculoFoda-1'!G12=1),OR('CalculoFoda-1'!H89=1,'CalculoFoda-1'!I89=1)),CalculosFoda!AF89,"") -> Barreras arancelarias y técnicas del destino | G17: =IF(AND(OR('CalculoFoda-1'!F12=1,'CalculoFoda-1'!G12=1),OR('CalculoFoda-1'!F89=1,'CalculoFoda-1'!G89=1)),CalculosFoda!AF89,"") | H17: =IF(OR(NOT(OR('CalculoFoda-1'!F12=1,'CalculoFoda-1'!G12=1,'CalculoFoda-1'!H12=1,'CalculoFoda-1'!I12=1)),NOT(OR('CalculoFoda-1'!F89=1,'CalculoFoda-1'!G89=1,'CalculoFoda-1'!H89=1,'CalculoFoda-1'!I89=1))),"sin dato: "&CalculosFoda!AF89,"")
C18: =+CalculosFoda!AF13 -> Competitividad de precio internacional | D18: =IF(AND(OR('CalculoFoda-1'!H13=1,'CalculoFoda-1'!I13=1),OR('CalculoFoda-1'!H97=1,'CalculoFoda-1'!I97=1)),CalculosFoda!AF97,"") | E18: =IF(AND(OR('CalculoFoda-1'!H13=1,'CalculoFoda-1'!I13=1),OR('CalculoFoda-1'!F97=1,'CalculoFoda-1'!G97=1)),CalculosFoda!AF97,"") -> Tipo de cambio y competitividad | F18: =IF(AND(OR('CalculoFoda-1'!F13=1,'CalculoFoda-1'!G13=1),OR('CalculoFoda-1'!H97=1,'CalculoFoda-1'!I97=1)),CalculosFoda!AF97,"") | G18: =IF(AND(OR('CalculoFoda-1'!F13=1,'CalculoFoda-1'!G13=1),OR('CalculoFoda-1'!F97=1,'CalculoFoda-1'!G97=1)),CalculosFoda!AF97,"") | H18: =IF(OR(NOT(OR('CalculoFoda-1'!F13=1,'CalculoFoda-1'!G13=1,'CalculoFoda-1'!H13=1,'CalculoFoda-1'!I13=1)),NOT(OR('CalculoFoda-1'!F97=1,'CalculoFoda-1'!G97=1,'CalculoFoda-1'!H97=1,'CalculoFoda-1'!I97=1))),"sin dato: "&CalculosFoda!AF97,"")
D19: =IF(AND(OR('CalculoFoda-1'!H13=1,'CalculoFoda-1'!I13=1),OR('CalculoFoda-1'!H102=1,'CalculoFoda-1'!I102=1)),CalculosFoda!AF102,"") -> Precios internacionales del producto | E19: =IF(AND(OR('CalculoFoda-1'!H13=1,'CalculoFoda-1'!I13=1),OR('CalculoFoda-1'!F102=1,'CalculoFoda-1'!G102=1)),CalculosFoda!AF102,"") | F19: =IF(AND(OR('CalculoFoda-1'!F13=1,'CalculoFoda-1'!G13=1),OR('CalculoFoda-1'!H102=1,'CalculoFoda-1'!I102=1)),CalculosFoda!AF102,"") | G19: =IF(AND(OR('CalculoFoda-1'!F13=1,'CalculoFoda-1'!G13=1),OR('CalculoFoda-1'!F102=1,'CalculoFoda-1'!G102=1)),CalculosFoda!AF102,"") | H19: =IF(OR(NOT(OR('CalculoFoda-1'!F13=1,'CalculoFoda-1'!G13=1,'CalculoFoda-1'!H13=1,'CalculoFoda-1'!I13=1)),NOT(OR('CalculoFoda-1'!F102=1,'CalculoFoda-1'!G102=1,'CalculoFoda-1'!H102=1,'CalculoFoda-1'!I102=1))),"sin dato: "&CalculosFoda!AF102,"")
D20: =IF(AND(OR('CalculoFoda-1'!H13=1,'CalculoFoda-1'!I13=1),OR('CalculoFoda-1'!H131=1,'CalculoFoda-1'!I131=1)),CalculosFoda!AF131,"") | E20: =IF(AND(OR('CalculoFoda-1'!H13=1,'CalculoFoda-1'!I13=1),OR('CalculoFoda-1'!F131=1,'CalculoFoda-1'!G131=1)),CalculosFoda!AF131,"") -> Rivalidad y competidores internacionales | F20: =IF(AND(OR('CalculoFoda-1'!F13=1,'CalculoFoda-1'!G13=1),OR('CalculoFoda-1'!H131=1,'CalculoFoda-1'!I131=1)),CalculosFoda!AF131,"") | G20: =IF(AND(OR('CalculoFoda-1'!F13=1,'CalculoFoda-1'!G13=1),OR('CalculoFoda-1'!F131=1,'CalculoFoda-1'!G131=1)),CalculosFoda!AF131,"") | H20: =IF(OR(NOT(OR('CalculoFoda-1'!F13=1,'CalculoFoda-1'!G13=1,'CalculoFoda-1'!H13=1,'CalculoFoda-1'!I13=1)),NOT(OR('CalculoFoda-1'!F131=1,'CalculoFoda-1'!G131=1,'CalculoFoda-1'!H131=1,'CalculoFoda-1'!I131=1))),"sin dato: "&CalculosFoda!AF131,"")
C21: =+CalculosFoda!AF14 -> Marca, presentación y material comercial | D21: =IF(AND(OR('CalculoFoda-1'!H14=1,'CalculoFoda-1'!I14=1),OR('CalculoFoda-1'!H92=1,'CalculoFoda-1'!I92=1)),CalculosFoda!AF92,"") -> Propiedad intelectual y seguridad jurídica | E21: =IF(AND(OR('CalculoFoda-1'!H14=1,'CalculoFoda-1'!I14=1),OR('CalculoFoda-1'!F92=1,'CalculoFoda-1'!G92=1)),CalculosFoda!AF92,"") | F21: =IF(AND(OR('CalculoFoda-1'!F14=1,'CalculoFoda-1'!G14=1),OR('CalculoFoda-1'!H92=1,'CalculoFoda-1'!I92=1)),CalculosFoda!AF92,"") | G21: =IF(AND(OR('CalculoFoda-1'!F14=1,'CalculoFoda-1'!G14=1),OR('CalculoFoda-1'!F92=1,'CalculoFoda-1'!G92=1)),CalculosFoda!AF92,"") | H21: =IF(OR(NOT(OR('CalculoFoda-1'!F14=1,'CalculoFoda-1'!G14=1,'CalculoFoda-1'!H14=1,'CalculoFoda-1'!I14=1)),NOT(OR('CalculoFoda-1'!F92=1,'CalculoFoda-1'!G92=1,'CalculoFoda-1'!H92=1,'CalculoFoda-1'!I92=1))),"sin dato: "&CalculosFoda!AF92,"")
C22: =+CalculosFoda!AF15 -> Origen e identidad regional | D22: =IF(AND(OR('CalculoFoda-1'!H15=1,'CalculoFoda-1'!I15=1),OR('CalculoFoda-1'!H107=1,'CalculoFoda-1'!I107=1)),CalculosFoda!AF107,"") | E22: =IF(AND(OR('CalculoFoda-1'!H15=1,'CalculoFoda-1'!I15=1),OR('CalculoFoda-1'!F107=1,'CalculoFoda-1'!G107=1)),CalculosFoda!AF107,"") | F22: =IF(AND(OR('CalculoFoda-1'!F15=1,'CalculoFoda-1'!G15=1),OR('CalculoFoda-1'!H107=1,'CalculoFoda-1'!I107=1)),CalculosFoda!AF107,"") | G22: =IF(AND(OR('CalculoFoda-1'!F15=1,'CalculoFoda-1'!G15=1),OR('CalculoFoda-1'!F107=1,'CalculoFoda-1'!G107=1)),CalculosFoda!AF107,"") -> Valoración del origen y la sustentabilidad | H22: =IF(OR(NOT(OR('CalculoFoda-1'!F15=1,'CalculoFoda-1'!G15=1,'CalculoFoda-1'!H15=1,'CalculoFoda-1'!I15=1)),NOT(OR('CalculoFoda-1'!F107=1,'CalculoFoda-1'!G107=1,'CalculoFoda-1'!H107=1,'CalculoFoda-1'!I107=1))),"sin dato: "&CalculosFoda!AF107,"")
D23: =IF(AND(OR('CalculoFoda-1'!H15=1,'CalculoFoda-1'!I15=1),OR('CalculoFoda-1'!H92=1,'CalculoFoda-1'!I92=1)),CalculosFoda!AF92,"") | E23: =IF(AND(OR('CalculoFoda-1'!H15=1,'CalculoFoda-1'!I15=1),OR('CalculoFoda-1'!F92=1,'CalculoFoda-1'!G92=1)),CalculosFoda!AF92,"") | F23: =IF(AND(OR('CalculoFoda-1'!F15=1,'CalculoFoda-1'!G15=1),OR('CalculoFoda-1'!H92=1,'CalculoFoda-1'!I92=1)),CalculosFoda!AF92,"") -> Propiedad intelectual y seguridad jurídica | G23: =IF(AND(OR('CalculoFoda-1'!F15=1,'CalculoFoda-1'!G15=1),OR('CalculoFoda-1'!F92=1,'CalculoFoda-1'!G92=1)),CalculosFoda!AF92,"") | H23: =IF(OR(NOT(OR('CalculoFoda-1'!F15=1,'CalculoFoda-1'!G15=1,'CalculoFoda-1'!H15=1,'CalculoFoda-1'!I15=1)),NOT(OR('CalculoFoda-1'!F92=1,'CalculoFoda-1'!G92=1,'CalculoFoda-1'!H92=1,'CalculoFoda-1'!I92=1))),"sin dato: "&CalculosFoda!AF92,"")
C24: =+CalculosFoda!AF16 -> Amplitud de línea y desarrollo de nuevos productos | D24: =IF(AND(OR('CalculoFoda-1'!H16=1,'CalculoFoda-1'!I16=1),OR('CalculoFoda-1'!H112=1,'CalculoFoda-1'!I112=1)),CalculosFoda!AF112,"") | E24: =IF(AND(OR('CalculoFoda-1'!H16=1,'CalculoFoda-1'!I16=1),OR('CalculoFoda-1'!F112=1,'CalculoFoda-1'!G112=1)),CalculosFoda!AF112,"") | F24: =IF(AND(OR('CalculoFoda-1'!F16=1,'CalculoFoda-1'!G16=1),OR('CalculoFoda-1'!H112=1,'CalculoFoda-1'!I112=1)),CalculosFoda!AF112,"") | G24: =IF(AND(OR('CalculoFoda-1'!F16=1,'CalculoFoda-1'!G16=1),OR('CalculoFoda-1'!F112=1,'CalculoFoda-1'!G112=1)),CalculosFoda!AF112,"") -> Avances tecnológicos del sector | H24: =IF(OR(NOT(OR('CalculoFoda-1'!F16=1,'CalculoFoda-1'!G16=1,'CalculoFoda-1'!H16=1,'CalculoFoda-1'!I16=1)),NOT(OR('CalculoFoda-1'!F112=1,'CalculoFoda-1'!G112=1,'CalculoFoda-1'!H112=1,'CalculoFoda-1'!I112=1))),"sin dato: "&CalculosFoda!AF112,"")
D25: =IF(AND(OR('CalculoFoda-1'!H16=1,'CalculoFoda-1'!I16=1),OR('CalculoFoda-1'!H129=1,'CalculoFoda-1'!I129=1)),CalculosFoda!AF129,"") | E25: =IF(AND(OR('CalculoFoda-1'!H16=1,'CalculoFoda-1'!I16=1),OR('CalculoFoda-1'!F129=1,'CalculoFoda-1'!G129=1)),CalculosFoda!AF129,"") | F25: =IF(AND(OR('CalculoFoda-1'!F16=1,'CalculoFoda-1'!G16=1),OR('CalculoFoda-1'!H129=1,'CalculoFoda-1'!I129=1)),CalculosFoda!AF129,"") | G25: =IF(AND(OR('CalculoFoda-1'!F16=1,'CalculoFoda-1'!G16=1),OR('CalculoFoda-1'!F129=1,'CalculoFoda-1'!G129=1)),CalculosFoda!AF129,"") -> Tamaño y crecimiento del mercado destino | H25: =IF(OR(NOT(OR('CalculoFoda-1'!F16=1,'CalculoFoda-1'!G16=1,'CalculoFoda-1'!H16=1,'CalculoFoda-1'!I16=1)),NOT(OR('CalculoFoda-1'!F129=1,'CalculoFoda-1'!G129=1,'CalculoFoda-1'!H129=1,'CalculoFoda-1'!I129=1))),"sin dato: "&CalculosFoda!AF129,"")
B27: =+FormularioFODA!B21 -> Canales | C27: =+CalculosFoda!AF19 -> Canales de comercialización externos | D27: =IF(AND(OR('CalculoFoda-1'!H19=1,'CalculoFoda-1'!I19=1),OR('CalculoFoda-1'!H127=1,'CalculoFoda-1'!I127=1)),CalculosFoda!AF127,"") | E27: =IF(AND(OR('CalculoFoda-1'!H19=1,'CalculoFoda-1'!I19=1),OR('CalculoFoda-1'!F127=1,'CalculoFoda-1'!G127=1)),CalculosFoda!AF127,"") | F27: =IF(AND(OR('CalculoFoda-1'!F19=1,'CalculoFoda-1'!G19=1),OR('CalculoFoda-1'!H127=1,'CalculoFoda-1'!I127=1)),CalculosFoda!AF127,"") | G27: =IF(AND(OR('CalculoFoda-1'!F19=1,'CalculoFoda-1'!G19=1),OR('CalculoFoda-1'!F127=1,'CalculoFoda-1'!G127=1)),CalculosFoda!AF127,"") | H27: =IF(OR(NOT(OR('CalculoFoda-1'!F19=1,'CalculoFoda-1'!G19=1,'CalculoFoda-1'!H19=1,'CalculoFoda-1'!I19=1)),NOT(OR('CalculoFoda-1'!F127=1,'CalculoFoda-1'!G127=1,'CalculoFoda-1'!H127=1,'CalculoFoda-1'!I127=1))),"sin dato: "&CalculosFoda!AF127,"") -> sin dato: Barreras de entrada al mercado destino
D28: =IF(AND(OR('CalculoFoda-1'!H19=1,'CalculoFoda-1'!I19=1),OR('CalculoFoda-1'!H113=1,'CalculoFoda-1'!I113=1)),CalculosFoda!AF113,"") | E28: =IF(AND(OR('CalculoFoda-1'!H19=1,'CalculoFoda-1'!I19=1),OR('CalculoFoda-1'!F113=1,'CalculoFoda-1'!G113=1)),CalculosFoda!AF113,"") -> Conectividad y plataformas de comercio electrónico | F28: =IF(AND(OR('CalculoFoda-1'!F19=1,'CalculoFoda-1'!G19=1),OR('CalculoFoda-1'!H113=1,'CalculoFoda-1'!I113=1)),CalculosFoda!AF113,"") | G28: =IF(AND(OR('CalculoFoda-1'!F19=1,'CalculoFoda-1'!G19=1),OR('CalculoFoda-1'!F113=1,'CalculoFoda-1'!G113=1)),CalculosFoda!AF113,"") | H28: =IF(OR(NOT(OR('CalculoFoda-1'!F19=1,'CalculoFoda-1'!G19=1,'CalculoFoda-1'!H19=1,'CalculoFoda-1'!I19=1)),NOT(OR('CalculoFoda-1'!F113=1,'CalculoFoda-1'!G113=1,'CalculoFoda-1'!H113=1,'CalculoFoda-1'!I113=1))),"sin dato: "&CalculosFoda!AF113,"")
C29: =+CalculosFoda!AF20 -> Presencia digital y venta online | D29: =IF(AND(OR('CalculoFoda-1'!H20=1,'CalculoFoda-1'!I20=1),OR('CalculoFoda-1'!H113=1,'CalculoFoda-1'!I113=1)),CalculosFoda!AF113,"") | E29: =IF(AND(OR('CalculoFoda-1'!H20=1,'CalculoFoda-1'!I20=1),OR('CalculoFoda-1'!F113=1,'CalculoFoda-1'!G113=1)),CalculosFoda!AF113,"") | F29: =IF(AND(OR('CalculoFoda-1'!F20=1,'CalculoFoda-1'!G20=1),OR('CalculoFoda-1'!H113=1,'CalculoFoda-1'!I113=1)),CalculosFoda!AF113,"") | G29: =IF(AND(OR('CalculoFoda-1'!F20=1,'CalculoFoda-1'!G20=1),OR('CalculoFoda-1'!F113=1,'CalculoFoda-1'!G113=1)),CalculosFoda!AF113,"") -> Conectividad y plataformas de comercio electrónico | H29: =IF(OR(NOT(OR('CalculoFoda-1'!F20=1,'CalculoFoda-1'!G20=1,'CalculoFoda-1'!H20=1,'CalculoFoda-1'!I20=1)),NOT(OR('CalculoFoda-1'!F113=1,'CalculoFoda-1'!G113=1,'CalculoFoda-1'!H113=1,'CalculoFoda-1'!I113=1))),"sin dato: "&CalculosFoda!AF113,"")
D30: =IF(AND(OR('CalculoFoda-1'!H20=1,'CalculoFoda-1'!I20=1),OR('CalculoFoda-1'!H114=1,'CalculoFoda-1'!I114=1)),CalculosFoda!AF114,"") | E30: =IF(AND(OR('CalculoFoda-1'!H20=1,'CalculoFoda-1'!I20=1),OR('CalculoFoda-1'!F114=1,'CalculoFoda-1'!G114=1)),CalculosFoda!AF114,"") | F30: =IF(AND(OR('CalculoFoda-1'!F20=1,'CalculoFoda-1'!G20=1),OR('CalculoFoda-1'!H114=1,'CalculoFoda-1'!I114=1)),CalculosFoda!AF114,"") | G30: =IF(AND(OR('CalculoFoda-1'!F20=1,'CalculoFoda-1'!G20=1),OR('CalculoFoda-1'!F114=1,'CalculoFoda-1'!G114=1)),CalculosFoda!AF114,"") -> Digitalización del comercio exterior | H30: =IF(OR(NOT(OR('CalculoFoda-1'!F20=1,'CalculoFoda-1'!G20=1,'CalculoFoda-1'!H20=1,'CalculoFoda-1'!I20=1)),NOT(OR('CalculoFoda-1'!F114=1,'CalculoFoda-1'!G114=1,'CalculoFoda-1'!H114=1,'CalculoFoda-1'!I114=1))),"sin dato: "&CalculosFoda!AF114,"")
C31: =+CalculosFoda!AF21 -> Promoción internacional | D31: =IF(AND(OR('CalculoFoda-1'!H21=1,'CalculoFoda-1'!I21=1),OR('CalculoFoda-1'!H91=1,'CalculoFoda-1'!I91=1)),CalculosFoda!AF91,"") | E31: =IF(AND(OR('CalculoFoda-1'!H21=1,'CalculoFoda-1'!I21=1),OR('CalculoFoda-1'!F91=1,'CalculoFoda-1'!G91=1)),CalculosFoda!AF91,"") | F31: =IF(AND(OR('CalculoFoda-1'!F21=1,'CalculoFoda-1'!G21=1),OR('CalculoFoda-1'!H91=1,'CalculoFoda-1'!I91=1)),CalculosFoda!AF91,"") | G31: =IF(AND(OR('CalculoFoda-1'!F21=1,'CalculoFoda-1'!G21=1),OR('CalculoFoda-1'!F91=1,'CalculoFoda-1'!G91=1)),CalculosFoda!AF91,"") -> Promoción y fomento a exportadores | H31: =IF(OR(NOT(OR('CalculoFoda-1'!F21=1,'CalculoFoda-1'!G21=1,'CalculoFoda-1'!H21=1,'CalculoFoda-1'!I21=1)),NOT(OR('CalculoFoda-1'!F91=1,'CalculoFoda-1'!G91=1,'CalculoFoda-1'!H91=1,'CalculoFoda-1'!I91=1))),"sin dato: "&CalculosFoda!AF91,"")
C32: =+CalculosFoda!AF22 -> Logística y embalaje de exportación | D32: =IF(AND(OR('CalculoFoda-1'!H22=1,'CalculoFoda-1'!I22=1),OR('CalculoFoda-1'!H118=1,'CalculoFoda-1'!I118=1)),CalculosFoda!AF118,"") | E32: =IF(AND(OR('CalculoFoda-1'!H22=1,'CalculoFoda-1'!I22=1),OR('CalculoFoda-1'!F118=1,'CalculoFoda-1'!G118=1)),CalculosFoda!AF118,"") | F32: =IF(AND(OR('CalculoFoda-1'!F22=1,'CalculoFoda-1'!G22=1),OR('CalculoFoda-1'!H118=1,'CalculoFoda-1'!I118=1)),CalculosFoda!AF118,"") | G32: =IF(AND(OR('CalculoFoda-1'!F22=1,'CalculoFoda-1'!G22=1),OR('CalculoFoda-1'!F118=1,'CalculoFoda-1'!G118=1)),CalculosFoda!AF118,"") -> Red vial y conectividad multimodal | H32: =IF(OR(NOT(OR('CalculoFoda-1'!F22=1,'CalculoFoda-1'!G22=1,'CalculoFoda-1'!H22=1,'CalculoFoda-1'!I22=1)),NOT(OR('CalculoFoda-1'!F118=1,'CalculoFoda-1'!G118=1,'CalculoFoda-1'!H118=1,'CalculoFoda-1'!I118=1))),"sin dato: "&CalculosFoda!AF118,"")
D33: =IF(AND(OR('CalculoFoda-1'!H22=1,'CalculoFoda-1'!I22=1),OR('CalculoFoda-1'!H119=1,'CalculoFoda-1'!I119=1)),CalculosFoda!AF119,"") | E33: =IF(AND(OR('CalculoFoda-1'!H22=1,'CalculoFoda-1'!I22=1),OR('CalculoFoda-1'!F119=1,'CalculoFoda-1'!G119=1)),CalculosFoda!AF119,"") | F33: =IF(AND(OR('CalculoFoda-1'!F22=1,'CalculoFoda-1'!G22=1),OR('CalculoFoda-1'!H119=1,'CalculoFoda-1'!I119=1)),CalculosFoda!AF119,"") | G33: =IF(AND(OR('CalculoFoda-1'!F22=1,'CalculoFoda-1'!G22=1),OR('CalculoFoda-1'!F119=1,'CalculoFoda-1'!G119=1)),CalculosFoda!AF119,"") -> Pasos de frontera y puentes internacionales | H33: =IF(OR(NOT(OR('CalculoFoda-1'!F22=1,'CalculoFoda-1'!G22=1,'CalculoFoda-1'!H22=1,'CalculoFoda-1'!I22=1)),NOT(OR('CalculoFoda-1'!F119=1,'CalculoFoda-1'!G119=1,'CalculoFoda-1'!H119=1,'CalculoFoda-1'!I119=1))),"sin dato: "&CalculosFoda!AF119,"")
D34: =IF(AND(OR('CalculoFoda-1'!H22=1,'CalculoFoda-1'!I22=1),OR('CalculoFoda-1'!H121=1,'CalculoFoda-1'!I121=1)),CalculosFoda!AF121,"") | E34: =IF(AND(OR('CalculoFoda-1'!H22=1,'CalculoFoda-1'!I22=1),OR('CalculoFoda-1'!F121=1,'CalculoFoda-1'!G121=1)),CalculosFoda!AF121,"") | F34: =IF(AND(OR('CalculoFoda-1'!F22=1,'CalculoFoda-1'!G22=1),OR('CalculoFoda-1'!H121=1,'CalculoFoda-1'!I121=1)),CalculosFoda!AF121,"") | G34: =IF(AND(OR('CalculoFoda-1'!F22=1,'CalculoFoda-1'!G22=1),OR('CalculoFoda-1'!F121=1,'CalculoFoda-1'!G121=1)),CalculosFoda!AF121,"") | H34: =IF(OR(NOT(OR('CalculoFoda-1'!F22=1,'CalculoFoda-1'!G22=1,'CalculoFoda-1'!H22=1,'CalculoFoda-1'!I22=1)),NOT(OR('CalculoFoda-1'!F121=1,'CalculoFoda-1'!G121=1,'CalculoFoda-1'!H121=1,'CalculoFoda-1'!I121=1))),"sin dato: "&CalculosFoda!AF121,"") -> sin dato: Costo y disponibilidad de fletes
C35: =+CalculosFoda!AF23 -> Gestión documental y aduanera | D35: =IF(AND(OR('CalculoFoda-1'!H23=1,'CalculoFoda-1'!I23=1),OR('CalculoFoda-1'!H90=1,'CalculoFoda-1'!I90=1)),CalculosFoda!AF90,"") | E35: =IF(AND(OR('CalculoFoda-1'!H23=1,'CalculoFoda-1'!I23=1),OR('CalculoFoda-1'!F90=1,'CalculoFoda-1'!G90=1)),CalculosFoda!AF90,"") | F35: =IF(AND(OR('CalculoFoda-1'!F23=1,'CalculoFoda-1'!G23=1),OR('CalculoFoda-1'!H90=1,'CalculoFoda-1'!I90=1)),CalculosFoda!AF90,"") | G35: =IF(AND(OR('CalculoFoda-1'!F23=1,'CalculoFoda-1'!G23=1),OR('CalculoFoda-1'!F90=1,'CalculoFoda-1'!G90=1)),CalculosFoda!AF90,"") -> Trámites y aduana | H35: =IF(OR(NOT(OR('CalculoFoda-1'!F23=1,'CalculoFoda-1'!G23=1,'CalculoFoda-1'!H23=1,'CalculoFoda-1'!I23=1)),NOT(OR('CalculoFoda-1'!F90=1,'CalculoFoda-1'!G90=1,'CalculoFoda-1'!H90=1,'CalculoFoda-1'!I90=1))),"sin dato: "&CalculosFoda!AF90,"")
D36: =IF(AND(OR('CalculoFoda-1'!H23=1,'CalculoFoda-1'!I23=1),OR('CalculoFoda-1'!H122=1,'CalculoFoda-1'!I122=1)),CalculosFoda!AF122,"") | E36: =IF(AND(OR('CalculoFoda-1'!H23=1,'CalculoFoda-1'!I23=1),OR('CalculoFoda-1'!F122=1,'CalculoFoda-1'!G122=1)),CalculosFoda!AF122,"") | F36: =IF(AND(OR('CalculoFoda-1'!F23=1,'CalculoFoda-1'!G23=1),OR('CalculoFoda-1'!H122=1,'CalculoFoda-1'!I122=1)),CalculosFoda!AF122,"") | G36: =IF(AND(OR('CalculoFoda-1'!F23=1,'CalculoFoda-1'!G23=1),OR('CalculoFoda-1'!F122=1,'CalculoFoda-1'!G122=1)),CalculosFoda!AF122,"") -> Servicios aduaneros locales | H36: =IF(OR(NOT(OR('CalculoFoda-1'!F23=1,'CalculoFoda-1'!G23=1,'CalculoFoda-1'!H23=1,'CalculoFoda-1'!I23=1)),NOT(OR('CalculoFoda-1'!F122=1,'CalculoFoda-1'!G122=1,'CalculoFoda-1'!H122=1,'CalculoFoda-1'!I122=1))),"sin dato: "&CalculosFoda!AF122,"")
D37: =IF(AND(OR('CalculoFoda-1'!H23=1,'CalculoFoda-1'!I23=1),OR('CalculoFoda-1'!H114=1,'CalculoFoda-1'!I114=1)),CalculosFoda!AF114,"") | E37: =IF(AND(OR('CalculoFoda-1'!H23=1,'CalculoFoda-1'!I23=1),OR('CalculoFoda-1'!F114=1,'CalculoFoda-1'!G114=1)),CalculosFoda!AF114,"") | F37: =IF(AND(OR('CalculoFoda-1'!F23=1,'CalculoFoda-1'!G23=1),OR('CalculoFoda-1'!H114=1,'CalculoFoda-1'!I114=1)),CalculosFoda!AF114,"") | G37: =IF(AND(OR('CalculoFoda-1'!F23=1,'CalculoFoda-1'!G23=1),OR('CalculoFoda-1'!F114=1,'CalculoFoda-1'!G114=1)),CalculosFoda!AF114,"") -> Digitalización del comercio exterior | H37: =IF(OR(NOT(OR('CalculoFoda-1'!F23=1,'CalculoFoda-1'!G23=1,'CalculoFoda-1'!H23=1,'CalculoFoda-1'!I23=1)),NOT(OR('CalculoFoda-1'!F114=1,'CalculoFoda-1'!G114=1,'CalculoFoda-1'!H114=1,'CalculoFoda-1'!I114=1))),"sin dato: "&CalculosFoda!AF114,"")
B39: =+FormularioFODA!B28 -> Relación con Clientes | C39: =+CalculosFoda!AF26 -> Atención y postventa internacional | H39: variable independiente
C40: =+CalculosFoda!AF27 -> Comunicación en idioma extranjero | D40: =IF(AND(OR('CalculoFoda-1'!H27=1,'CalculoFoda-1'!I27=1),OR('CalculoFoda-1'!H106=1,'CalculoFoda-1'!I106=1)),CalculosFoda!AF106,"") | E40: =IF(AND(OR('CalculoFoda-1'!H27=1,'CalculoFoda-1'!I27=1),OR('CalculoFoda-1'!F106=1,'CalculoFoda-1'!G106=1)),CalculosFoda!AF106,"") | F40: =IF(AND(OR('CalculoFoda-1'!F27=1,'CalculoFoda-1'!G27=1),OR('CalculoFoda-1'!H106=1,'CalculoFoda-1'!I106=1)),CalculosFoda!AF106,"") -> Idioma y cercanía cultural | G40: =IF(AND(OR('CalculoFoda-1'!F27=1,'CalculoFoda-1'!G27=1),OR('CalculoFoda-1'!F106=1,'CalculoFoda-1'!G106=1)),CalculosFoda!AF106,"") | H40: =IF(OR(NOT(OR('CalculoFoda-1'!F27=1,'CalculoFoda-1'!G27=1,'CalculoFoda-1'!H27=1,'CalculoFoda-1'!I27=1)),NOT(OR('CalculoFoda-1'!F106=1,'CalculoFoda-1'!G106=1,'CalculoFoda-1'!H106=1,'CalculoFoda-1'!I106=1))),"sin dato: "&CalculosFoda!AF106,"")
C41: =+CalculosFoda!AF28 -> Contratos y condiciones con compradores | D41: =IF(AND(OR('CalculoFoda-1'!H28=1,'CalculoFoda-1'!I28=1),OR('CalculoFoda-1'!H92=1,'CalculoFoda-1'!I92=1)),CalculosFoda!AF92,"") | E41: =IF(AND(OR('CalculoFoda-1'!H28=1,'CalculoFoda-1'!I28=1),OR('CalculoFoda-1'!F92=1,'CalculoFoda-1'!G92=1)),CalculosFoda!AF92,"") | F41: =IF(AND(OR('CalculoFoda-1'!F28=1,'CalculoFoda-1'!G28=1),OR('CalculoFoda-1'!H92=1,'CalculoFoda-1'!I92=1)),CalculosFoda!AF92,"") -> Propiedad intelectual y seguridad jurídica | G41: =IF(AND(OR('CalculoFoda-1'!F28=1,'CalculoFoda-1'!G28=1),OR('CalculoFoda-1'!F92=1,'CalculoFoda-1'!G92=1)),CalculosFoda!AF92,"") | H41: =IF(OR(NOT(OR('CalculoFoda-1'!F28=1,'CalculoFoda-1'!G28=1,'CalculoFoda-1'!H28=1,'CalculoFoda-1'!I28=1)),NOT(OR('CalculoFoda-1'!F92=1,'CalculoFoda-1'!G92=1,'CalculoFoda-1'!H92=1,'CalculoFoda-1'!I92=1))),"sin dato: "&CalculosFoda!AF92,"")
C42: =+CalculosFoda!AF29 -> Fidelización y recompra | D42: =IF(AND(OR('CalculoFoda-1'!H29=1,'CalculoFoda-1'!I29=1),OR('CalculoFoda-1'!H128=1,'CalculoFoda-1'!I128=1)),CalculosFoda!AF128,"") | E42: =IF(AND(OR('CalculoFoda-1'!H29=1,'CalculoFoda-1'!I29=1),OR('CalculoFoda-1'!F128=1,'CalculoFoda-1'!G128=1)),CalculosFoda!AF128,"") | F42: =IF(AND(OR('CalculoFoda-1'!F29=1,'CalculoFoda-1'!G29=1),OR('CalculoFoda-1'!H128=1,'CalculoFoda-1'!I128=1)),CalculosFoda!AF128,"") | G42: =IF(AND(OR('CalculoFoda-1'!F29=1,'CalculoFoda-1'!G29=1),OR('CalculoFoda-1'!F128=1,'CalculoFoda-1'!G128=1)),CalculosFoda!AF128,"") -> Costos de cambio de los clientes externos | H42: =IF(OR(NOT(OR('CalculoFoda-1'!F29=1,'CalculoFoda-1'!G29=1,'CalculoFoda-1'!H29=1,'CalculoFoda-1'!I29=1)),NOT(OR('CalculoFoda-1'!F128=1,'CalculoFoda-1'!G128=1,'CalculoFoda-1'!H128=1,'CalculoFoda-1'!I128=1))),"sin dato: "&CalculosFoda!AF128,"")
C43: =+CalculosFoda!AF30 -> Gestión de reclamos y devoluciones | H43: variable independiente
B45: =+FormularioFODA!B35 -> Fuentes de Ingresos | C45: =+CalculosFoda!AF33 -> Evolución de ventas | D45: =IF(AND(OR('CalculoFoda-1'!H33=1,'CalculoFoda-1'!I33=1),OR('CalculoFoda-1'!H95=1,'CalculoFoda-1'!I95=1)),CalculosFoda!AF95,"") | E45: =IF(AND(OR('CalculoFoda-1'!H33=1,'CalculoFoda-1'!I33=1),OR('CalculoFoda-1'!F95=1,'CalculoFoda-1'!G95=1)),CalculosFoda!AF95,"") -> Crecimiento económico y ciclo | F45: =IF(AND(OR('CalculoFoda-1'!F33=1,'CalculoFoda-1'!G33=1),OR('CalculoFoda-1'!H95=1,'CalculoFoda-1'!I95=1)),CalculosFoda!AF95,"") | G45: =IF(AND(OR('CalculoFoda-1'!F33=1,'CalculoFoda-1'!G33=1),OR('CalculoFoda-1'!F95=1,'CalculoFoda-1'!G95=1)),CalculosFoda!AF95,"") | H45: =IF(OR(NOT(OR('CalculoFoda-1'!F33=1,'CalculoFoda-1'!G33=1,'CalculoFoda-1'!H33=1,'CalculoFoda-1'!I33=1)),NOT(OR('CalculoFoda-1'!F95=1,'CalculoFoda-1'!G95=1,'CalculoFoda-1'!H95=1,'CalculoFoda-1'!I95=1))),"sin dato: "&CalculosFoda!AF95,"")
D46: =IF(AND(OR('CalculoFoda-1'!H33=1,'CalculoFoda-1'!I33=1),OR('CalculoFoda-1'!H96=1,'CalculoFoda-1'!I96=1)),CalculosFoda!AF96,"") | E46: =IF(AND(OR('CalculoFoda-1'!H33=1,'CalculoFoda-1'!I33=1),OR('CalculoFoda-1'!F96=1,'CalculoFoda-1'!G96=1)),CalculosFoda!AF96,"") -> Crecimiento sectorial del rubro | F46: =IF(AND(OR('CalculoFoda-1'!F33=1,'CalculoFoda-1'!G33=1),OR('CalculoFoda-1'!H96=1,'CalculoFoda-1'!I96=1)),CalculosFoda!AF96,"") | G46: =IF(AND(OR('CalculoFoda-1'!F33=1,'CalculoFoda-1'!G33=1),OR('CalculoFoda-1'!F96=1,'CalculoFoda-1'!G96=1)),CalculosFoda!AF96,"") | H46: =IF(OR(NOT(OR('CalculoFoda-1'!F33=1,'CalculoFoda-1'!G33=1,'CalculoFoda-1'!H33=1,'CalculoFoda-1'!I33=1)),NOT(OR('CalculoFoda-1'!F96=1,'CalculoFoda-1'!G96=1,'CalculoFoda-1'!H96=1,'CalculoFoda-1'!I96=1))),"sin dato: "&CalculosFoda!AF96,"")
C47: =+CalculosFoda!AF34 -> Fijación de precio de exportación | D47: =IF(AND(OR('CalculoFoda-1'!H34=1,'CalculoFoda-1'!I34=1),OR('CalculoFoda-1'!H97=1,'CalculoFoda-1'!I97=1)),CalculosFoda!AF97,"") | E47: =IF(AND(OR('CalculoFoda-1'!H34=1,'CalculoFoda-1'!I34=1),OR('CalculoFoda-1'!F97=1,'CalculoFoda-1'!G97=1)),CalculosFoda!AF97,"") -> Tipo de cambio y competitividad | F47: =IF(AND(OR('CalculoFoda-1'!F34=1,'CalculoFoda-1'!G34=1),OR('CalculoFoda-1'!H97=1,'CalculoFoda-1'!I97=1)),CalculosFoda!AF97,"") | G47: =IF(AND(OR('CalculoFoda-1'!F34=1,'CalculoFoda-1'!G34=1),OR('CalculoFoda-1'!F97=1,'CalculoFoda-1'!G97=1)),CalculosFoda!AF97,"") | H47: =IF(OR(NOT(OR('CalculoFoda-1'!F34=1,'CalculoFoda-1'!G34=1,'CalculoFoda-1'!H34=1,'CalculoFoda-1'!I34=1)),NOT(OR('CalculoFoda-1'!F97=1,'CalculoFoda-1'!G97=1,'CalculoFoda-1'!H97=1,'CalculoFoda-1'!I97=1))),"sin dato: "&CalculosFoda!AF97,"")
D48: =IF(AND(OR('CalculoFoda-1'!H34=1,'CalculoFoda-1'!I34=1),OR('CalculoFoda-1'!H102=1,'CalculoFoda-1'!I102=1)),CalculosFoda!AF102,"") -> Precios internacionales del producto | E48: =IF(AND(OR('CalculoFoda-1'!H34=1,'CalculoFoda-1'!I34=1),OR('CalculoFoda-1'!F102=1,'CalculoFoda-1'!G102=1)),CalculosFoda!AF102,"") | F48: =IF(AND(OR('CalculoFoda-1'!F34=1,'CalculoFoda-1'!G34=1),OR('CalculoFoda-1'!H102=1,'CalculoFoda-1'!I102=1)),CalculosFoda!AF102,"") | G48: =IF(AND(OR('CalculoFoda-1'!F34=1,'CalculoFoda-1'!G34=1),OR('CalculoFoda-1'!F102=1,'CalculoFoda-1'!G102=1)),CalculosFoda!AF102,"") | H48: =IF(OR(NOT(OR('CalculoFoda-1'!F34=1,'CalculoFoda-1'!G34=1,'CalculoFoda-1'!H34=1,'CalculoFoda-1'!I34=1)),NOT(OR('CalculoFoda-1'!F102=1,'CalculoFoda-1'!G102=1,'CalculoFoda-1'!H102=1,'CalculoFoda-1'!I102=1))),"sin dato: "&CalculosFoda!AF102,"")
C49: =+CalculosFoda!AF35 -> Margen del producto exportable | D49: =IF(AND(OR('CalculoFoda-1'!H35=1,'CalculoFoda-1'!I35=1),OR('CalculoFoda-1'!H101=1,'CalculoFoda-1'!I101=1)),CalculosFoda!AF101,"") | E49: =IF(AND(OR('CalculoFoda-1'!H35=1,'CalculoFoda-1'!I35=1),OR('CalculoFoda-1'!F101=1,'CalculoFoda-1'!G101=1)),CalculosFoda!AF101,"") | F49: =IF(AND(OR('CalculoFoda-1'!F35=1,'CalculoFoda-1'!G35=1),OR('CalculoFoda-1'!H101=1,'CalculoFoda-1'!I101=1)),CalculosFoda!AF101,"") | G49: =IF(AND(OR('CalculoFoda-1'!F35=1,'CalculoFoda-1'!G35=1),OR('CalculoFoda-1'!F101=1,'CalculoFoda-1'!G101=1)),CalculosFoda!AF101,"") | H49: =IF(OR(NOT(OR('CalculoFoda-1'!F35=1,'CalculoFoda-1'!G35=1,'CalculoFoda-1'!H35=1,'CalculoFoda-1'!I35=1)),NOT(OR('CalculoFoda-1'!F101=1,'CalculoFoda-1'!G101=1,'CalculoFoda-1'!H101=1,'CalculoFoda-1'!I101=1))),"sin dato: "&CalculosFoda!AF101,"") -> sin dato: Impuestos, derechos de exportación y reintegros
D50: =IF(AND(OR('CalculoFoda-1'!H35=1,'CalculoFoda-1'!I35=1),OR('CalculoFoda-1'!H98=1,'CalculoFoda-1'!I98=1)),CalculosFoda!AF98,"") | E50: =IF(AND(OR('CalculoFoda-1'!H35=1,'CalculoFoda-1'!I35=1),OR('CalculoFoda-1'!F98=1,'CalculoFoda-1'!G98=1)),CalculosFoda!AF98,"") | F50: =IF(AND(OR('CalculoFoda-1'!F35=1,'CalculoFoda-1'!G35=1),OR('CalculoFoda-1'!H98=1,'CalculoFoda-1'!I98=1)),CalculosFoda!AF98,"") | G50: =IF(AND(OR('CalculoFoda-1'!F35=1,'CalculoFoda-1'!G35=1),OR('CalculoFoda-1'!F98=1,'CalculoFoda-1'!G98=1)),CalculosFoda!AF98,"") | H50: =IF(OR(NOT(OR('CalculoFoda-1'!F35=1,'CalculoFoda-1'!G35=1,'CalculoFoda-1'!H35=1,'CalculoFoda-1'!I35=1)),NOT(OR('CalculoFoda-1'!F98=1,'CalculoFoda-1'!G98=1,'CalculoFoda-1'!H98=1,'CalculoFoda-1'!I98=1))),"sin dato: "&CalculosFoda!AF98,"") -> sin dato: Inflación y costos internos
C51: =+CalculosFoda!AF36 -> Medios y condiciones de cobro | D51: =IF(AND(OR('CalculoFoda-1'!H36=1,'CalculoFoda-1'!I36=1),OR('CalculoFoda-1'!H100=1,'CalculoFoda-1'!I100=1)),CalculosFoda!AF100,"") | E51: =IF(AND(OR('CalculoFoda-1'!H36=1,'CalculoFoda-1'!I36=1),OR('CalculoFoda-1'!F100=1,'CalculoFoda-1'!G100=1)),CalculosFoda!AF100,"") -> Cobros y acceso a divisas | F51: =IF(AND(OR('CalculoFoda-1'!F36=1,'CalculoFoda-1'!G36=1),OR('CalculoFoda-1'!H100=1,'CalculoFoda-1'!I100=1)),CalculosFoda!AF100,"") | G51: =IF(AND(OR('CalculoFoda-1'!F36=1,'CalculoFoda-1'!G36=1),OR('CalculoFoda-1'!F100=1,'CalculoFoda-1'!G100=1)),CalculosFoda!AF100,"") | H51: =IF(OR(NOT(OR('CalculoFoda-1'!F36=1,'CalculoFoda-1'!G36=1,'CalculoFoda-1'!H36=1,'CalculoFoda-1'!I36=1)),NOT(OR('CalculoFoda-1'!F100=1,'CalculoFoda-1'!G100=1,'CalculoFoda-1'!H100=1,'CalculoFoda-1'!I100=1))),"sin dato: "&CalculosFoda!AF100,"")
C52: =+CalculosFoda!AF37 -> Diversificación de ingresos | D52: =IF(AND(OR('CalculoFoda-1'!H37=1,'CalculoFoda-1'!I37=1),OR('CalculoFoda-1'!H130=1,'CalculoFoda-1'!I130=1)),CalculosFoda!AF130,"") -> Poder negociador de compradores e importadores | E52: =IF(AND(OR('CalculoFoda-1'!H37=1,'CalculoFoda-1'!I37=1),OR('CalculoFoda-1'!F130=1,'CalculoFoda-1'!G130=1)),CalculosFoda!AF130,"") | F52: =IF(AND(OR('CalculoFoda-1'!F37=1,'CalculoFoda-1'!G37=1),OR('CalculoFoda-1'!H130=1,'CalculoFoda-1'!I130=1)),CalculosFoda!AF130,"") | G52: =IF(AND(OR('CalculoFoda-1'!F37=1,'CalculoFoda-1'!G37=1),OR('CalculoFoda-1'!F130=1,'CalculoFoda-1'!G130=1)),CalculosFoda!AF130,"") | H52: =IF(OR(NOT(OR('CalculoFoda-1'!F37=1,'CalculoFoda-1'!G37=1,'CalculoFoda-1'!H37=1,'CalculoFoda-1'!I37=1)),NOT(OR('CalculoFoda-1'!F130=1,'CalculoFoda-1'!G130=1,'CalculoFoda-1'!H130=1,'CalculoFoda-1'!I130=1))),"sin dato: "&CalculosFoda!AF130,"")
C53: =+CalculosFoda!AF38 -> Resistencia a variaciones cambiarias | D53: =IF(AND(OR('CalculoFoda-1'!H38=1,'CalculoFoda-1'!I38=1),OR('CalculoFoda-1'!H97=1,'CalculoFoda-1'!I97=1)),CalculosFoda!AF97,"") | E53: =IF(AND(OR('CalculoFoda-1'!H38=1,'CalculoFoda-1'!I38=1),OR('CalculoFoda-1'!F97=1,'CalculoFoda-1'!G97=1)),CalculosFoda!AF97,"") | F53: =IF(AND(OR('CalculoFoda-1'!F38=1,'CalculoFoda-1'!G38=1),OR('CalculoFoda-1'!H97=1,'CalculoFoda-1'!I97=1)),CalculosFoda!AF97,"") | G53: =IF(AND(OR('CalculoFoda-1'!F38=1,'CalculoFoda-1'!G38=1),OR('CalculoFoda-1'!F97=1,'CalculoFoda-1'!G97=1)),CalculosFoda!AF97,"") -> Tipo de cambio y competitividad | H53: =IF(OR(NOT(OR('CalculoFoda-1'!F38=1,'CalculoFoda-1'!G38=1,'CalculoFoda-1'!H38=1,'CalculoFoda-1'!I38=1)),NOT(OR('CalculoFoda-1'!F97=1,'CalculoFoda-1'!G97=1,'CalculoFoda-1'!H97=1,'CalculoFoda-1'!I97=1))),"sin dato: "&CalculosFoda!AF97,"")
B55: =+FormularioFODA!B44 -> Recursos Clave | C55: =+CalculosFoda!AF41 -> Capacidad instalada y ociosa | D55: =IF(AND(OR('CalculoFoda-1'!H41=1,'CalculoFoda-1'!I41=1),OR('CalculoFoda-1'!H129=1,'CalculoFoda-1'!I129=1)),CalculosFoda!AF129,"") | E55: =IF(AND(OR('CalculoFoda-1'!H41=1,'CalculoFoda-1'!I41=1),OR('CalculoFoda-1'!F129=1,'CalculoFoda-1'!G129=1)),CalculosFoda!AF129,"") -> Tamaño y crecimiento del mercado destino | F55: =IF(AND(OR('CalculoFoda-1'!F41=1,'CalculoFoda-1'!G41=1),OR('CalculoFoda-1'!H129=1,'CalculoFoda-1'!I129=1)),CalculosFoda!AF129,"") | G55: =IF(AND(OR('CalculoFoda-1'!F41=1,'CalculoFoda-1'!G41=1),OR('CalculoFoda-1'!F129=1,'CalculoFoda-1'!G129=1)),CalculosFoda!AF129,"") | H55: =IF(OR(NOT(OR('CalculoFoda-1'!F41=1,'CalculoFoda-1'!G41=1,'CalculoFoda-1'!H41=1,'CalculoFoda-1'!I41=1)),NOT(OR('CalculoFoda-1'!F129=1,'CalculoFoda-1'!G129=1,'CalculoFoda-1'!H129=1,'CalculoFoda-1'!I129=1))),"sin dato: "&CalculosFoda!AF129,"")
C56: =+CalculosFoda!AF42 -> Estado y tecnología de la maquinaria | D56: =IF(AND(OR('CalculoFoda-1'!H42=1,'CalculoFoda-1'!I42=1),OR('CalculoFoda-1'!H112=1,'CalculoFoda-1'!I112=1)),CalculosFoda!AF112,"") | E56: =IF(AND(OR('CalculoFoda-1'!H42=1,'CalculoFoda-1'!I42=1),OR('CalculoFoda-1'!F112=1,'CalculoFoda-1'!G112=1)),CalculosFoda!AF112,"") -> Avances tecnológicos del sector | F56: =IF(AND(OR('CalculoFoda-1'!F42=1,'CalculoFoda-1'!G42=1),OR('CalculoFoda-1'!H112=1,'CalculoFoda-1'!I112=1)),CalculosFoda!AF112,"") | G56: =IF(AND(OR('CalculoFoda-1'!F42=1,'CalculoFoda-1'!G42=1),OR('CalculoFoda-1'!F112=1,'CalculoFoda-1'!G112=1)),CalculosFoda!AF112,"") | H56: =IF(OR(NOT(OR('CalculoFoda-1'!F42=1,'CalculoFoda-1'!G42=1,'CalculoFoda-1'!H42=1,'CalculoFoda-1'!I42=1)),NOT(OR('CalculoFoda-1'!F112=1,'CalculoFoda-1'!G112=1,'CalculoFoda-1'!H112=1,'CalculoFoda-1'!I112=1))),"sin dato: "&CalculosFoda!AF112,"")
D57: =IF(AND(OR('CalculoFoda-1'!H42=1,'CalculoFoda-1'!I42=1),OR('CalculoFoda-1'!H99=1,'CalculoFoda-1'!I99=1)),CalculosFoda!AF99,"") | E57: =IF(AND(OR('CalculoFoda-1'!H42=1,'CalculoFoda-1'!I42=1),OR('CalculoFoda-1'!F99=1,'CalculoFoda-1'!G99=1)),CalculosFoda!AF99,"") -> Financiamiento y crédito para exportar | F57: =IF(AND(OR('CalculoFoda-1'!F42=1,'CalculoFoda-1'!G42=1),OR('CalculoFoda-1'!H99=1,'CalculoFoda-1'!I99=1)),CalculosFoda!AF99,"") | G57: =IF(AND(OR('CalculoFoda-1'!F42=1,'CalculoFoda-1'!G42=1),OR('CalculoFoda-1'!F99=1,'CalculoFoda-1'!G99=1)),CalculosFoda!AF99,"") | H57: =IF(OR(NOT(OR('CalculoFoda-1'!F42=1,'CalculoFoda-1'!G42=1,'CalculoFoda-1'!H42=1,'CalculoFoda-1'!I42=1)),NOT(OR('CalculoFoda-1'!F99=1,'CalculoFoda-1'!G99=1,'CalculoFoda-1'!H99=1,'CalculoFoda-1'!I99=1))),"sin dato: "&CalculosFoda!AF99,"")
C58: =+CalculosFoda!AF43 -> Personal calificado | D58: =IF(AND(OR('CalculoFoda-1'!H43=1,'CalculoFoda-1'!I43=1),OR('CalculoFoda-1'!H108=1,'CalculoFoda-1'!I108=1)),CalculosFoda!AF108,"") -> Formación técnica y mano de obra regional | E58: =IF(AND(OR('CalculoFoda-1'!H43=1,'CalculoFoda-1'!I43=1),OR('CalculoFoda-1'!F108=1,'CalculoFoda-1'!G108=1)),CalculosFoda!AF108,"") | F58: =IF(AND(OR('CalculoFoda-1'!F43=1,'CalculoFoda-1'!G43=1),OR('CalculoFoda-1'!H108=1,'CalculoFoda-1'!I108=1)),CalculosFoda!AF108,"") | G58: =IF(AND(OR('CalculoFoda-1'!F43=1,'CalculoFoda-1'!G43=1),OR('CalculoFoda-1'!F108=1,'CalculoFoda-1'!G108=1)),CalculosFoda!AF108,"") | H58: =IF(OR(NOT(OR('CalculoFoda-1'!F43=1,'CalculoFoda-1'!G43=1,'CalculoFoda-1'!H43=1,'CalculoFoda-1'!I43=1)),NOT(OR('CalculoFoda-1'!F108=1,'CalculoFoda-1'!G108=1,'CalculoFoda-1'!H108=1,'CalculoFoda-1'!I108=1))),"sin dato: "&CalculosFoda!AF108,"")
C59: =+CalculosFoda!AF44 -> Formación continua y capacitación en comercio exterior | D59: =IF(AND(OR('CalculoFoda-1'!H44=1,'CalculoFoda-1'!I44=1),OR('CalculoFoda-1'!H108=1,'CalculoFoda-1'!I108=1)),CalculosFoda!AF108,"") | E59: =IF(AND(OR('CalculoFoda-1'!H44=1,'CalculoFoda-1'!I44=1),OR('CalculoFoda-1'!F108=1,'CalculoFoda-1'!G108=1)),CalculosFoda!AF108,"") | F59: =IF(AND(OR('CalculoFoda-1'!F44=1,'CalculoFoda-1'!G44=1),OR('CalculoFoda-1'!H108=1,'CalculoFoda-1'!I108=1)),CalculosFoda!AF108,"") -> Formación técnica y mano de obra regional | G59: =IF(AND(OR('CalculoFoda-1'!F44=1,'CalculoFoda-1'!G44=1),OR('CalculoFoda-1'!F108=1,'CalculoFoda-1'!G108=1)),CalculosFoda!AF108,"") | H59: =IF(OR(NOT(OR('CalculoFoda-1'!F44=1,'CalculoFoda-1'!G44=1,'CalculoFoda-1'!H44=1,'CalculoFoda-1'!I44=1)),NOT(OR('CalculoFoda-1'!F108=1,'CalculoFoda-1'!G108=1,'CalculoFoda-1'!H108=1,'CalculoFoda-1'!I108=1))),"sin dato: "&CalculosFoda!AF108,"")
D60: =IF(AND(OR('CalculoFoda-1'!H44=1,'CalculoFoda-1'!I44=1),OR('CalculoFoda-1'!H91=1,'CalculoFoda-1'!I91=1)),CalculosFoda!AF91,"") | E60: =IF(AND(OR('CalculoFoda-1'!H44=1,'CalculoFoda-1'!I44=1),OR('CalculoFoda-1'!F91=1,'CalculoFoda-1'!G91=1)),CalculosFoda!AF91,"") | F60: =IF(AND(OR('CalculoFoda-1'!F44=1,'CalculoFoda-1'!G44=1),OR('CalculoFoda-1'!H91=1,'CalculoFoda-1'!I91=1)),CalculosFoda!AF91,"") | G60: =IF(AND(OR('CalculoFoda-1'!F44=1,'CalculoFoda-1'!G44=1),OR('CalculoFoda-1'!F91=1,'CalculoFoda-1'!G91=1)),CalculosFoda!AF91,"") -> Promoción y fomento a exportadores | H60: =IF(OR(NOT(OR('CalculoFoda-1'!F44=1,'CalculoFoda-1'!G44=1,'CalculoFoda-1'!H44=1,'CalculoFoda-1'!I44=1)),NOT(OR('CalculoFoda-1'!F91=1,'CalculoFoda-1'!G91=1,'CalculoFoda-1'!H91=1,'CalculoFoda-1'!I91=1))),"sin dato: "&CalculosFoda!AF91,"")
C61: =+CalculosFoda!AF45 -> Capital de trabajo y capacidad financiera | D61: =IF(AND(OR('CalculoFoda-1'!H45=1,'CalculoFoda-1'!I45=1),OR('CalculoFoda-1'!H99=1,'CalculoFoda-1'!I99=1)),CalculosFoda!AF99,"") | E61: =IF(AND(OR('CalculoFoda-1'!H45=1,'CalculoFoda-1'!I45=1),OR('CalculoFoda-1'!F99=1,'CalculoFoda-1'!G99=1)),CalculosFoda!AF99,"") | F61: =IF(AND(OR('CalculoFoda-1'!F45=1,'CalculoFoda-1'!G45=1),OR('CalculoFoda-1'!H99=1,'CalculoFoda-1'!I99=1)),CalculosFoda!AF99,"") | G61: =IF(AND(OR('CalculoFoda-1'!F45=1,'CalculoFoda-1'!G45=1),OR('CalculoFoda-1'!F99=1,'CalculoFoda-1'!G99=1)),CalculosFoda!AF99,"") -> Financiamiento y crédito para exportar | H61: =IF(OR(NOT(OR('CalculoFoda-1'!F45=1,'CalculoFoda-1'!G45=1,'CalculoFoda-1'!H45=1,'CalculoFoda-1'!I45=1)),NOT(OR('CalculoFoda-1'!F99=1,'CalculoFoda-1'!G99=1,'CalculoFoda-1'!H99=1,'CalculoFoda-1'!I99=1))),"sin dato: "&CalculosFoda!AF99,"")
D62: =IF(AND(OR('CalculoFoda-1'!H45=1,'CalculoFoda-1'!I45=1),OR('CalculoFoda-1'!H100=1,'CalculoFoda-1'!I100=1)),CalculosFoda!AF100,"") | E62: =IF(AND(OR('CalculoFoda-1'!H45=1,'CalculoFoda-1'!I45=1),OR('CalculoFoda-1'!F100=1,'CalculoFoda-1'!G100=1)),CalculosFoda!AF100,"") | F62: =IF(AND(OR('CalculoFoda-1'!F45=1,'CalculoFoda-1'!G45=1),OR('CalculoFoda-1'!H100=1,'CalculoFoda-1'!I100=1)),CalculosFoda!AF100,"") | G62: =IF(AND(OR('CalculoFoda-1'!F45=1,'CalculoFoda-1'!G45=1),OR('CalculoFoda-1'!F100=1,'CalculoFoda-1'!G100=1)),CalculosFoda!AF100,"") -> Cobros y acceso a divisas | H62: =IF(OR(NOT(OR('CalculoFoda-1'!F45=1,'CalculoFoda-1'!G45=1,'CalculoFoda-1'!H45=1,'CalculoFoda-1'!I45=1)),NOT(OR('CalculoFoda-1'!F100=1,'CalculoFoda-1'!G100=1,'CalculoFoda-1'!H100=1,'CalculoFoda-1'!I100=1))),"sin dato: "&CalculosFoda!AF100,"")
C63: =+CalculosFoda!AF46 -> Sistemas de información y gestión | D63: =IF(AND(OR('CalculoFoda-1'!H46=1,'CalculoFoda-1'!I46=1),OR('CalculoFoda-1'!H114=1,'CalculoFoda-1'!I114=1)),CalculosFoda!AF114,"") | E63: =IF(AND(OR('CalculoFoda-1'!H46=1,'CalculoFoda-1'!I46=1),OR('CalculoFoda-1'!F114=1,'CalculoFoda-1'!G114=1)),CalculosFoda!AF114,"") -> Digitalización del comercio exterior | F63: =IF(AND(OR('CalculoFoda-1'!F46=1,'CalculoFoda-1'!G46=1),OR('CalculoFoda-1'!H114=1,'CalculoFoda-1'!I114=1)),CalculosFoda!AF114,"") | G63: =IF(AND(OR('CalculoFoda-1'!F46=1,'CalculoFoda-1'!G46=1),OR('CalculoFoda-1'!F114=1,'CalculoFoda-1'!G114=1)),CalculosFoda!AF114,"") | H63: =IF(OR(NOT(OR('CalculoFoda-1'!F46=1,'CalculoFoda-1'!G46=1,'CalculoFoda-1'!H46=1,'CalculoFoda-1'!I46=1)),NOT(OR('CalculoFoda-1'!F114=1,'CalculoFoda-1'!G114=1,'CalculoFoda-1'!H114=1,'CalculoFoda-1'!I114=1))),"sin dato: "&CalculosFoda!AF114,"")
D64: =IF(AND(OR('CalculoFoda-1'!H46=1,'CalculoFoda-1'!I46=1),OR('CalculoFoda-1'!H115=1,'CalculoFoda-1'!I115=1)),CalculosFoda!AF115,"") | E64: =IF(AND(OR('CalculoFoda-1'!H46=1,'CalculoFoda-1'!I46=1),OR('CalculoFoda-1'!F115=1,'CalculoFoda-1'!G115=1)),CalculosFoda!AF115,"") -> Trazabilidad y certificación digital | F64: =IF(AND(OR('CalculoFoda-1'!F46=1,'CalculoFoda-1'!G46=1),OR('CalculoFoda-1'!H115=1,'CalculoFoda-1'!I115=1)),CalculosFoda!AF115,"") | G64: =IF(AND(OR('CalculoFoda-1'!F46=1,'CalculoFoda-1'!G46=1),OR('CalculoFoda-1'!F115=1,'CalculoFoda-1'!G115=1)),CalculosFoda!AF115,"") | H64: =IF(OR(NOT(OR('CalculoFoda-1'!F46=1,'CalculoFoda-1'!G46=1,'CalculoFoda-1'!H46=1,'CalculoFoda-1'!I46=1)),NOT(OR('CalculoFoda-1'!F115=1,'CalculoFoda-1'!G115=1,'CalculoFoda-1'!H115=1,'CalculoFoda-1'!I115=1))),"sin dato: "&CalculosFoda!AF115,"")
C65: =+CalculosFoda!AF47 -> Infraestructura, depósitos y conservación | D65: =IF(AND(OR('CalculoFoda-1'!H47=1,'CalculoFoda-1'!I47=1),OR('CalculoFoda-1'!H124=1,'CalculoFoda-1'!I124=1)),CalculosFoda!AF124,"") | E65: =IF(AND(OR('CalculoFoda-1'!H47=1,'CalculoFoda-1'!I47=1),OR('CalculoFoda-1'!F124=1,'CalculoFoda-1'!G124=1)),CalculosFoda!AF124,"") | F65: =IF(AND(OR('CalculoFoda-1'!F47=1,'CalculoFoda-1'!G47=1),OR('CalculoFoda-1'!H124=1,'CalculoFoda-1'!I124=1)),CalculosFoda!AF124,"") | G65: =IF(AND(OR('CalculoFoda-1'!F47=1,'CalculoFoda-1'!G47=1),OR('CalculoFoda-1'!F124=1,'CalculoFoda-1'!G124=1)),CalculosFoda!AF124,"") -> Energía y servicios públicos industriales | H65: =IF(OR(NOT(OR('CalculoFoda-1'!F47=1,'CalculoFoda-1'!G47=1,'CalculoFoda-1'!H47=1,'CalculoFoda-1'!I47=1)),NOT(OR('CalculoFoda-1'!F124=1,'CalculoFoda-1'!G124=1,'CalculoFoda-1'!H124=1,'CalculoFoda-1'!I124=1))),"sin dato: "&CalculosFoda!AF124,"")
C66: =+CalculosFoda!AF48 -> Habilitaciones y registros oficiales | D66: =IF(AND(OR('CalculoFoda-1'!H48=1,'CalculoFoda-1'!I48=1),OR('CalculoFoda-1'!H146=1,'CalculoFoda-1'!I146=1)),CalculosFoda!AF146,"") | E66: =IF(AND(OR('CalculoFoda-1'!H48=1,'CalculoFoda-1'!I48=1),OR('CalculoFoda-1'!F146=1,'CalculoFoda-1'!G146=1)),CalculosFoda!AF146,"") -> Requisitos sanitarios y fitosanitarios del destino | F66: =IF(AND(OR('CalculoFoda-1'!F48=1,'CalculoFoda-1'!G48=1),OR('CalculoFoda-1'!H146=1,'CalculoFoda-1'!I146=1)),CalculosFoda!AF146,"") | G66: =IF(AND(OR('CalculoFoda-1'!F48=1,'CalculoFoda-1'!G48=1),OR('CalculoFoda-1'!F146=1,'CalculoFoda-1'!G146=1)),CalculosFoda!AF146,"") | H66: =IF(OR(NOT(OR('CalculoFoda-1'!F48=1,'CalculoFoda-1'!G48=1,'CalculoFoda-1'!H48=1,'CalculoFoda-1'!I48=1)),NOT(OR('CalculoFoda-1'!F146=1,'CalculoFoda-1'!G146=1,'CalculoFoda-1'!H146=1,'CalculoFoda-1'!I146=1))),"sin dato: "&CalculosFoda!AF146,"")
D67: =IF(AND(OR('CalculoFoda-1'!H48=1,'CalculoFoda-1'!I48=1),OR('CalculoFoda-1'!H90=1,'CalculoFoda-1'!I90=1)),CalculosFoda!AF90,"") | E67: =IF(AND(OR('CalculoFoda-1'!H48=1,'CalculoFoda-1'!I48=1),OR('CalculoFoda-1'!F90=1,'CalculoFoda-1'!G90=1)),CalculosFoda!AF90,"") -> Trámites y aduana | F67: =IF(AND(OR('CalculoFoda-1'!F48=1,'CalculoFoda-1'!G48=1),OR('CalculoFoda-1'!H90=1,'CalculoFoda-1'!I90=1)),CalculosFoda!AF90,"") | G67: =IF(AND(OR('CalculoFoda-1'!F48=1,'CalculoFoda-1'!G48=1),OR('CalculoFoda-1'!F90=1,'CalculoFoda-1'!G90=1)),CalculosFoda!AF90,"") | H67: =IF(OR(NOT(OR('CalculoFoda-1'!F48=1,'CalculoFoda-1'!G48=1,'CalculoFoda-1'!H48=1,'CalculoFoda-1'!I48=1)),NOT(OR('CalculoFoda-1'!F90=1,'CalculoFoda-1'!G90=1,'CalculoFoda-1'!H90=1,'CalculoFoda-1'!I90=1))),"sin dato: "&CalculosFoda!AF90,"")
B69: =+FormularioFODA!B54 -> Actividades Clave | C69: =+CalculosFoda!AF51 -> Descripción técnica y estandarización | H69: variable independiente
C70: =+CalculosFoda!AF52 -> Mantenimiento y continuidad operativa | D70: =IF(AND(OR('CalculoFoda-1'!H52=1,'CalculoFoda-1'!I52=1),OR('CalculoFoda-1'!H124=1,'CalculoFoda-1'!I124=1)),CalculosFoda!AF124,"") | E70: =IF(AND(OR('CalculoFoda-1'!H52=1,'CalculoFoda-1'!I52=1),OR('CalculoFoda-1'!F124=1,'CalculoFoda-1'!G124=1)),CalculosFoda!AF124,"") -> Energía y servicios públicos industriales | F70: =IF(AND(OR('CalculoFoda-1'!F52=1,'CalculoFoda-1'!G52=1),OR('CalculoFoda-1'!H124=1,'CalculoFoda-1'!I124=1)),CalculosFoda!AF124,"") | G70: =IF(AND(OR('CalculoFoda-1'!F52=1,'CalculoFoda-1'!G52=1),OR('CalculoFoda-1'!F124=1,'CalculoFoda-1'!G124=1)),CalculosFoda!AF124,"") | H70: =IF(OR(NOT(OR('CalculoFoda-1'!F52=1,'CalculoFoda-1'!G52=1,'CalculoFoda-1'!H52=1,'CalculoFoda-1'!I52=1)),NOT(OR('CalculoFoda-1'!F124=1,'CalculoFoda-1'!G124=1,'CalculoFoda-1'!H124=1,'CalculoFoda-1'!I124=1))),"sin dato: "&CalculosFoda!AF124,"")
D71: =IF(AND(OR('CalculoFoda-1'!H52=1,'CalculoFoda-1'!I52=1),OR('CalculoFoda-1'!H112=1,'CalculoFoda-1'!I112=1)),CalculosFoda!AF112,"") | E71: =IF(AND(OR('CalculoFoda-1'!H52=1,'CalculoFoda-1'!I52=1),OR('CalculoFoda-1'!F112=1,'CalculoFoda-1'!G112=1)),CalculosFoda!AF112,"") -> Avances tecnológicos del sector | F71: =IF(AND(OR('CalculoFoda-1'!F52=1,'CalculoFoda-1'!G52=1),OR('CalculoFoda-1'!H112=1,'CalculoFoda-1'!I112=1)),CalculosFoda!AF112,"") | G71: =IF(AND(OR('CalculoFoda-1'!F52=1,'CalculoFoda-1'!G52=1),OR('CalculoFoda-1'!F112=1,'CalculoFoda-1'!G112=1)),CalculosFoda!AF112,"") | H71: =IF(OR(NOT(OR('CalculoFoda-1'!F52=1,'CalculoFoda-1'!G52=1,'CalculoFoda-1'!H52=1,'CalculoFoda-1'!I52=1)),NOT(OR('CalculoFoda-1'!F112=1,'CalculoFoda-1'!G112=1,'CalculoFoda-1'!H112=1,'CalculoFoda-1'!I112=1))),"sin dato: "&CalculosFoda!AF112,"")
C72: =+CalculosFoda!AF53 -> Planificación de producción y abastecimiento | D72: =IF(AND(OR('CalculoFoda-1'!H53=1,'CalculoFoda-1'!I53=1),OR('CalculoFoda-1'!H135=1,'CalculoFoda-1'!I135=1)),CalculosFoda!AF135,"") -> Cantidad de proveedores | E72: =IF(AND(OR('CalculoFoda-1'!H53=1,'CalculoFoda-1'!I53=1),OR('CalculoFoda-1'!F135=1,'CalculoFoda-1'!G135=1)),CalculosFoda!AF135,"") | F72: =IF(AND(OR('CalculoFoda-1'!F53=1,'CalculoFoda-1'!G53=1),OR('CalculoFoda-1'!H135=1,'CalculoFoda-1'!I135=1)),CalculosFoda!AF135,"") | G72: =IF(AND(OR('CalculoFoda-1'!F53=1,'CalculoFoda-1'!G53=1),OR('CalculoFoda-1'!F135=1,'CalculoFoda-1'!G135=1)),CalculosFoda!AF135,"") | H72: =IF(OR(NOT(OR('CalculoFoda-1'!F53=1,'CalculoFoda-1'!G53=1,'CalculoFoda-1'!H53=1,'CalculoFoda-1'!I53=1)),NOT(OR('CalculoFoda-1'!F135=1,'CalculoFoda-1'!G135=1,'CalculoFoda-1'!H135=1,'CalculoFoda-1'!I135=1))),"sin dato: "&CalculosFoda!AF135,"")
D73: =IF(AND(OR('CalculoFoda-1'!H53=1,'CalculoFoda-1'!I53=1),OR('CalculoFoda-1'!H138=1,'CalculoFoda-1'!I138=1)),CalculosFoda!AF138,"") -> Disponibilidad y estacionalidad de materia prima | E73: =IF(AND(OR('CalculoFoda-1'!H53=1,'CalculoFoda-1'!I53=1),OR('CalculoFoda-1'!F138=1,'CalculoFoda-1'!G138=1)),CalculosFoda!AF138,"") | F73: =IF(AND(OR('CalculoFoda-1'!F53=1,'CalculoFoda-1'!G53=1),OR('CalculoFoda-1'!H138=1,'CalculoFoda-1'!I138=1)),CalculosFoda!AF138,"") | G73: =IF(AND(OR('CalculoFoda-1'!F53=1,'CalculoFoda-1'!G53=1),OR('CalculoFoda-1'!F138=1,'CalculoFoda-1'!G138=1)),CalculosFoda!AF138,"") | H73: =IF(OR(NOT(OR('CalculoFoda-1'!F53=1,'CalculoFoda-1'!G53=1,'CalculoFoda-1'!H53=1,'CalculoFoda-1'!I53=1)),NOT(OR('CalculoFoda-1'!F138=1,'CalculoFoda-1'!G138=1,'CalculoFoda-1'!H138=1,'CalculoFoda-1'!I138=1))),"sin dato: "&CalculosFoda!AF138,"")
C74: =+CalculosFoda!AF54 -> Gestión de calidad | D74: =IF(AND(OR('CalculoFoda-1'!H54=1,'CalculoFoda-1'!I54=1),OR('CalculoFoda-1'!H147=1,'CalculoFoda-1'!I147=1)),CalculosFoda!AF147,"") | E74: =IF(AND(OR('CalculoFoda-1'!H54=1,'CalculoFoda-1'!I54=1),OR('CalculoFoda-1'!F147=1,'CalculoFoda-1'!G147=1)),CalculosFoda!AF147,"") | F74: =IF(AND(OR('CalculoFoda-1'!F54=1,'CalculoFoda-1'!G54=1),OR('CalculoFoda-1'!H147=1,'CalculoFoda-1'!I147=1)),CalculosFoda!AF147,"") -> Certificaciones exigidas por los compradores | G74: =IF(AND(OR('CalculoFoda-1'!F54=1,'CalculoFoda-1'!G54=1),OR('CalculoFoda-1'!F147=1,'CalculoFoda-1'!G147=1)),CalculosFoda!AF147,"") | H74: =IF(OR(NOT(OR('CalculoFoda-1'!F54=1,'CalculoFoda-1'!G54=1,'CalculoFoda-1'!H54=1,'CalculoFoda-1'!I54=1)),NOT(OR('CalculoFoda-1'!F147=1,'CalculoFoda-1'!G147=1,'CalculoFoda-1'!H147=1,'CalculoFoda-1'!I147=1))),"sin dato: "&CalculosFoda!AF147,"")
D75: =IF(AND(OR('CalculoFoda-1'!H54=1,'CalculoFoda-1'!I54=1),OR('CalculoFoda-1'!H146=1,'CalculoFoda-1'!I146=1)),CalculosFoda!AF146,"") | E75: =IF(AND(OR('CalculoFoda-1'!H54=1,'CalculoFoda-1'!I54=1),OR('CalculoFoda-1'!F146=1,'CalculoFoda-1'!G146=1)),CalculosFoda!AF146,"") | F75: =IF(AND(OR('CalculoFoda-1'!F54=1,'CalculoFoda-1'!G54=1),OR('CalculoFoda-1'!H146=1,'CalculoFoda-1'!I146=1)),CalculosFoda!AF146,"") | G75: =IF(AND(OR('CalculoFoda-1'!F54=1,'CalculoFoda-1'!G54=1),OR('CalculoFoda-1'!F146=1,'CalculoFoda-1'!G146=1)),CalculosFoda!AF146,"") -> Requisitos sanitarios y fitosanitarios del destino | H75: =IF(OR(NOT(OR('CalculoFoda-1'!F54=1,'CalculoFoda-1'!G54=1,'CalculoFoda-1'!H54=1,'CalculoFoda-1'!I54=1)),NOT(OR('CalculoFoda-1'!F146=1,'CalculoFoda-1'!G146=1,'CalculoFoda-1'!H146=1,'CalculoFoda-1'!I146=1))),"sin dato: "&CalculosFoda!AF146,"")
C76: =+CalculosFoda!AF55 -> Trazabilidad y control de stock | D76: =IF(AND(OR('CalculoFoda-1'!H55=1,'CalculoFoda-1'!I55=1),OR('CalculoFoda-1'!H115=1,'CalculoFoda-1'!I115=1)),CalculosFoda!AF115,"") | E76: =IF(AND(OR('CalculoFoda-1'!H55=1,'CalculoFoda-1'!I55=1),OR('CalculoFoda-1'!F115=1,'CalculoFoda-1'!G115=1)),CalculosFoda!AF115,"") | F76: =IF(AND(OR('CalculoFoda-1'!F55=1,'CalculoFoda-1'!G55=1),OR('CalculoFoda-1'!H115=1,'CalculoFoda-1'!I115=1)),CalculosFoda!AF115,"") | G76: =IF(AND(OR('CalculoFoda-1'!F55=1,'CalculoFoda-1'!G55=1),OR('CalculoFoda-1'!F115=1,'CalculoFoda-1'!G115=1)),CalculosFoda!AF115,"") -> Trazabilidad y certificación digital | H76: =IF(OR(NOT(OR('CalculoFoda-1'!F55=1,'CalculoFoda-1'!G55=1,'CalculoFoda-1'!H55=1,'CalculoFoda-1'!I55=1)),NOT(OR('CalculoFoda-1'!F115=1,'CalculoFoda-1'!G115=1,'CalculoFoda-1'!H115=1,'CalculoFoda-1'!I115=1))),"sin dato: "&CalculosFoda!AF115,"")
C77: =+CalculosFoda!AF56 -> Cumplimiento de plazos de entrega | D77: =IF(AND(OR('CalculoFoda-1'!H56=1,'CalculoFoda-1'!I56=1),OR('CalculoFoda-1'!H119=1,'CalculoFoda-1'!I119=1)),CalculosFoda!AF119,"") | E77: =IF(AND(OR('CalculoFoda-1'!H56=1,'CalculoFoda-1'!I56=1),OR('CalculoFoda-1'!F119=1,'CalculoFoda-1'!G119=1)),CalculosFoda!AF119,"") -> Pasos de frontera y puentes internacionales | F77: =IF(AND(OR('CalculoFoda-1'!F56=1,'CalculoFoda-1'!G56=1),OR('CalculoFoda-1'!H119=1,'CalculoFoda-1'!I119=1)),CalculosFoda!AF119,"") | G77: =IF(AND(OR('CalculoFoda-1'!F56=1,'CalculoFoda-1'!G56=1),OR('CalculoFoda-1'!F119=1,'CalculoFoda-1'!G119=1)),CalculosFoda!AF119,"") | H77: =IF(OR(NOT(OR('CalculoFoda-1'!F56=1,'CalculoFoda-1'!G56=1,'CalculoFoda-1'!H56=1,'CalculoFoda-1'!I56=1)),NOT(OR('CalculoFoda-1'!F119=1,'CalculoFoda-1'!G119=1,'CalculoFoda-1'!H119=1,'CalculoFoda-1'!I119=1))),"sin dato: "&CalculosFoda!AF119,"")
D78: =IF(AND(OR('CalculoFoda-1'!H56=1,'CalculoFoda-1'!I56=1),OR('CalculoFoda-1'!H121=1,'CalculoFoda-1'!I121=1)),CalculosFoda!AF121,"") | E78: =IF(AND(OR('CalculoFoda-1'!H56=1,'CalculoFoda-1'!I56=1),OR('CalculoFoda-1'!F121=1,'CalculoFoda-1'!G121=1)),CalculosFoda!AF121,"") | F78: =IF(AND(OR('CalculoFoda-1'!F56=1,'CalculoFoda-1'!G56=1),OR('CalculoFoda-1'!H121=1,'CalculoFoda-1'!I121=1)),CalculosFoda!AF121,"") | G78: =IF(AND(OR('CalculoFoda-1'!F56=1,'CalculoFoda-1'!G56=1),OR('CalculoFoda-1'!F121=1,'CalculoFoda-1'!G121=1)),CalculosFoda!AF121,"") | H78: =IF(OR(NOT(OR('CalculoFoda-1'!F56=1,'CalculoFoda-1'!G56=1,'CalculoFoda-1'!H56=1,'CalculoFoda-1'!I56=1)),NOT(OR('CalculoFoda-1'!F121=1,'CalculoFoda-1'!G121=1,'CalculoFoda-1'!H121=1,'CalculoFoda-1'!I121=1))),"sin dato: "&CalculosFoda!AF121,"") -> sin dato: Costo y disponibilidad de fletes
C79: =+CalculosFoda!AF57 -> Mejora de procesos e I+D | D79: =IF(AND(OR('CalculoFoda-1'!H57=1,'CalculoFoda-1'!I57=1),OR('CalculoFoda-1'!H112=1,'CalculoFoda-1'!I112=1)),CalculosFoda!AF112,"") | E79: =IF(AND(OR('CalculoFoda-1'!H57=1,'CalculoFoda-1'!I57=1),OR('CalculoFoda-1'!F112=1,'CalculoFoda-1'!G112=1)),CalculosFoda!AF112,"") | F79: =IF(AND(OR('CalculoFoda-1'!F57=1,'CalculoFoda-1'!G57=1),OR('CalculoFoda-1'!H112=1,'CalculoFoda-1'!I112=1)),CalculosFoda!AF112,"") | G79: =IF(AND(OR('CalculoFoda-1'!F57=1,'CalculoFoda-1'!G57=1),OR('CalculoFoda-1'!F112=1,'CalculoFoda-1'!G112=1)),CalculosFoda!AF112,"") -> Avances tecnológicos del sector | H79: =IF(OR(NOT(OR('CalculoFoda-1'!F57=1,'CalculoFoda-1'!G57=1,'CalculoFoda-1'!H57=1,'CalculoFoda-1'!I57=1)),NOT(OR('CalculoFoda-1'!F112=1,'CalculoFoda-1'!G112=1,'CalculoFoda-1'!H112=1,'CalculoFoda-1'!I112=1))),"sin dato: "&CalculosFoda!AF112,"")
C80: =+CalculosFoda!AF58 -> Gestión ambiental y de residuos | D80: =IF(AND(OR('CalculoFoda-1'!H58=1,'CalculoFoda-1'!I58=1),OR('CalculoFoda-1'!H145=1,'CalculoFoda-1'!I145=1)),CalculosFoda!AF145,"") | E80: =IF(AND(OR('CalculoFoda-1'!H58=1,'CalculoFoda-1'!I58=1),OR('CalculoFoda-1'!F145=1,'CalculoFoda-1'!G145=1)),CalculosFoda!AF145,"") | F80: =IF(AND(OR('CalculoFoda-1'!F58=1,'CalculoFoda-1'!G58=1),OR('CalculoFoda-1'!H145=1,'CalculoFoda-1'!I145=1)),CalculosFoda!AF145,"") -> Regulación ambiental y forestal | G80: =IF(AND(OR('CalculoFoda-1'!F58=1,'CalculoFoda-1'!G58=1),OR('CalculoFoda-1'!F145=1,'CalculoFoda-1'!G145=1)),CalculosFoda!AF145,"") | H80: =IF(OR(NOT(OR('CalculoFoda-1'!F58=1,'CalculoFoda-1'!G58=1,'CalculoFoda-1'!H58=1,'CalculoFoda-1'!I58=1)),NOT(OR('CalculoFoda-1'!F145=1,'CalculoFoda-1'!G145=1,'CalculoFoda-1'!H145=1,'CalculoFoda-1'!I145=1))),"sin dato: "&CalculosFoda!AF145,"")
C81: =+CalculosFoda!AF59 -> Seguridad e higiene laboral | H81: variable independiente
B83: =+FormularioFODA!B65 -> Socios Clave | C83: =+CalculosFoda!AF62 -> Proveedores estratégicos | D83: =IF(AND(OR('CalculoFoda-1'!H62=1,'CalculoFoda-1'!I62=1),OR('CalculoFoda-1'!H135=1,'CalculoFoda-1'!I135=1)),CalculosFoda!AF135,"") -> Cantidad de proveedores | E83: =IF(AND(OR('CalculoFoda-1'!H62=1,'CalculoFoda-1'!I62=1),OR('CalculoFoda-1'!F135=1,'CalculoFoda-1'!G135=1)),CalculosFoda!AF135,"") | F83: =IF(AND(OR('CalculoFoda-1'!F62=1,'CalculoFoda-1'!G62=1),OR('CalculoFoda-1'!H135=1,'CalculoFoda-1'!I135=1)),CalculosFoda!AF135,"") | G83: =IF(AND(OR('CalculoFoda-1'!F62=1,'CalculoFoda-1'!G62=1),OR('CalculoFoda-1'!F135=1,'CalculoFoda-1'!G135=1)),CalculosFoda!AF135,"") | H83: =IF(OR(NOT(OR('CalculoFoda-1'!F62=1,'CalculoFoda-1'!G62=1,'CalculoFoda-1'!H62=1,'CalculoFoda-1'!I62=1)),NOT(OR('CalculoFoda-1'!F135=1,'CalculoFoda-1'!G135=1,'CalculoFoda-1'!H135=1,'CalculoFoda-1'!I135=1))),"sin dato: "&CalculosFoda!AF135,"")
D84: =IF(AND(OR('CalculoFoda-1'!H62=1,'CalculoFoda-1'!I62=1),OR('CalculoFoda-1'!H136=1,'CalculoFoda-1'!I136=1)),CalculosFoda!AF136,"") | E84: =IF(AND(OR('CalculoFoda-1'!H62=1,'CalculoFoda-1'!I62=1),OR('CalculoFoda-1'!F136=1,'CalculoFoda-1'!G136=1)),CalculosFoda!AF136,"") -> Calidad y cumplimiento de proveedores | F84: =IF(AND(OR('CalculoFoda-1'!F62=1,'CalculoFoda-1'!G62=1),OR('CalculoFoda-1'!H136=1,'CalculoFoda-1'!I136=1)),CalculosFoda!AF136,"") | G84: =IF(AND(OR('CalculoFoda-1'!F62=1,'CalculoFoda-1'!G62=1),OR('CalculoFoda-1'!F136=1,'CalculoFoda-1'!G136=1)),CalculosFoda!AF136,"") | H84: =IF(OR(NOT(OR('CalculoFoda-1'!F62=1,'CalculoFoda-1'!G62=1,'CalculoFoda-1'!H62=1,'CalculoFoda-1'!I62=1)),NOT(OR('CalculoFoda-1'!F136=1,'CalculoFoda-1'!G136=1,'CalculoFoda-1'!H136=1,'CalculoFoda-1'!I136=1))),"sin dato: "&CalculosFoda!AF136,"")
D85: =IF(AND(OR('CalculoFoda-1'!H62=1,'CalculoFoda-1'!I62=1),OR('CalculoFoda-1'!H137=1,'CalculoFoda-1'!I137=1)),CalculosFoda!AF137,"") | E85: =IF(AND(OR('CalculoFoda-1'!H62=1,'CalculoFoda-1'!I62=1),OR('CalculoFoda-1'!F137=1,'CalculoFoda-1'!G137=1)),CalculosFoda!AF137,"") -> Poder negociador de los proveedores | F85: =IF(AND(OR('CalculoFoda-1'!F62=1,'CalculoFoda-1'!G62=1),OR('CalculoFoda-1'!H137=1,'CalculoFoda-1'!I137=1)),CalculosFoda!AF137,"") | G85: =IF(AND(OR('CalculoFoda-1'!F62=1,'CalculoFoda-1'!G62=1),OR('CalculoFoda-1'!F137=1,'CalculoFoda-1'!G137=1)),CalculosFoda!AF137,"") | H85: =IF(OR(NOT(OR('CalculoFoda-1'!F62=1,'CalculoFoda-1'!G62=1,'CalculoFoda-1'!H62=1,'CalculoFoda-1'!I62=1)),NOT(OR('CalculoFoda-1'!F137=1,'CalculoFoda-1'!G137=1,'CalculoFoda-1'!H137=1,'CalculoFoda-1'!I137=1))),"sin dato: "&CalculosFoda!AF137,"")
C86: =+CalculosFoda!AF63 -> Alianzas comerciales | D86: =IF(AND(OR('CalculoFoda-1'!H63=1,'CalculoFoda-1'!I63=1),OR('CalculoFoda-1'!H127=1,'CalculoFoda-1'!I127=1)),CalculosFoda!AF127,"") | E86: =IF(AND(OR('CalculoFoda-1'!H63=1,'CalculoFoda-1'!I63=1),OR('CalculoFoda-1'!F127=1,'CalculoFoda-1'!G127=1)),CalculosFoda!AF127,"") | F86: =IF(AND(OR('CalculoFoda-1'!F63=1,'CalculoFoda-1'!G63=1),OR('CalculoFoda-1'!H127=1,'CalculoFoda-1'!I127=1)),CalculosFoda!AF127,"") | G86: =IF(AND(OR('CalculoFoda-1'!F63=1,'CalculoFoda-1'!G63=1),OR('CalculoFoda-1'!F127=1,'CalculoFoda-1'!G127=1)),CalculosFoda!AF127,"") | H86: =IF(OR(NOT(OR('CalculoFoda-1'!F63=1,'CalculoFoda-1'!G63=1,'CalculoFoda-1'!H63=1,'CalculoFoda-1'!I63=1)),NOT(OR('CalculoFoda-1'!F127=1,'CalculoFoda-1'!G127=1,'CalculoFoda-1'!H127=1,'CalculoFoda-1'!I127=1))),"sin dato: "&CalculosFoda!AF127,"") -> sin dato: Barreras de entrada al mercado destino
D87: =IF(AND(OR('CalculoFoda-1'!H63=1,'CalculoFoda-1'!I63=1),OR('CalculoFoda-1'!H109=1,'CalculoFoda-1'!I109=1)),CalculosFoda!AF109,"") | E87: =IF(AND(OR('CalculoFoda-1'!H63=1,'CalculoFoda-1'!I63=1),OR('CalculoFoda-1'!F109=1,'CalculoFoda-1'!G109=1)),CalculosFoda!AF109,"") | F87: =IF(AND(OR('CalculoFoda-1'!F63=1,'CalculoFoda-1'!G63=1),OR('CalculoFoda-1'!H109=1,'CalculoFoda-1'!I109=1)),CalculosFoda!AF109,"") -> Asociativismo y cultura exportadora regional | G87: =IF(AND(OR('CalculoFoda-1'!F63=1,'CalculoFoda-1'!G63=1),OR('CalculoFoda-1'!F109=1,'CalculoFoda-1'!G109=1)),CalculosFoda!AF109,"") | H87: =IF(OR(NOT(OR('CalculoFoda-1'!F63=1,'CalculoFoda-1'!G63=1,'CalculoFoda-1'!H63=1,'CalculoFoda-1'!I63=1)),NOT(OR('CalculoFoda-1'!F109=1,'CalculoFoda-1'!G109=1,'CalculoFoda-1'!H109=1,'CalculoFoda-1'!I109=1))),"sin dato: "&CalculosFoda!AF109,"")
C88: =+CalculosFoda!AF64 -> Socios logísticos y aduaneros | D88: =IF(AND(OR('CalculoFoda-1'!H64=1,'CalculoFoda-1'!I64=1),OR('CalculoFoda-1'!H123=1,'CalculoFoda-1'!I123=1)),CalculosFoda!AF123,"") | E88: =IF(AND(OR('CalculoFoda-1'!H64=1,'CalculoFoda-1'!I64=1),OR('CalculoFoda-1'!F123=1,'CalculoFoda-1'!G123=1)),CalculosFoda!AF123,"") | F88: =IF(AND(OR('CalculoFoda-1'!F64=1,'CalculoFoda-1'!G64=1),OR('CalculoFoda-1'!H123=1,'CalculoFoda-1'!I123=1)),CalculosFoda!AF123,"") | G88: =IF(AND(OR('CalculoFoda-1'!F64=1,'CalculoFoda-1'!G64=1),OR('CalculoFoda-1'!F123=1,'CalculoFoda-1'!G123=1)),CalculosFoda!AF123,"") -> Prestadores logísticos regionales | H88: =IF(OR(NOT(OR('CalculoFoda-1'!F64=1,'CalculoFoda-1'!G64=1,'CalculoFoda-1'!H64=1,'CalculoFoda-1'!I64=1)),NOT(OR('CalculoFoda-1'!F123=1,'CalculoFoda-1'!G123=1,'CalculoFoda-1'!H123=1,'CalculoFoda-1'!I123=1))),"sin dato: "&CalculosFoda!AF123,"")
D89: =IF(AND(OR('CalculoFoda-1'!H64=1,'CalculoFoda-1'!I64=1),OR('CalculoFoda-1'!H122=1,'CalculoFoda-1'!I122=1)),CalculosFoda!AF122,"") | E89: =IF(AND(OR('CalculoFoda-1'!H64=1,'CalculoFoda-1'!I64=1),OR('CalculoFoda-1'!F122=1,'CalculoFoda-1'!G122=1)),CalculosFoda!AF122,"") | F89: =IF(AND(OR('CalculoFoda-1'!F64=1,'CalculoFoda-1'!G64=1),OR('CalculoFoda-1'!H122=1,'CalculoFoda-1'!I122=1)),CalculosFoda!AF122,"") | G89: =IF(AND(OR('CalculoFoda-1'!F64=1,'CalculoFoda-1'!G64=1),OR('CalculoFoda-1'!F122=1,'CalculoFoda-1'!G122=1)),CalculosFoda!AF122,"") -> Servicios aduaneros locales | H89: =IF(OR(NOT(OR('CalculoFoda-1'!F64=1,'CalculoFoda-1'!G64=1,'CalculoFoda-1'!H64=1,'CalculoFoda-1'!I64=1)),NOT(OR('CalculoFoda-1'!F122=1,'CalculoFoda-1'!G122=1,'CalculoFoda-1'!H122=1,'CalculoFoda-1'!I122=1))),"sin dato: "&CalculosFoda!AF122,"")
C90: =+CalculosFoda!AF65 -> Apoyo institucional | D90: =IF(AND(OR('CalculoFoda-1'!H65=1,'CalculoFoda-1'!I65=1),OR('CalculoFoda-1'!H91=1,'CalculoFoda-1'!I91=1)),CalculosFoda!AF91,"") | E90: =IF(AND(OR('CalculoFoda-1'!H65=1,'CalculoFoda-1'!I65=1),OR('CalculoFoda-1'!F91=1,'CalculoFoda-1'!G91=1)),CalculosFoda!AF91,"") -> Promoción y fomento a exportadores | F90: =IF(AND(OR('CalculoFoda-1'!F65=1,'CalculoFoda-1'!G65=1),OR('CalculoFoda-1'!H91=1,'CalculoFoda-1'!I91=1)),CalculosFoda!AF91,"") | G90: =IF(AND(OR('CalculoFoda-1'!F65=1,'CalculoFoda-1'!G65=1),OR('CalculoFoda-1'!F91=1,'CalculoFoda-1'!G91=1)),CalculosFoda!AF91,"") | H90: =IF(OR(NOT(OR('CalculoFoda-1'!F65=1,'CalculoFoda-1'!G65=1,'CalculoFoda-1'!H65=1,'CalculoFoda-1'!I65=1)),NOT(OR('CalculoFoda-1'!F91=1,'CalculoFoda-1'!G91=1,'CalculoFoda-1'!H91=1,'CalculoFoda-1'!I91=1))),"sin dato: "&CalculosFoda!AF91,"")
D91: =IF(AND(OR('CalculoFoda-1'!H65=1,'CalculoFoda-1'!I65=1),OR('CalculoFoda-1'!H109=1,'CalculoFoda-1'!I109=1)),CalculosFoda!AF109,"") -> Asociativismo y cultura exportadora regional | E91: =IF(AND(OR('CalculoFoda-1'!H65=1,'CalculoFoda-1'!I65=1),OR('CalculoFoda-1'!F109=1,'CalculoFoda-1'!G109=1)),CalculosFoda!AF109,"") | F91: =IF(AND(OR('CalculoFoda-1'!F65=1,'CalculoFoda-1'!G65=1),OR('CalculoFoda-1'!H109=1,'CalculoFoda-1'!I109=1)),CalculosFoda!AF109,"") | G91: =IF(AND(OR('CalculoFoda-1'!F65=1,'CalculoFoda-1'!G65=1),OR('CalculoFoda-1'!F109=1,'CalculoFoda-1'!G109=1)),CalculosFoda!AF109,"") | H91: =IF(OR(NOT(OR('CalculoFoda-1'!F65=1,'CalculoFoda-1'!G65=1,'CalculoFoda-1'!H65=1,'CalculoFoda-1'!I65=1)),NOT(OR('CalculoFoda-1'!F109=1,'CalculoFoda-1'!G109=1,'CalculoFoda-1'!H109=1,'CalculoFoda-1'!I109=1))),"sin dato: "&CalculosFoda!AF109,"")
C92: =+CalculosFoda!AF66 -> Socios financieros y de seguros | D92: =IF(AND(OR('CalculoFoda-1'!H66=1,'CalculoFoda-1'!I66=1),OR('CalculoFoda-1'!H99=1,'CalculoFoda-1'!I99=1)),CalculosFoda!AF99,"") | E92: =IF(AND(OR('CalculoFoda-1'!H66=1,'CalculoFoda-1'!I66=1),OR('CalculoFoda-1'!F99=1,'CalculoFoda-1'!G99=1)),CalculosFoda!AF99,"") | F92: =IF(AND(OR('CalculoFoda-1'!F66=1,'CalculoFoda-1'!G66=1),OR('CalculoFoda-1'!H99=1,'CalculoFoda-1'!I99=1)),CalculosFoda!AF99,"") | G92: =IF(AND(OR('CalculoFoda-1'!F66=1,'CalculoFoda-1'!G66=1),OR('CalculoFoda-1'!F99=1,'CalculoFoda-1'!G99=1)),CalculosFoda!AF99,"") -> Financiamiento y crédito para exportar | H92: =IF(OR(NOT(OR('CalculoFoda-1'!F66=1,'CalculoFoda-1'!G66=1,'CalculoFoda-1'!H66=1,'CalculoFoda-1'!I66=1)),NOT(OR('CalculoFoda-1'!F99=1,'CalculoFoda-1'!G99=1,'CalculoFoda-1'!H99=1,'CalculoFoda-1'!I99=1))),"sin dato: "&CalculosFoda!AF99,"")
C93: =+CalculosFoda!AF67 -> Tercerización y subcontratación | D93: =IF(AND(OR('CalculoFoda-1'!H67=1,'CalculoFoda-1'!I67=1),OR('CalculoFoda-1'!H137=1,'CalculoFoda-1'!I137=1)),CalculosFoda!AF137,"") | E93: =IF(AND(OR('CalculoFoda-1'!H67=1,'CalculoFoda-1'!I67=1),OR('CalculoFoda-1'!F137=1,'CalculoFoda-1'!G137=1)),CalculosFoda!AF137,"") -> Poder negociador de los proveedores | F93: =IF(AND(OR('CalculoFoda-1'!F67=1,'CalculoFoda-1'!G67=1),OR('CalculoFoda-1'!H137=1,'CalculoFoda-1'!I137=1)),CalculosFoda!AF137,"") | G93: =IF(AND(OR('CalculoFoda-1'!F67=1,'CalculoFoda-1'!G67=1),OR('CalculoFoda-1'!F137=1,'CalculoFoda-1'!G137=1)),CalculosFoda!AF137,"") | H93: =IF(OR(NOT(OR('CalculoFoda-1'!F67=1,'CalculoFoda-1'!G67=1,'CalculoFoda-1'!H67=1,'CalculoFoda-1'!I67=1)),NOT(OR('CalculoFoda-1'!F137=1,'CalculoFoda-1'!G137=1,'CalculoFoda-1'!H137=1,'CalculoFoda-1'!I137=1))),"sin dato: "&CalculosFoda!AF137,"")
B95: =+FormularioFODA!B73 -> Estructura de Costos | C95: =+CalculosFoda!AF70 -> Costos fijos | D95: =IF(AND(OR('CalculoFoda-1'!H70=1,'CalculoFoda-1'!I70=1),OR('CalculoFoda-1'!H98=1,'CalculoFoda-1'!I98=1)),CalculosFoda!AF98,"") | E95: =IF(AND(OR('CalculoFoda-1'!H70=1,'CalculoFoda-1'!I70=1),OR('CalculoFoda-1'!F98=1,'CalculoFoda-1'!G98=1)),CalculosFoda!AF98,"") | F95: =IF(AND(OR('CalculoFoda-1'!F70=1,'CalculoFoda-1'!G70=1),OR('CalculoFoda-1'!H98=1,'CalculoFoda-1'!I98=1)),CalculosFoda!AF98,"") | G95: =IF(AND(OR('CalculoFoda-1'!F70=1,'CalculoFoda-1'!G70=1),OR('CalculoFoda-1'!F98=1,'CalculoFoda-1'!G98=1)),CalculosFoda!AF98,"") | H95: =IF(OR(NOT(OR('CalculoFoda-1'!F70=1,'CalculoFoda-1'!G70=1,'CalculoFoda-1'!H70=1,'CalculoFoda-1'!I70=1)),NOT(OR('CalculoFoda-1'!F98=1,'CalculoFoda-1'!G98=1,'CalculoFoda-1'!H98=1,'CalculoFoda-1'!I98=1))),"sin dato: "&CalculosFoda!AF98,"") -> sin dato: Inflación y costos internos
D96: =IF(AND(OR('CalculoFoda-1'!H70=1,'CalculoFoda-1'!I70=1),OR('CalculoFoda-1'!H124=1,'CalculoFoda-1'!I124=1)),CalculosFoda!AF124,"") | E96: =IF(AND(OR('CalculoFoda-1'!H70=1,'CalculoFoda-1'!I70=1),OR('CalculoFoda-1'!F124=1,'CalculoFoda-1'!G124=1)),CalculosFoda!AF124,"") -> Energía y servicios públicos industriales | F96: =IF(AND(OR('CalculoFoda-1'!F70=1,'CalculoFoda-1'!G70=1),OR('CalculoFoda-1'!H124=1,'CalculoFoda-1'!I124=1)),CalculosFoda!AF124,"") | G96: =IF(AND(OR('CalculoFoda-1'!F70=1,'CalculoFoda-1'!G70=1),OR('CalculoFoda-1'!F124=1,'CalculoFoda-1'!G124=1)),CalculosFoda!AF124,"") | H96: =IF(OR(NOT(OR('CalculoFoda-1'!F70=1,'CalculoFoda-1'!G70=1,'CalculoFoda-1'!H70=1,'CalculoFoda-1'!I70=1)),NOT(OR('CalculoFoda-1'!F124=1,'CalculoFoda-1'!G124=1,'CalculoFoda-1'!H124=1,'CalculoFoda-1'!I124=1))),"sin dato: "&CalculosFoda!AF124,"")
C97: =+CalculosFoda!AF71 -> Punto de equilibrio y escala mínima exportable | D97: =IF(AND(OR('CalculoFoda-1'!H71=1,'CalculoFoda-1'!I71=1),OR('CalculoFoda-1'!H97=1,'CalculoFoda-1'!I97=1)),CalculosFoda!AF97,"") | E97: =IF(AND(OR('CalculoFoda-1'!H71=1,'CalculoFoda-1'!I71=1),OR('CalculoFoda-1'!F97=1,'CalculoFoda-1'!G97=1)),CalculosFoda!AF97,"") | F97: =IF(AND(OR('CalculoFoda-1'!F71=1,'CalculoFoda-1'!G71=1),OR('CalculoFoda-1'!H97=1,'CalculoFoda-1'!I97=1)),CalculosFoda!AF97,"") | G97: =IF(AND(OR('CalculoFoda-1'!F71=1,'CalculoFoda-1'!G71=1),OR('CalculoFoda-1'!F97=1,'CalculoFoda-1'!G97=1)),CalculosFoda!AF97,"") | H97: =IF(OR(NOT(OR('CalculoFoda-1'!F71=1,'CalculoFoda-1'!G71=1,'CalculoFoda-1'!H71=1,'CalculoFoda-1'!I71=1)),NOT(OR('CalculoFoda-1'!F97=1,'CalculoFoda-1'!G97=1,'CalculoFoda-1'!H97=1,'CalculoFoda-1'!I97=1))),"sin dato: "&CalculosFoda!AF97,"") -> sin dato: Tipo de cambio y competitividad
C98: =+CalculosFoda!AF72 -> Sistema de costos de exportación | D98: =IF(AND(OR('CalculoFoda-1'!H72=1,'CalculoFoda-1'!I72=1),OR('CalculoFoda-1'!H97=1,'CalculoFoda-1'!I97=1)),CalculosFoda!AF97,"") | E98: =IF(AND(OR('CalculoFoda-1'!H72=1,'CalculoFoda-1'!I72=1),OR('CalculoFoda-1'!F97=1,'CalculoFoda-1'!G97=1)),CalculosFoda!AF97,"") -> Tipo de cambio y competitividad | F98: =IF(AND(OR('CalculoFoda-1'!F72=1,'CalculoFoda-1'!G72=1),OR('CalculoFoda-1'!H97=1,'CalculoFoda-1'!I97=1)),CalculosFoda!AF97,"") | G98: =IF(AND(OR('CalculoFoda-1'!F72=1,'CalculoFoda-1'!G72=1),OR('CalculoFoda-1'!F97=1,'CalculoFoda-1'!G97=1)),CalculosFoda!AF97,"") | H98: =IF(OR(NOT(OR('CalculoFoda-1'!F72=1,'CalculoFoda-1'!G72=1,'CalculoFoda-1'!H72=1,'CalculoFoda-1'!I72=1)),NOT(OR('CalculoFoda-1'!F97=1,'CalculoFoda-1'!G97=1,'CalculoFoda-1'!H97=1,'CalculoFoda-1'!I97=1))),"sin dato: "&CalculosFoda!AF97,"")
D99: =IF(AND(OR('CalculoFoda-1'!H72=1,'CalculoFoda-1'!I72=1),OR('CalculoFoda-1'!H101=1,'CalculoFoda-1'!I101=1)),CalculosFoda!AF101,"") -> Impuestos, derechos de exportación y reintegros | E99: =IF(AND(OR('CalculoFoda-1'!H72=1,'CalculoFoda-1'!I72=1),OR('CalculoFoda-1'!F101=1,'CalculoFoda-1'!G101=1)),CalculosFoda!AF101,"") | F99: =IF(AND(OR('CalculoFoda-1'!F72=1,'CalculoFoda-1'!G72=1),OR('CalculoFoda-1'!H101=1,'CalculoFoda-1'!I101=1)),CalculosFoda!AF101,"") | G99: =IF(AND(OR('CalculoFoda-1'!F72=1,'CalculoFoda-1'!G72=1),OR('CalculoFoda-1'!F101=1,'CalculoFoda-1'!G101=1)),CalculosFoda!AF101,"") | H99: =IF(OR(NOT(OR('CalculoFoda-1'!F72=1,'CalculoFoda-1'!G72=1,'CalculoFoda-1'!H72=1,'CalculoFoda-1'!I72=1)),NOT(OR('CalculoFoda-1'!F101=1,'CalculoFoda-1'!G101=1,'CalculoFoda-1'!H101=1,'CalculoFoda-1'!I101=1))),"sin dato: "&CalculosFoda!AF101,"")
C100: =+CalculosFoda!AF73 -> Costo de materias primas | D100: =IF(AND(OR('CalculoFoda-1'!H73=1,'CalculoFoda-1'!I73=1),OR('CalculoFoda-1'!H137=1,'CalculoFoda-1'!I137=1)),CalculosFoda!AF137,"") | E100: =IF(AND(OR('CalculoFoda-1'!H73=1,'CalculoFoda-1'!I73=1),OR('CalculoFoda-1'!F137=1,'CalculoFoda-1'!G137=1)),CalculosFoda!AF137,"") | F100: =IF(AND(OR('CalculoFoda-1'!F73=1,'CalculoFoda-1'!G73=1),OR('CalculoFoda-1'!H137=1,'CalculoFoda-1'!I137=1)),CalculosFoda!AF137,"") | G100: =IF(AND(OR('CalculoFoda-1'!F73=1,'CalculoFoda-1'!G73=1),OR('CalculoFoda-1'!F137=1,'CalculoFoda-1'!G137=1)),CalculosFoda!AF137,"") -> Poder negociador de los proveedores | H100: =IF(OR(NOT(OR('CalculoFoda-1'!F73=1,'CalculoFoda-1'!G73=1,'CalculoFoda-1'!H73=1,'CalculoFoda-1'!I73=1)),NOT(OR('CalculoFoda-1'!F137=1,'CalculoFoda-1'!G137=1,'CalculoFoda-1'!H137=1,'CalculoFoda-1'!I137=1))),"sin dato: "&CalculosFoda!AF137,"")
D101: =IF(AND(OR('CalculoFoda-1'!H73=1,'CalculoFoda-1'!I73=1),OR('CalculoFoda-1'!H138=1,'CalculoFoda-1'!I138=1)),CalculosFoda!AF138,"") | E101: =IF(AND(OR('CalculoFoda-1'!H73=1,'CalculoFoda-1'!I73=1),OR('CalculoFoda-1'!F138=1,'CalculoFoda-1'!G138=1)),CalculosFoda!AF138,"") | F101: =IF(AND(OR('CalculoFoda-1'!F73=1,'CalculoFoda-1'!G73=1),OR('CalculoFoda-1'!H138=1,'CalculoFoda-1'!I138=1)),CalculosFoda!AF138,"") -> Disponibilidad y estacionalidad de materia prima | G101: =IF(AND(OR('CalculoFoda-1'!F73=1,'CalculoFoda-1'!G73=1),OR('CalculoFoda-1'!F138=1,'CalculoFoda-1'!G138=1)),CalculosFoda!AF138,"") | H101: =IF(OR(NOT(OR('CalculoFoda-1'!F73=1,'CalculoFoda-1'!G73=1,'CalculoFoda-1'!H73=1,'CalculoFoda-1'!I73=1)),NOT(OR('CalculoFoda-1'!F138=1,'CalculoFoda-1'!G138=1,'CalculoFoda-1'!H138=1,'CalculoFoda-1'!I138=1))),"sin dato: "&CalculosFoda!AF138,"")
D102: =IF(AND(OR('CalculoFoda-1'!H73=1,'CalculoFoda-1'!I73=1),OR('CalculoFoda-1'!H102=1,'CalculoFoda-1'!I102=1)),CalculosFoda!AF102,"") | E102: =IF(AND(OR('CalculoFoda-1'!H73=1,'CalculoFoda-1'!I73=1),OR('CalculoFoda-1'!F102=1,'CalculoFoda-1'!G102=1)),CalculosFoda!AF102,"") | F102: =IF(AND(OR('CalculoFoda-1'!F73=1,'CalculoFoda-1'!G73=1),OR('CalculoFoda-1'!H102=1,'CalculoFoda-1'!I102=1)),CalculosFoda!AF102,"") -> Precios internacionales del producto | G102: =IF(AND(OR('CalculoFoda-1'!F73=1,'CalculoFoda-1'!G73=1),OR('CalculoFoda-1'!F102=1,'CalculoFoda-1'!G102=1)),CalculosFoda!AF102,"") | H102: =IF(OR(NOT(OR('CalculoFoda-1'!F73=1,'CalculoFoda-1'!G73=1,'CalculoFoda-1'!H73=1,'CalculoFoda-1'!I73=1)),NOT(OR('CalculoFoda-1'!F102=1,'CalculoFoda-1'!G102=1,'CalculoFoda-1'!H102=1,'CalculoFoda-1'!I102=1))),"sin dato: "&CalculosFoda!AF102,"")
C103: =+CalculosFoda!AF74 -> Costos logísticos y de comercio exterior | D103: =IF(AND(OR('CalculoFoda-1'!H74=1,'CalculoFoda-1'!I74=1),OR('CalculoFoda-1'!H121=1,'CalculoFoda-1'!I121=1)),CalculosFoda!AF121,"") | E103: =IF(AND(OR('CalculoFoda-1'!H74=1,'CalculoFoda-1'!I74=1),OR('CalculoFoda-1'!F121=1,'CalculoFoda-1'!G121=1)),CalculosFoda!AF121,"") | F103: =IF(AND(OR('CalculoFoda-1'!F74=1,'CalculoFoda-1'!G74=1),OR('CalculoFoda-1'!H121=1,'CalculoFoda-1'!I121=1)),CalculosFoda!AF121,"") | G103: =IF(AND(OR('CalculoFoda-1'!F74=1,'CalculoFoda-1'!G74=1),OR('CalculoFoda-1'!F121=1,'CalculoFoda-1'!G121=1)),CalculosFoda!AF121,"") | H103: =IF(OR(NOT(OR('CalculoFoda-1'!F74=1,'CalculoFoda-1'!G74=1,'CalculoFoda-1'!H74=1,'CalculoFoda-1'!I74=1)),NOT(OR('CalculoFoda-1'!F121=1,'CalculoFoda-1'!G121=1,'CalculoFoda-1'!H121=1,'CalculoFoda-1'!I121=1))),"sin dato: "&CalculosFoda!AF121,"") -> sin dato: Costo y disponibilidad de fletes
C104: =+CalculosFoda!AF75 -> Endeudamiento | D104: =IF(AND(OR('CalculoFoda-1'!H75=1,'CalculoFoda-1'!I75=1),OR('CalculoFoda-1'!H99=1,'CalculoFoda-1'!I99=1)),CalculosFoda!AF99,"") | E104: =IF(AND(OR('CalculoFoda-1'!H75=1,'CalculoFoda-1'!I75=1),OR('CalculoFoda-1'!F99=1,'CalculoFoda-1'!G99=1)),CalculosFoda!AF99,"") -> Financiamiento y crédito para exportar | F104: =IF(AND(OR('CalculoFoda-1'!F75=1,'CalculoFoda-1'!G75=1),OR('CalculoFoda-1'!H99=1,'CalculoFoda-1'!I99=1)),CalculosFoda!AF99,"") | G104: =IF(AND(OR('CalculoFoda-1'!F75=1,'CalculoFoda-1'!G75=1),OR('CalculoFoda-1'!F99=1,'CalculoFoda-1'!G99=1)),CalculosFoda!AF99,"") | H104: =IF(OR(NOT(OR('CalculoFoda-1'!F75=1,'CalculoFoda-1'!G75=1,'CalculoFoda-1'!H75=1,'CalculoFoda-1'!I75=1)),NOT(OR('CalculoFoda-1'!F99=1,'CalculoFoda-1'!G99=1,'CalculoFoda-1'!H99=1,'CalculoFoda-1'!I99=1))),"sin dato: "&CalculosFoda!AF99,"")
B106: =+FormularioFODA!B82 -> Gestión y Compromiso Exportador | C106: =+CalculosFoda!AF78 -> Estrategia y objetivos de largo plazo | D106: =IF(AND(OR('CalculoFoda-1'!H78=1,'CalculoFoda-1'!I78=1),OR('CalculoFoda-1'!H87=1,'CalculoFoda-1'!I87=1)),CalculosFoda!AF87,"") | E106: =IF(AND(OR('CalculoFoda-1'!H78=1,'CalculoFoda-1'!I78=1),OR('CalculoFoda-1'!F87=1,'CalculoFoda-1'!G87=1)),CalculosFoda!AF87,"") | F106: =IF(AND(OR('CalculoFoda-1'!F78=1,'CalculoFoda-1'!G78=1),OR('CalculoFoda-1'!H87=1,'CalculoFoda-1'!I87=1)),CalculosFoda!AF87,"") | G106: =IF(AND(OR('CalculoFoda-1'!F78=1,'CalculoFoda-1'!G78=1),OR('CalculoFoda-1'!F87=1,'CalculoFoda-1'!G87=1)),CalculosFoda!AF87,"") -> Política de comercio exterior | H106: =IF(OR(NOT(OR('CalculoFoda-1'!F78=1,'CalculoFoda-1'!G78=1,'CalculoFoda-1'!H78=1,'CalculoFoda-1'!I78=1)),NOT(OR('CalculoFoda-1'!F87=1,'CalculoFoda-1'!G87=1,'CalculoFoda-1'!H87=1,'CalculoFoda-1'!I87=1))),"sin dato: "&CalculosFoda!AF87,"")
C107: =+CalculosFoda!AF79 -> Compromiso de la dirección | H107: variable independiente
C108: =+CalculosFoda!AF80 -> Estructura y responsable de comercio exterior | H108: variable independiente
C109: =+CalculosFoda!AF81 -> Conocimiento de la competencia internacional | D109: =IF(AND(OR('CalculoFoda-1'!H81=1,'CalculoFoda-1'!I81=1),OR('CalculoFoda-1'!H131=1,'CalculoFoda-1'!I131=1)),CalculosFoda!AF131,"") | E109: =IF(AND(OR('CalculoFoda-1'!H81=1,'CalculoFoda-1'!I81=1),OR('CalculoFoda-1'!F131=1,'CalculoFoda-1'!G131=1)),CalculosFoda!AF131,"") -> Rivalidad y competidores internacionales | F109: =IF(AND(OR('CalculoFoda-1'!F81=1,'CalculoFoda-1'!G81=1),OR('CalculoFoda-1'!H131=1,'CalculoFoda-1'!I131=1)),CalculosFoda!AF131,"") | G109: =IF(AND(OR('CalculoFoda-1'!F81=1,'CalculoFoda-1'!G81=1),OR('CalculoFoda-1'!F131=1,'CalculoFoda-1'!G131=1)),CalculosFoda!AF131,"") | H109: =IF(OR(NOT(OR('CalculoFoda-1'!F81=1,'CalculoFoda-1'!G81=1,'CalculoFoda-1'!H81=1,'CalculoFoda-1'!I81=1)),NOT(OR('CalculoFoda-1'!F131=1,'CalculoFoda-1'!G131=1,'CalculoFoda-1'!H131=1,'CalculoFoda-1'!I131=1))),"sin dato: "&CalculosFoda!AF131,"")
D110: =IF(AND(OR('CalculoFoda-1'!H81=1,'CalculoFoda-1'!I81=1),OR('CalculoFoda-1'!H132=1,'CalculoFoda-1'!I132=1)),CalculosFoda!AF132,"") -> Cambios del mercado e inteligencia comercial | E110: =IF(AND(OR('CalculoFoda-1'!H81=1,'CalculoFoda-1'!I81=1),OR('CalculoFoda-1'!F132=1,'CalculoFoda-1'!G132=1)),CalculosFoda!AF132,"") | F110: =IF(AND(OR('CalculoFoda-1'!F81=1,'CalculoFoda-1'!G81=1),OR('CalculoFoda-1'!H132=1,'CalculoFoda-1'!I132=1)),CalculosFoda!AF132,"") | G110: =IF(AND(OR('CalculoFoda-1'!F81=1,'CalculoFoda-1'!G81=1),OR('CalculoFoda-1'!F132=1,'CalculoFoda-1'!G132=1)),CalculosFoda!AF132,"") | H110: =IF(OR(NOT(OR('CalculoFoda-1'!F81=1,'CalculoFoda-1'!G81=1,'CalculoFoda-1'!H81=1,'CalculoFoda-1'!I81=1)),NOT(OR('CalculoFoda-1'!F132=1,'CalculoFoda-1'!G132=1,'CalculoFoda-1'!H132=1,'CalculoFoda-1'!I132=1))),"sin dato: "&CalculosFoda!AF132,"")
...

Sheet PART1 FODA
B2: AMBITO INTERNO | D2: Fortalezas | E2: Debilidades
B3: =+FormularioFODA!B5 -> Segmentos de Clientes | C3: IA1 | D3: =+IF(OR('CalculoFoda-1'!H3=1,'CalculoFoda-1'!I3=1),CalculosFoda!AF3,"") -> Definición de segmentos y países objetivo | E3: =+IF(OR('CalculoFoda-1'!F3=1,'CalculoFoda-1'!G3=1),CalculosFoda!AF3,"")
C4: IA2 | D4: =+IF(OR('CalculoFoda-1'!H4=1,'CalculoFoda-1'!I4=1),CalculosFoda!AF4,"") -> Conocimiento de las necesidades del cliente externo | E4: =+IF(OR('CalculoFoda-1'!F4=1,'CalculoFoda-1'!G4=1),CalculosFoda!AF4,"")
C5: IA3 | D5: =+IF(OR('CalculoFoda-1'!H5=1,'CalculoFoda-1'!I5=1),CalculosFoda!AF5,"") -> Concentración de clientes | E5: =+IF(OR('CalculoFoda-1'!F5=1,'CalculoFoda-1'!G5=1),CalculosFoda!AF5,"")
C6: IA4 | D6: =+IF(OR('CalculoFoda-1'!H6=1,'CalculoFoda-1'!I6=1),CalculosFoda!AF6,"") | E6: =+IF(OR('CalculoFoda-1'!F6=1,'CalculoFoda-1'!G6=1),CalculosFoda!AF6,"") -> Experiencia previa exportadora
C7: IA5 | D7: =+IF(OR('CalculoFoda-1'!H7=1,'CalculoFoda-1'!I7=1),CalculosFoda!AF7,"") | E7: =+IF(OR('CalculoFoda-1'!F7=1,'CalculoFoda-1'!G7=1),CalculosFoda!AF7,"") -> Acceso a información de mercados
B10: =+FormularioFODA!B12 -> Propuesta de Valor | C10: IB1 | D10: =+IF(OR('CalculoFoda-1'!H10=1,'CalculoFoda-1'!I10=1),CalculosFoda!AF10,"") | E10: =+IF(OR('CalculoFoda-1'!F10=1,'CalculoFoda-1'!G10=1),CalculosFoda!AF10,"") -> Diferenciación del producto
C11: IB2 | D11: =+IF(OR('CalculoFoda-1'!H11=1,'CalculoFoda-1'!I11=1),CalculosFoda!AF11,"") -> Adecuación a requisitos del mercado destino | E11: =+IF(OR('CalculoFoda-1'!F11=1,'CalculoFoda-1'!G11=1),CalculosFoda!AF11,"")
C12: IB3 | D12: =+IF(OR('CalculoFoda-1'!H12=1,'CalculoFoda-1'!I12=1),CalculosFoda!AF12,"") | E12: =+IF(OR('CalculoFoda-1'!F12=1,'CalculoFoda-1'!G12=1),CalculosFoda!AF12,"") -> Certificaciones y normas de producto
C13: IB4 | D13: =+IF(OR('CalculoFoda-1'!H13=1,'CalculoFoda-1'!I13=1),CalculosFoda!AF13,"") -> Competitividad de precio internacional | E13: =+IF(OR('CalculoFoda-1'!F13=1,'CalculoFoda-1'!G13=1),CalculosFoda!AF13,"")
C14: IB5 | D14: =+IF(OR('CalculoFoda-1'!H14=1,'CalculoFoda-1'!I14=1),CalculosFoda!AF14,"") -> Marca, presentación y material comercial | E14: =+IF(OR('CalculoFoda-1'!F14=1,'CalculoFoda-1'!G14=1),CalculosFoda!AF14,"")
C15: IB6 | D15: =+IF(OR('CalculoFoda-1'!H15=1,'CalculoFoda-1'!I15=1),CalculosFoda!AF15,"") | E15: =+IF(OR('CalculoFoda-1'!F15=1,'CalculoFoda-1'!G15=1),CalculosFoda!AF15,"") -> Origen e identidad regional
C16: IB7 | D16: =+IF(OR('CalculoFoda-1'!H16=1,'CalculoFoda-1'!I16=1),CalculosFoda!AF16,"") | E16: =+IF(OR('CalculoFoda-1'!F16=1,'CalculoFoda-1'!G16=1),CalculosFoda!AF16,"") -> Amplitud de línea y desarrollo de nuevos productos
B19: =+FormularioFODA!B21 -> Canales | C19: IC1 | D19: =+IF(OR('CalculoFoda-1'!H19=1,'CalculoFoda-1'!I19=1),CalculosFoda!AF19,"") -> Canales de comercialización externos | E19: =+IF(OR('CalculoFoda-1'!F19=1,'CalculoFoda-1'!G19=1),CalculosFoda!AF19,"")
C20: IC2 | D20: =+IF(OR('CalculoFoda-1'!H20=1,'CalculoFoda-1'!I20=1),CalculosFoda!AF20,"") | E20: =+IF(OR('CalculoFoda-1'!F20=1,'CalculoFoda-1'!G20=1),CalculosFoda!AF20,"") -> Presencia digital y venta online
C21: IC3 | D21: =+IF(OR('CalculoFoda-1'!H21=1,'CalculoFoda-1'!I21=1),CalculosFoda!AF21,"") | E21: =+IF(OR('CalculoFoda-1'!F21=1,'CalculoFoda-1'!G21=1),CalculosFoda!AF21,"") -> Promoción internacional
C22: IC4 | D22: =+IF(OR('CalculoFoda-1'!H22=1,'CalculoFoda-1'!I22=1),CalculosFoda!AF22,"") | E22: =+IF(OR('CalculoFoda-1'!F22=1,'CalculoFoda-1'!G22=1),CalculosFoda!AF22,"") -> Logística y embalaje de exportación
C23: IC5 | D23: =+IF(OR('CalculoFoda-1'!H23=1,'CalculoFoda-1'!I23=1),CalculosFoda!AF23,"") | E23: =+IF(OR('CalculoFoda-1'!F23=1,'CalculoFoda-1'!G23=1),CalculosFoda!AF23,"") -> Gestión documental y aduanera
B26: =+FormularioFODA!B28 -> Relación con Clientes | C26: ID1 | D26: =+IF(OR('CalculoFoda-1'!H26=1,'CalculoFoda-1'!I26=1),CalculosFoda!AF26,"") -> Atención y postventa internacional | E26: =+IF(OR('CalculoFoda-1'!F26=1,'CalculoFoda-1'!G26=1),CalculosFoda!AF26,"")
C27: ID2 | D27: =+IF(OR('CalculoFoda-1'!H27=1,'CalculoFoda-1'!I27=1),CalculosFoda!AF27,"") | E27: =+IF(OR('CalculoFoda-1'!F27=1,'CalculoFoda-1'!G27=1),CalculosFoda!AF27,"") -> Comunicación en idioma extranjero
C28: ID3 | D28: =+IF(OR('CalculoFoda-1'!H28=1,'CalculoFoda-1'!I28=1),CalculosFoda!AF28,"") | E28: =+IF(OR('CalculoFoda-1'!F28=1,'CalculoFoda-1'!G28=1),CalculosFoda!AF28,"") -> Contratos y condiciones con compradores
C29: ID4 | D29: =+IF(OR('CalculoFoda-1'!H29=1,'CalculoFoda-1'!I29=1),CalculosFoda!AF29,"") | E29: =+IF(OR('CalculoFoda-1'!F29=1,'CalculoFoda-1'!G29=1),CalculosFoda!AF29,"") -> Fidelización y recompra
C30: ID5 | D30: =+IF(OR('CalculoFoda-1'!H30=1,'CalculoFoda-1'!I30=1),CalculosFoda!AF30,"") | E30: =+IF(OR('CalculoFoda-1'!F30=1,'CalculoFoda-1'!G30=1),CalculosFoda!AF30,"") -> Gestión de reclamos y devoluciones
B33: =+FormularioFODA!B35 -> Fuentes de Ingresos | C33: IE1 | D33: =+IF(OR('CalculoFoda-1'!H33=1,'CalculoFoda-1'!I33=1),CalculosFoda!AF33,"") -> Evolución de ventas | E33: =+IF(OR('CalculoFoda-1'!F33=1,'CalculoFoda-1'!G33=1),CalculosFoda!AF33,"")
C34: IE2 | D34: =+IF(OR('CalculoFoda-1'!H34=1,'CalculoFoda-1'!I34=1),CalculosFoda!AF34,"") -> Fijación de precio de exportación | E34: =+IF(OR('CalculoFoda-1'!F34=1,'CalculoFoda-1'!G34=1),CalculosFoda!AF34,"")
C35: IE3 | D35: =+IF(OR('CalculoFoda-1'!H35=1,'CalculoFoda-1'!I35=1),CalculosFoda!AF35,"") | E35: =+IF(OR('CalculoFoda-1'!F35=1,'CalculoFoda-1'!G35=1),CalculosFoda!AF35,"")
C36: IE4 | D36: =+IF(OR('CalculoFoda-1'!H36=1,'CalculoFoda-1'!I36=1),CalculosFoda!AF36,"") -> Medios y condiciones de cobro | E36: =+IF(OR('CalculoFoda-1'!F36=1,'CalculoFoda-1'!G36=1),CalculosFoda!AF36,"")
C37: IE5 | D37: =+IF(OR('CalculoFoda-1'!H37=1,'CalculoFoda-1'!I37=1),CalculosFoda!AF37,"") -> Diversificación de ingresos | E37: =+IF(OR('CalculoFoda-1'!F37=1,'CalculoFoda-1'!G37=1),CalculosFoda!AF37,"")
C38: IE6 | D38: =+IF(OR('CalculoFoda-1'!H38=1,'CalculoFoda-1'!I38=1),CalculosFoda!AF38,"") | E38: =+IF(OR('CalculoFoda-1'!F38=1,'CalculoFoda-1'!G38=1),CalculosFoda!AF38,"") -> Resistencia a variaciones cambiarias
B41: =+FormularioFODA!B44 -> Recursos Clave | C41: IF1 | D41: =+IF(OR('CalculoFoda-1'!H41=1,'CalculoFoda-1'!I41=1),CalculosFoda!AF41,"") -> Capacidad instalada y ociosa | E41: =+IF(OR('CalculoFoda-1'!F41=1,'CalculoFoda-1'!G41=1),CalculosFoda!AF41,"")
C42: IF2 | D42: =+IF(OR('CalculoFoda-1'!H42=1,'CalculoFoda-1'!I42=1),CalculosFoda!AF42,"") -> Estado y tecnología de la maquinaria | E42: =+IF(OR('CalculoFoda-1'!F42=1,'CalculoFoda-1'!G42=1),CalculosFoda!AF42,"")
C43: IF3 | D43: =+IF(OR('CalculoFoda-1'!H43=1,'CalculoFoda-1'!I43=1),CalculosFoda!AF43,"") -> Personal calificado | E43: =+IF(OR('CalculoFoda-1'!F43=1,'CalculoFoda-1'!G43=1),CalculosFoda!AF43,"")
C44: IF4 | D44: =+IF(OR('CalculoFoda-1'!H44=1,'CalculoFoda-1'!I44=1),CalculosFoda!AF44,"") | E44: =+IF(OR('CalculoFoda-1'!F44=1,'CalculoFoda-1'!G44=1),CalculosFoda!AF44,"") -> Formación continua y capacitación en comercio exterior
C45: IF5 | D45: =+IF(OR('CalculoFoda-1'!H45=1,'CalculoFoda-1'!I45=1),CalculosFoda!AF45,"") | E45: =+IF(OR('CalculoFoda-1'!F45=1,'CalculoFoda-1'!G45=1),CalculosFoda!AF45,"") -> Capital de trabajo y capacidad financiera
C46: IF6 | D46: =+IF(OR('CalculoFoda-1'!H46=1,'CalculoFoda-1'!I46=1),CalculosFoda!AF46,"") -> Sistemas de información y gestión | E46: =+IF(OR('CalculoFoda-1'!F46=1,'CalculoFoda-1'!G46=1),CalculosFoda!AF46,"")
C47: IF7 | D47: =+IF(OR('CalculoFoda-1'!H47=1,'CalculoFoda-1'!I47=1),CalculosFoda!AF47,"") | E47: =+IF(OR('CalculoFoda-1'!F47=1,'CalculoFoda-1'!G47=1),CalculosFoda!AF47,"") -> Infraestructura, depósitos y conservación
C48: IF8 | D48: =+IF(OR('CalculoFoda-1'!H48=1,'CalculoFoda-1'!I48=1),CalculosFoda!AF48,"") -> Habilitaciones y registros oficiales | E48: =+IF(OR('CalculoFoda-1'!F48=1,'CalculoFoda-1'!G48=1),CalculosFoda!AF48,"")
B51: =+FormularioFODA!B54 -> Actividades Clave | C51: IG1 | D51: =+IF(OR('CalculoFoda-1'!H51=1,'CalculoFoda-1'!I51=1),CalculosFoda!AF51,"") | E51: =+IF(OR('CalculoFoda-1'!F51=1,'CalculoFoda-1'!G51=1),CalculosFoda!AF51,"") -> Descripción técnica y estandarización
C52: IG2 | D52: =+IF(OR('CalculoFoda-1'!H52=1,'CalculoFoda-1'!I52=1),CalculosFoda!AF52,"") -> Mantenimiento y continuidad operativa | E52: =+IF(OR('CalculoFoda-1'!F52=1,'CalculoFoda-1'!G52=1),CalculosFoda!AF52,"")
C53: IG3 | D53: =+IF(OR('CalculoFoda-1'!H53=1,'CalculoFoda-1'!I53=1),CalculosFoda!AF53,"") -> Planificación de producción y abastecimiento | E53: =+IF(OR('CalculoFoda-1'!F53=1,'CalculoFoda-1'!G53=1),CalculosFoda!AF53,"")
C54: IG4 | D54: =+IF(OR('CalculoFoda-1'!H54=1,'CalculoFoda-1'!I54=1),CalculosFoda!AF54,"") | E54: =+IF(OR('CalculoFoda-1'!F54=1,'CalculoFoda-1'!G54=1),CalculosFoda!AF54,"") -> Gestión de calidad
C55: IG5 | D55: =+IF(OR('CalculoFoda-1'!H55=1,'CalculoFoda-1'!I55=1),CalculosFoda!AF55,"") | E55: =+IF(OR('CalculoFoda-1'!F55=1,'CalculoFoda-1'!G55=1),CalculosFoda!AF55,"") -> Trazabilidad y control de stock
C56: IG6 | D56: =+IF(OR('CalculoFoda-1'!H56=1,'CalculoFoda-1'!I56=1),CalculosFoda!AF56,"") -> Cumplimiento de plazos de entrega | E56: =+IF(OR('CalculoFoda-1'!F56=1,'CalculoFoda-1'!G56=1),CalculosFoda!AF56,"")
C57: IG7 | D57: =+IF(OR('CalculoFoda-1'!H57=1,'CalculoFoda-1'!I57=1),CalculosFoda!AF57,"") | E57: =+IF(OR('CalculoFoda-1'!F57=1,'CalculoFoda-1'!G57=1),CalculosFoda!AF57,"") -> Mejora de procesos e I+D
C58: IG8 | D58: =+IF(OR('CalculoFoda-1'!H58=1,'CalculoFoda-1'!I58=1),CalculosFoda!AF58,"") | E58: =+IF(OR('CalculoFoda-1'!F58=1,'CalculoFoda-1'!G58=1),CalculosFoda!AF58,"") -> Gestión ambiental y de residuos
C59: IG9 | D59: =+IF(OR('CalculoFoda-1'!H59=1,'CalculoFoda-1'!I59=1),CalculosFoda!AF59,"") | E59: =+IF(OR('CalculoFoda-1'!F59=1,'CalculoFoda-1'!G59=1),CalculosFoda!AF59,"") -> Seguridad e higiene laboral
B62: =+FormularioFODA!B65 -> Socios Clave | C62: IH1 | D62: =+IF(OR('CalculoFoda-1'!H62=1,'CalculoFoda-1'!I62=1),CalculosFoda!AF62,"") -> Proveedores estratégicos | E62: =+IF(OR('CalculoFoda-1'!F62=1,'CalculoFoda-1'!G62=1),CalculosFoda!AF62,"")
C63: IH2 | D63: =+IF(OR('CalculoFoda-1'!H63=1,'CalculoFoda-1'!I63=1),CalculosFoda!AF63,"") | E63: =+IF(OR('CalculoFoda-1'!F63=1,'CalculoFoda-1'!G63=1),CalculosFoda!AF63,"") -> Alianzas comerciales
C64: IH3 | D64: =+IF(OR('CalculoFoda-1'!H64=1,'CalculoFoda-1'!I64=1),CalculosFoda!AF64,"") | E64: =+IF(OR('CalculoFoda-1'!F64=1,'CalculoFoda-1'!G64=1),CalculosFoda!AF64,"") -> Socios logísticos y aduaneros
C65: IH4 | D65: =+IF(OR('CalculoFoda-1'!H65=1,'CalculoFoda-1'!I65=1),CalculosFoda!AF65,"") -> Apoyo institucional | E65: =+IF(OR('CalculoFoda-1'!F65=1,'CalculoFoda-1'!G65=1),CalculosFoda!AF65,"")
C66: IH5 | D66: =+IF(OR('CalculoFoda-1'!H66=1,'CalculoFoda-1'!I66=1),CalculosFoda!AF66,"") | E66: =+IF(OR('CalculoFoda-1'!F66=1,'CalculoFoda-1'!G66=1),CalculosFoda!AF66,"") -> Socios financieros y de seguros
C67: IH6 | D67: =+IF(OR('CalculoFoda-1'!H67=1,'CalculoFoda-1'!I67=1),CalculosFoda!AF67,"") -> Tercerización y subcontratación | E67: =+IF(OR('CalculoFoda-1'!F67=1,'CalculoFoda-1'!G67=1),CalculosFoda!AF67,"")
B70: =+FormularioFODA!B73 -> Estructura de Costos | C70: II1 | D70: =+IF(OR('CalculoFoda-1'!H70=1,'CalculoFoda-1'!I70=1),CalculosFoda!AF70,"") -> Costos fijos | E70: =+IF(OR('CalculoFoda-1'!F70=1,'CalculoFoda-1'!G70=1),CalculosFoda!AF70,"")
C71: II2 | D71: =+IF(OR('CalculoFoda-1'!H71=1,'CalculoFoda-1'!I71=1),CalculosFoda!AF71,"") | E71: =+IF(OR('CalculoFoda-1'!F71=1,'CalculoFoda-1'!G71=1),CalculosFoda!AF71,"")
C72: II3 | D72: =+IF(OR('CalculoFoda-1'!H72=1,'CalculoFoda-1'!I72=1),CalculosFoda!AF72,"") -> Sistema de costos de exportación | E72: =+IF(OR('CalculoFoda-1'!F72=1,'CalculoFoda-1'!G72=1),CalculosFoda!AF72,"")
C73: II4 | D73: =+IF(OR('CalculoFoda-1'!H73=1,'CalculoFoda-1'!I73=1),CalculosFoda!AF73,"") | E73: =+IF(OR('CalculoFoda-1'!F73=1,'CalculoFoda-1'!G73=1),CalculosFoda!AF73,"") -> Costo de materias primas
C74: II5 | D74: =+IF(OR('CalculoFoda-1'!H74=1,'CalculoFoda-1'!I74=1),CalculosFoda!AF74,"") | E74: =+IF(OR('CalculoFoda-1'!F74=1,'CalculoFoda-1'!G74=1),CalculosFoda!AF74,"") -> Costos logísticos y de comercio exterior
C75: II6 | D75: =+IF(OR('CalculoFoda-1'!H75=1,'CalculoFoda-1'!I75=1),CalculosFoda!AF75,"") -> Endeudamiento | E75: =+IF(OR('CalculoFoda-1'!F75=1,'CalculoFoda-1'!G75=1),CalculosFoda!AF75,"")
B78: =+FormularioFODA!B82 -> Gestión y Compromiso Exportador | C78: IJ1 | D78: =+IF(OR('CalculoFoda-1'!H78=1,'CalculoFoda-1'!I78=1),CalculosFoda!AF78,"") | E78: =+IF(OR('CalculoFoda-1'!F78=1,'CalculoFoda-1'!G78=1),CalculosFoda!AF78,"") -> Estrategia y objetivos de largo plazo
C79: IJ2 | D79: =+IF(OR('CalculoFoda-1'!H79=1,'CalculoFoda-1'!I79=1),CalculosFoda!AF79,"") | E79: =+IF(OR('CalculoFoda-1'!F79=1,'CalculoFoda-1'!G79=1),CalculosFoda!AF79,"") -> Compromiso de la dirección
C80: IJ3 | D80: =+IF(OR('CalculoFoda-1'!H80=1,'CalculoFoda-1'!I80=1),CalculosFoda!AF80,"") | E80: =+IF(OR('CalculoFoda-1'!F80=1,'CalculoFoda-1'!G80=1),CalculosFoda!AF80,"") -> Estructura y responsable de comercio exterior
C81: IJ4 | D81: =+IF(OR('CalculoFoda-1'!H81=1,'CalculoFoda-1'!I81=1),CalculosFoda!AF81,"") -> Conocimiento de la competencia internacional | E81: =+IF(OR('CalculoFoda-1'!F81=1,'CalculoFoda-1'!G81=1),CalculosFoda!AF81,"")
C82: IJ5 | D82: =+IF(OR('CalculoFoda-1'!H82=1,'CalculoFoda-1'!I82=1),CalculosFoda!AF82,"") | E82: =+IF(OR('CalculoFoda-1'!F82=1,'CalculoFoda-1'!G82=1),CalculosFoda!AF82,"") -> Capacidad de anticipación a los cambios
C83: IJ6 | D83: =+IF(OR('CalculoFoda-1'!H83=1,'CalculoFoda-1'!I83=1),CalculosFoda!AF83,"") | E83: =+IF(OR('CalculoFoda-1'!F83=1,'CalculoFoda-1'!G83=1),CalculosFoda!AF83,"") -> Cultura empresarial y estilo de dirección
C84: IJ7 | D84: =+IF(OR('CalculoFoda-1'!H84=1,'CalculoFoda-1'!I84=1),CalculosFoda!AF84,"") | E84: =+IF(OR('CalculoFoda-1'!F84=1,'CalculoFoda-1'!G84=1),CalculosFoda!AF84,"")
B86: AMBITO EXTERNO | D86: OPORTUNIDADES | E86: AMENAZAS
B87: =+FormularioFODA!B92 -> Ámbito Político/Legal y Regulatorio | C87: EA1 | D87: =+IF(OR('CalculoFoda-1'!H87=1,'CalculoFoda-1'!I87=1),CalculosFoda!AF87,"") | E87: =+IF(OR('CalculoFoda-1'!F87=1,'CalculoFoda-1'!G87=1),CalculosFoda!AF87,"") -> Política de comercio exterior
C88: EA2 | D88: =+IF(OR('CalculoFoda-1'!H88=1,'CalculoFoda-1'!I88=1),CalculosFoda!AF88,"") | E88: =+IF(OR('CalculoFoda-1'!F88=1,'CalculoFoda-1'!G88=1),CalculosFoda!AF88,"") -> Acuerdos comerciales y preferencias arancelarias
C89: EA3 | D89: =+IF(OR('CalculoFoda-1'!H89=1,'CalculoFoda-1'!I89=1),CalculosFoda!AF89,"") -> Barreras arancelarias y técnicas del destino | E89: =+IF(OR('CalculoFoda-1'!F89=1,'CalculoFoda-1'!G89=1),CalculosFoda!AF89,"")
C90: EA4 | D90: =+IF(OR('CalculoFoda-1'!H90=1,'CalculoFoda-1'!I90=1),CalculosFoda!AF90,"") | E90: =+IF(OR('CalculoFoda-1'!F90=1,'CalculoFoda-1'!G90=1),CalculosFoda!AF90,"") -> Trámites y aduana
C91: EA5 | D91: =+IF(OR('CalculoFoda-1'!H91=1,'CalculoFoda-1'!I91=1),CalculosFoda!AF91,"") | E91: =+IF(OR('CalculoFoda-1'!F91=1,'CalculoFoda-1'!G91=1),CalculosFoda!AF91,"") -> Promoción y fomento a exportadores
C92: EA6 | D92: =+IF(OR('CalculoFoda-1'!H92=1,'CalculoFoda-1'!I92=1),CalculosFoda!AF92,"") -> Propiedad intelectual y seguridad jurídica | E92: =+IF(OR('CalculoFoda-1'!F92=1,'CalculoFoda-1'!G92=1),CalculosFoda!AF92,"")
B95: =+FormularioFODA!B100 -> Ámbito Económico/Financiero/Cambiario | C95: EB1 | D95: =+IF(OR('CalculoFoda-1'!H95=1,'CalculoFoda-1'!I95=1),CalculosFoda!AF95,"") | E95: =+IF(OR('CalculoFoda-1'!F95=1,'CalculoFoda-1'!G95=1),CalculosFoda!AF95,"") -> Crecimiento económico y ciclo
C96: EB2 | D96: =+IF(OR('CalculoFoda-1'!H96=1,'CalculoFoda-1'!I96=1),CalculosFoda!AF96,"") | E96: =+IF(OR('CalculoFoda-1'!F96=1,'CalculoFoda-1'!G96=1),CalculosFoda!AF96,"") -> Crecimiento sectorial del rubro
C97: EB3 | D97: =+IF(OR('CalculoFoda-1'!H97=1,'CalculoFoda-1'!I97=1),CalculosFoda!AF97,"") | E97: =+IF(OR('CalculoFoda-1'!F97=1,'CalculoFoda-1'!G97=1),CalculosFoda!AF97,"") -> Tipo de cambio y competitividad
C98: EB4 | D98: =+IF(OR('CalculoFoda-1'!H98=1,'CalculoFoda-1'!I98=1),CalculosFoda!AF98,"") | E98: =+IF(OR('CalculoFoda-1'!F98=1,'CalculoFoda-1'!G98=1),CalculosFoda!AF98,"")
C99: EB5 | D99: =+IF(OR('CalculoFoda-1'!H99=1,'CalculoFoda-1'!I99=1),CalculosFoda!AF99,"") | E99: =+IF(OR('CalculoFoda-1'!F99=1,'CalculoFoda-1'!G99=1),CalculosFoda!AF99,"") -> Financiamiento y crédito para exportar
C100: EB6 | D100: =+IF(OR('CalculoFoda-1'!H100=1,'CalculoFoda-1'!I100=1),CalculosFoda!AF100,"") | E100: =+IF(OR('CalculoFoda-1'!F100=1,'CalculoFoda-1'!G100=1),CalculosFoda!AF100,"") -> Cobros y acceso a divisas
C101: EB7 | D101: =+IF(OR('CalculoFoda-1'!H101=1,'CalculoFoda-1'!I101=1),CalculosFoda!AF101,"") -> Impuestos, derechos de exportación y reintegros | E101: =+IF(OR('CalculoFoda-1'!F101=1,'CalculoFoda-1'!G101=1),CalculosFoda!AF101,"")
C102: EB8 | D102: =+IF(OR('CalculoFoda-1'!H102=1,'CalculoFoda-1'!I102=1),CalculosFoda!AF102,"") -> Precios internacionales del producto | E102: =+IF(OR('CalculoFoda-1'!F102=1,'CalculoFoda-1'!G102=1),CalculosFoda!AF102,"")
B105: =+FormularioFODA!B110 -> Ámbito Sociocultural | C105: EC1 | D105: =+IF(OR('CalculoFoda-1'!H105=1,'CalculoFoda-1'!I105=1),CalculosFoda!AF105,"") | E105: =+IF(OR('CalculoFoda-1'!F105=1,'CalculoFoda-1'!G105=1),CalculosFoda!AF105,"") -> Afinidad cultural y hábitos de consumo
C106: EC2 | D106: =+IF(OR('CalculoFoda-1'!H106=1,'CalculoFoda-1'!I106=1),CalculosFoda!AF106,"") -> Idioma y cercanía cultural | E106: =+IF(OR('CalculoFoda-1'!F106=1,'CalculoFoda-1'!G106=1),CalculosFoda!AF106,"")
C107: EC3 | D107: =+IF(OR('CalculoFoda-1'!H107=1,'CalculoFoda-1'!I107=1),CalculosFoda!AF107,"") | E107: =+IF(OR('CalculoFoda-1'!F107=1,'CalculoFoda-1'!G107=1),CalculosFoda!AF107,"") -> Valoración del origen y la sustentabilidad
C108: EC4 | D108: =+IF(OR('CalculoFoda-1'!H108=1,'CalculoFoda-1'!I108=1),CalculosFoda!AF108,"") -> Formación técnica y mano de obra regional | E108: =+IF(OR('CalculoFoda-1'!F108=1,'CalculoFoda-1'!G108=1),CalculosFoda!AF108,"")
C109: EC5 | D109: =+IF(OR('CalculoFoda-1'!H109=1,'CalculoFoda-1'!I109=1),CalculosFoda!AF109,"") -> Asociativismo y cultura exportadora regional | E109: =+IF(OR('CalculoFoda-1'!F109=1,'CalculoFoda-1'!G109=1),CalculosFoda!AF109,"")
B112: =+FormularioFODA!B117 -> Ámbito Tecnológico y Digital | C112: ED1 | D112: =+IF(OR('CalculoFoda-1'!H112=1,'CalculoFoda-1'!I112=1),CalculosFoda!AF112,"") | E112: =+IF(OR('CalculoFoda-1'!F112=1,'CalculoFoda-1'!G112=1),CalculosFoda!AF112,"") -> Avances tecnológicos del sector
C113: ED2 | D113: =+IF(OR('CalculoFoda-1'!H113=1,'CalculoFoda-1'!I113=1),CalculosFoda!AF113,"") | E113: =+IF(OR('CalculoFoda-1'!F113=1,'CalculoFoda-1'!G113=1),CalculosFoda!AF113,"") -> Conectividad y plataformas de comercio electrónico
C114: ED3 | D114: =+IF(OR('CalculoFoda-1'!H114=1,'CalculoFoda-1'!I114=1),CalculosFoda!AF114,"") | E114: =+IF(OR('CalculoFoda-1'!F114=1,'CalculoFoda-1'!G114=1),CalculosFoda!AF114,"") -> Digitalización del comercio exterior
C115: ED4 | D115: =+IF(OR('CalculoFoda-1'!H115=1,'CalculoFoda-1'!I115=1),CalculosFoda!AF115,"") | E115: =+IF(OR('CalculoFoda-1'!F115=1,'CalculoFoda-1'!G115=1),CalculosFoda!AF115,"") -> Trazabilidad y certificación digital
B118: =+FormularioFODA!B123 -> Logística e Infraestructura Regional | C118: EE1 | D118: =+IF(OR('CalculoFoda-1'!H118=1,'CalculoFoda-1'!I118=1),CalculosFoda!AF118,"") | E118: =+IF(OR('CalculoFoda-1'!F118=1,'CalculoFoda-1'!G118=1),CalculosFoda!AF118,"") -> Red vial y conectividad multimodal
C119: EE2 | D119: =+IF(OR('CalculoFoda-1'!H119=1,'CalculoFoda-1'!I119=1),CalculosFoda!AF119,"") | E119: =+IF(OR('CalculoFoda-1'!F119=1,'CalculoFoda-1'!G119=1),CalculosFoda!AF119,"") -> Pasos de frontera y puentes internacionales
C120: EE3 | D120: =+IF(OR('CalculoFoda-1'!H120=1,'CalculoFoda-1'!I120=1),CalculosFoda!AF120,"") | E120: =+IF(OR('CalculoFoda-1'!F120=1,'CalculoFoda-1'!G120=1),CalculosFoda!AF120,"") -> Puertos, hidrovía y salida a ultramar
C121: EE4 | D121: =+IF(OR('CalculoFoda-1'!H121=1,'CalculoFoda-1'!I121=1),CalculosFoda!AF121,"") | E121: =+IF(OR('CalculoFoda-1'!F121=1,'CalculoFoda-1'!G121=1),CalculosFoda!AF121,"")
C122: EE5 | D122: =+IF(OR('CalculoFoda-1'!H122=1,'CalculoFoda-1'!I122=1),CalculosFoda!AF122,"") | E122: =+IF(OR('CalculoFoda-1'!F122=1,'CalculoFoda-1'!G122=1),CalculosFoda!AF122,"") -> Servicios aduaneros locales
C123: EE6 | D123: =+IF(OR('CalculoFoda-1'!H123=1,'CalculoFoda-1'!I123=1),CalculosFoda!AF123,"") | E123: =+IF(OR('CalculoFoda-1'!F123=1,'CalculoFoda-1'!G123=1),CalculosFoda!AF123,"") -> Prestadores logísticos regionales
C124: EE7 | D124: =+IF(OR('CalculoFoda-1'!H124=1,'CalculoFoda-1'!I124=1),CalculosFoda!AF124,"") | E124: =+IF(OR('CalculoFoda-1'!F124=1,'CalculoFoda-1'!G124=1),CalculosFoda!AF124,"") -> Energía y servicios públicos industriales
B127: =+FormularioFODA!B132 -> Mercado y Competencia | C127: EF1 | D127: =+IF(OR('CalculoFoda-1'!H127=1,'CalculoFoda-1'!I127=1),CalculosFoda!AF127,"") | E127: =+IF(OR('CalculoFoda-1'!F127=1,'CalculoFoda-1'!G127=1),CalculosFoda!AF127,"")
C128: EF2 | D128: =+IF(OR('CalculoFoda-1'!H128=1,'CalculoFoda-1'!I128=1),CalculosFoda!AF128,"") | E128: =+IF(OR('CalculoFoda-1'!F128=1,'CalculoFoda-1'!G128=1),CalculosFoda!AF128,"") -> Costos de cambio de los clientes externos
C129: EF3 | D129: =+IF(OR('CalculoFoda-1'!H129=1,'CalculoFoda-1'!I129=1),CalculosFoda!AF129,"") | E129: =+IF(OR('CalculoFoda-1'!F129=1,'CalculoFoda-1'!G129=1),CalculosFoda!AF129,"") -> Tamaño y crecimiento del mercado destino
C130: EF4 | D130: =+IF(OR('CalculoFoda-1'!H130=1,'CalculoFoda-1'!I130=1),CalculosFoda!AF130,"") -> Poder negociador de compradores e importadores | E130: =+IF(OR('CalculoFoda-1'!F130=1,'CalculoFoda-1'!G130=1),CalculosFoda!AF130,"")
...

Sheet ResumenFODA
C2: Situación Ideal | D2: Situación Peor | E2: Situación Actual | F2: Factores Favorables | G2: Factores Adversos
B4: AREA INTERNA - VISTO DESDE EL MODELO CANVAS
B5: =+FormularioFODA!B5 -> Segmentos de Clientes | C5: 1 | D5: -1 | E5: =+'CalculoFoda-1'!X8 -> 0.088235294 | F5: =SUM('CalculoFoda-1'!H8:I8) -> 3 | G5: =SUM('CalculoFoda-1'!F8:G8) -> 2
B6: =+FormularioFODA!B12 -> Propuesta de Valor | C6: 1 | D6: -1 | E6: =+'CalculoFoda-1'!X17 -> 0.02173913 | F6: =SUM('CalculoFoda-1'!H17:I17) -> 3 | G6: =SUM('CalculoFoda-1'!F17:G17) -> 4
B7: =+FormularioFODA!B21 -> Canales | C7: 1 | D7: -1 | E7: =+'CalculoFoda-1'!X24 -> -0.66666667 | F7: =SUM('CalculoFoda-1'!H24:I24) -> 1 | G7: =SUM('CalculoFoda-1'!F24:G24) -> 4
B8: =+FormularioFODA!B28 -> Relación con Clientes | C8: 1 | D8: -1 | E8: =+'CalculoFoda-1'!X31 -> -0.35294118 | F8: =SUM('CalculoFoda-1'!H31:I31) -> 1 | G8: =SUM('CalculoFoda-1'!F31:G31) -> 4
B9: =+FormularioFODA!B35 -> Fuentes de Ingresos | C9: 1 | D9: -1 | E9: =+'CalculoFoda-1'!X39 -> 0.35294118 | F9: =SUM('CalculoFoda-1'!H39:I39) -> 4 | G9: =SUM('CalculoFoda-1'!F39:G39) -> 1
B10: =+FormularioFODA!B44 -> Recursos Clave | C10: 1 | D10: -1 | E10: =+'CalculoFoda-1'!X49 -> 0.076923077 | F10: =SUM('CalculoFoda-1'!H49:I49) -> 5 | G10: =SUM('CalculoFoda-1'!F49:G49) -> 3
B11: =+FormularioFODA!B54 -> Actividades Clave | C11: 1 | D11: -1 | E11: =+'CalculoFoda-1'!X60 -> -0.2962963 | F11: =SUM('CalculoFoda-1'!H60:I60) -> 3 | G11: =SUM('CalculoFoda-1'!F60:G60) -> 6
B12: =+FormularioFODA!B65 -> Socios Clave | C12: 1 | D12: -1 | E12: =+'CalculoFoda-1'!X68 -> -0.047619048 | F12: =SUM('CalculoFoda-1'!H68:I68) -> 3 | G12: =SUM('CalculoFoda-1'!F68:G68) -> 3
B13: =+FormularioFODA!B73 -> Estructura de Costos | C13: 1 | D13: -1 | E13: =+'CalculoFoda-1'!X76 -> 0.175 | F13: =SUM('CalculoFoda-1'!H76:I76) -> 3 | G13: =SUM('CalculoFoda-1'!F76:G76) -> 2
B14: =+FormularioFODA!B82 -> Gestión y Compromiso Exportador | C14: 1 | D14: -1 | E14: =+'CalculoFoda-1'!X85 -> -0.54347826 | F14: =SUM('CalculoFoda-1'!H85:I85) -> 1 | G14: =SUM('CalculoFoda-1'!F85:G85) -> 5
B17: AMBIENTE EXTERNO - ENTORNO DE EXPORTACIÓN
B18: =+FormularioFODA!B92 -> Ámbito Político/Legal y Regulatorio | C18: 1 | D18: -1 | E18: =+'CalculoFoda-1'!X93 -> -0.16666667 | F18: =SUM('CalculoFoda-1'!H93:I93) -> 2 | G18: =SUM('CalculoFoda-1'!F93:G93) -> 4
B19: =+FormularioFODA!B100 -> Ámbito Económico/Financiero/Cambiario | C19: 1 | D19: -1 | E19: =+'CalculoFoda-1'!X103 -> -0.31818182 | F19: =SUM('CalculoFoda-1'!H103:I103) -> 2 | G19: =SUM('CalculoFoda-1'!F103:G103) -> 5
B20: =+FormularioFODA!B110 -> Ámbito Sociocultural | C20: 1 | D20: -1 | E20: =+'CalculoFoda-1'!X110 -> 0.46153846 | F20: =SUM('CalculoFoda-1'!H110:I110) -> 3 | G20: =SUM('CalculoFoda-1'!F110:G110) -> 2
B21: =+FormularioFODA!B117 -> Ámbito Tecnológico y Digital | C21: 1 | D21: -1 | E21: =+'CalculoFoda-1'!X116 -> -0.63636364 | F21: =SUM('CalculoFoda-1'!H116:I116) -> 0 | G21: =SUM('CalculoFoda-1'!F116:G116) -> 4
B22: =+FormularioFODA!B123 -> Logística e Infraestructura Regional | C22: 1 | D22: -1 | E22: =+'CalculoFoda-1'!X125 -> -0.45454545 | F22: =SUM('CalculoFoda-1'!H125:I125) -> 0 | G22: =SUM('CalculoFoda-1'!F125:G125) -> 6
B23: =+FormularioFODA!B132 -> Mercado y Competencia | C23: 1 | D23: -1 | E23: =+'CalculoFoda-1'!X133 -> -0.14705882 | F23: =SUM('CalculoFoda-1'!H133:I133) -> 2 | G23: =SUM('CalculoFoda-1'!F133:G133) -> 3
B24: =+FormularioFODA!B140 -> Proveedores | C24: 1 | D24: -1 | E24: =+'CalculoFoda-1'!X139 -> 0 | F24: =SUM('CalculoFoda-1'!H139:I139) -> 2 | G24: =SUM('CalculoFoda-1'!F139:G139) -> 2
B25: =+FormularioFODA!B146 -> Sustitutos de los Productos Ofrecidos | C25: 1 | D25: -1 | E25: =+'CalculoFoda-1'!X143 -> -0.14285714 | F25: =SUM('CalculoFoda-1'!H143:I143) -> 1 | G25: =SUM('CalculoFoda-1'!F143:G143) -> 1
B26: =+FormularioFODA!B150 -> Ámbito Ambiental, Sanitario y Climático | C26: 1 | D26: -1 | E26: =+'CalculoFoda-1'!X149 -> -0.25 | F26: =SUM('CalculoFoda-1'!H149:I149) -> 2 | G26: =SUM('CalculoFoda-1'!F149:G149) -> 2
B29: CUADRO DE EVOLUCIÓN INTERNA | K29: CUADRO DE EVOLUCIÓN EXTERNA
B30: Situación Actual: promedio ponderado por impacto, de -1 (muy desfavorable) a +1 (muy favorable).

Sheet VIABILIDAD
B1: DIAGNÓSTICO DE VIABILIDAD EXPORTADORA – Primer diagnóstico FODA/DAFO/SWOT
B2: Datos de la empresa (completar)
B3: Empresa | C3: Ejemplo: Aserradero Norte S.R.L. (Eldorado, Misiones)
B4: Rubro / producto
B5: Mercado(s) objetivo
B6: Relevado por (equipo)
B7: Fecha del relevamiento
B8: Perfil de la empresa
B9: =IF(C8="No exporta - evalúa iniciar","Ver LEEME §8: quién responde cada bloque y cómo leer Situación/Impacto sin actividad exportadora.","")
B10: Parámetros del diagnóstico (editables)
B11: Umbral VIABLE (puntaje promedio mínimo, escala 0-10) | C11: 7 | D11: Supuesto del diseño: 7 = 'Favorable' en promedio. 5 = 'Desfavorable' en el límite (semáforo original). Válido para ambos perfiles de empresa.
B12: Umbral VIABLE CON CONDICIONES (puntaje mínimo) | C12: 5
B14: CAPACIDAD INTERNA (Canvas) | C14: Puntaje ponderado (0-10) | D14: Semáforo | E14: Ítems evaluados | F14: Alertas (ítems < 5 pts)
B15: =+FormularioFODA!B5 -> Segmentos de Clientes | C15: =+CalculosFoda!AE8 -> 6.1763706 | D15: =IF(C15=0,"sin datos",IF(C15>10,"Excelencia",IF(C15>=8,"Bueno",IF(C15>=5,"Regular","Alarmante")))) -> Regular | E15: =COUNTIF(CalculosFoda!J3:J7,">0")&" de 5" -> 5 de 5 | F15: =COUNTIFS(CalculosFoda!AD3:AD7,"<5",CalculosFoda!AD3:AD7,">0") -> 2
B16: =+FormularioFODA!B12 -> Propuesta de Valor | C16: =+CalculosFoda!AE17 -> 6.5216239 | D16: =IF(C16=0,"sin datos",IF(C16>10,"Excelencia",IF(C16>=8,"Bueno",IF(C16>=5,"Regular","Alarmante")))) -> Regular | E16: =COUNTIF(CalculosFoda!J10:J16,">0")&" de 7" -> 7 de 7 | F16: =COUNTIFS(CalculosFoda!AD10:AD16,"<5",CalculosFoda!AD10:AD16,">0") -> 4
